Workbook
Name Domain_List: Variables!$C$2:$C$15
Name Incident: Variables!$S$2:$S$26
Name Incident_PR: Variables!$I$2:$I$5
Name OpCo_List: Variables!$A$2:$A$4
Name P_Ticket: Variables!$W$2:$W$26
Name P_Ticket_PR: Variables!$M$2:$M$4
Name Queue_List: Variables!$E$2:$E$42
Name Resolution_List: Variables!$Q$2:$Q$5
Name RFS: Variables!$U$2:$U$13
Name RFS_PR: Variables!$K$2:$K$2
Name Status_List: Variables!$O$2:$O$5
Name SubCategory: Variables!$Y$2:$Y$34
Name Type_List: Variables!$G$2:$G$4
Name UKBankHolidays: Variables!$A$13:$A$21

Sheet MSR
A1: Date Picker | B1: 46235 | C1: 46265
A3: Queue Name | B3: Op Co | C3: Domain | D3: P1 Raised | E3: P1 Actioned | F3: P1 Backlogs | G3: P2 Raised | H3: P2 Actioned | I3: P2 Backlogs | J3: P3 Raised | K3: P3 Actioned | L3: P3 Backlogs | M3: P4 Raised | N3: P4 Actioned | O3: P4 Backlogs | P3: RFS Raised | Q3: RFS Actioned | R3: RFS Backlogs | S3: P_Ticket Raised | T3: P_Ticket Actioned | U3: Changes Implemented | V3: Changes Successful | W3: High P_Ticket Raised | X3: High P_Ticket Actioned
A4: APPSUP_SIPLIVE APPSUP_SIPENVHEALTH APPSUP_SIPTOOLS APPSUP_TTPTESTLAB APPSUP_DEVICESLIVE | B4: BA | C4: SIP | D4: =COUNTIFS( SIP!$D:$D,"Incident", SIP!$G:$G,1, SIP!$C:$C,"SIP", SIP!$U:$U,"NO", SIP!$L:$L,">="&$B$1, SIP!$L:$L,"<"&$C$1+1 ) -> 0 | E4: =SUM( COUNTIFS( SIP!$D:$D,"Incident", SIP!$G:$G,1, SIP!$C:$C,"SIP", SIP!$I:$I,"Closed", SIP!$U:$U,"NO", SIP!$N:$N,">="&$B$1, SIP!$N:$N,"<"&$C$1+1 ), COUNTIFS( SIP!$D:$D,"Incident", SIP!$G:$G,1, SIP!$C:$C,"SIP", SIP!$I:$I,"Triaged", SIP!$U:$U,"NO", SIP!$N:$N,">="&$B$1, SIP!$N:$N,"<"&$C$1+1 ) ) -> 0 | F4: =COUNTIFS( SIP!$C:$C,"SIP", SIP!$D:$D,"Incident", SIP!$G:$G,1, SIP!$U:$U,"<>YES", SIP!$K:$K,"<"&$B$1, SIP!$N:$N,"" ) + COUNTIFS( SIP!$C:$C,"SIP", SIP!$D:$D,"Incident", SIP!$G:$G,1, SIP!$U:$U,"<>YES", SIP!$K:$K,"<"&$B$1, SIP!$N:$N,">="&$B$1 ) + COUNTIFS( SIP!$C:$C,"SIP", SIP!$D:$D,"Incident", SIP!$G:$G,1, SIP!$U:$U,"<>YES", SIP!$K:$K,">="&$B$1, SIP!$K:$K,"<"&$C$1+1 ) - COUNTIFS( SIP!$C:$C,"SIP", SIP!$D:$D,"Incident", SIP!$G:$G,1, SIP!$U:$U,"<>YES", SIP!$I:$I,"Closed", SIP!$N:$N,">="&$B$1, SIP!$N:$N,"<"&$C$1+1 ) - COUNTIFS( SIP!$C:$C,"SIP", SIP!$D:$D,"Incident", SIP!$G:$G,1, SIP!$U:$U,"<>YES", SIP!$I:$I,"Triaged", SIP!$N:$N,">="&$B$1, SIP!$N:$N,"<"&$C$1+1 ) -> 0 | G4: =COUNTIFS( SIP!$D:$D,"Incident", SIP!$G:$G,2, SIP!$C:$C,"SIP", SIP!$U:$U,"NO", SIP!$L:$L,">="&$B$1, SIP!$L:$L,"<"&$C$1+1 ) -> 0 | H4: =SUM( COUNTIFS( SIP!$D:$D,"Incident", SIP!$G:$G,2, SIP!$C:$C,"SIP", SIP!$I:$I,"Closed", SIP!$U:$U,"NO", SIP!$N:$N,">="&$B$1, SIP!$N:$N,"<"&$C$1+1 ), COUNTIFS( SIP!$D:$D,"Incident", SIP!$G:$G,2, SIP!$C:$C,"SIP", SIP!$I:$I,"Triaged", SIP!$U:$U,"NO", SIP!$N:$N,">="&$B$1, SIP!$N:$N,"<"&$C$1+1 ) ) -> 0 | I4: =COUNTIFS( SIP!$C:$C,"SIP", SIP!$D:$D,"Incident", SIP!$G:$G,2, SIP!$U:$U,"<>YES", SIP!$K:$K,"<"&$B$1, SIP!$N:$N,"" ) + COUNTIFS( SIP!$C:$C,"SIP", SIP!$D:$D,"Incident", SIP!$G:$G,2, SIP!$U:$U,"<>YES", SIP!$K:$K,"<"&$B$1, SIP!$N:$N,">="&$B$1 ) + COUNTIFS( SIP!$C:$C,"SIP", SIP!$D:$D,"Incident", SIP!$G:$G,2, SIP!$U:$U,"<>YES", SIP!$K:$K,">="&$B$1, SIP!$K:$K,"<"&$C$1+1 ) - COUNTIFS( SIP!$C:$C,"SIP", SIP!$D:$D,"Incident", SIP!$G:$G,2, SIP!$U:$U,"<>YES", SIP!$I:$I,"Closed", SIP!$N:$N,">="&$B$1, SIP!$N:$N,"<"&$C$1+1 ) - COUNTIFS( SIP!$C:$C,"SIP", SIP!$D:$D,"Incident", SIP!$G:$G,2, SIP!$U:$U,"<>YES", SIP!$I:$I,"Triaged", SIP!$N:$N,">="&$B$1, SIP!$N:$N,"<"&$C$1+1 ) -> 0 | J4: =COUNTIFS( SIP!$D:$D,"Incident", SIP!$G:$G,3, SIP!$C:$C,"SIP", SIP!$U:$U,"NO", SIP!$L:$L,">="&$B$1, SIP!$L:$L,"<"&$C$1+1 ) -> 0 | K4: =SUM( COUNTIFS( SIP!$D:$D,"Incident", SIP!$G:$G,3, SIP!$C:$C,"SIP", SIP!$I:$I,"Closed", SIP!$U:$U,"NO", SIP!$N:$N,">="&$B$1, SIP!$N:$N,"<"&$C$1+1 ), COUNTIFS( SIP!$D:$D,"Incident", SIP!$G:$G,3, SIP!$C:$C,"SIP", SIP!$I:$I,"Triaged", SIP!$U:$U,"NO", SIP!$N:$N,">="&$B$1, SIP!$N:$N,"<"&$C$1+1 ) ) -> 0 | L4: =COUNTIFS( SIP!$C:$C,"SIP", SIP!$D:$D,"Incident", SIP!$G:$G,3, SIP!$U:$U,"<>YES", SIP!$K:$K,"<"&$B$1, SIP!$N:$N,"" ) + COUNTIFS( SIP!$C:$C,"SIP", SIP!$D:$D,"Incident", SIP!$G:$G,3, SIP!$U:$U,"<>YES", SIP!$K:$K,"<"&$B$1, SIP!$N:$N,">="&$B$1 ) + COUNTIFS( SIP!$C:$C,"SIP", SIP!$D:$D,"Incident", SIP!$G:$G,3, SIP!$U:$U,"<>YES", SIP!$K:$K,">="&$B$1, SIP!$K:$K,"<"&$C$1+1 ) - COUNTIFS( SIP!$C:$C,"SIP", SIP!$D:$D,"Incident", SIP!$G:$G,3, SIP!$U:$U,"<>YES", SIP!$I:$I,"Closed", SIP!$N:$N,">="&$B$1, SIP!$N:$N,"<"&$C$1+1 ) - COUNTIFS( SIP!$C:$C,"SIP", SIP!$D:$D,"Incident", SIP!$G:$G,3, SIP!$U:$U,"<>YES", SIP!$I:$I,"Triaged", SIP!$N:$N,">="&$B$1, SIP!$N:$N,"<"&$C$1+1 ) -> 211 | M4: =COUNTIFS( SIP!$D:$D,"Incident", SIP!$G:$G,4, SIP!$C:$C,"SIP", SIP!$U:$U,"NO", SIP!$L:$L,">="&$B$1, SIP!$L:$L,"<"&$C$1+1 ) -> 0 | N4: =SUM( COUNTIFS( SIP!$D:$D,"Incident", SIP!$G:$G,4, SIP!$C:$C,"SIP", SIP!$I:$I,"Closed", SIP!$U:$U,"NO", SIP!$N:$N,">="&$B$1, SIP!$N:$N,"<"&$C$1+1 ), COUNTIFS( SIP!$D:$D,"Incident", SIP!$G:$G,4, SIP!$C:$C,"SIP", SIP!$I:$I,"Triaged", SIP!$U:$U,"NO", SIP!$N:$N,">="&$B$1, SIP!$N:$N,"<"&$C$1+1 ) ) -> 0 | O4: =COUNTIFS( SIP!$C:$C,"SIP", SIP!$D:$D,"Incident", SIP!$G:$G,4, SIP!$U:$U,"<>YES", SIP!$K:$K,"<"&$B$1, SIP!$N:$N,"" ) + COUNTIFS( SIP!$C:$C,"SIP", SIP!$D:$D,"Incident", SIP!$G:$G,4, SIP!$U:$U,"<>YES", SIP!$K:$K,"<"&$B$1, SIP!$N:$N,">="&$B$1 ) + COUNTIFS( SIP!$C:$C,"SIP", SIP!$D:$D,"Incident", SIP!$G:$G,4, SIP!$U:$U,"<>YES", SIP!$K:$K,">="&$B$1, SIP!$K:$K,"<"&$C$1+1 ) - COUNTIFS( SIP!$C:$C,"SIP", SIP!$D:$D,"Incident", SIP!$G:$G,4, SIP!$U:$U,"<>YES", SIP!$I:$I,"Closed", SIP!$N:$N,">="&$B$1, SIP!$N:$N,"<"&$C$1+1 ) - COUNTIFS( SIP!$C:$C,"SIP", SIP!$D:$D,"Incident", SIP!$G:$G,4, SIP!$U:$U,"<>YES", SIP!$I:$I,"Triaged", SIP!$N:$N,">="&$B$1, SIP!$N:$N,"<"&$C$1+1 ) -> 67 | P4: =COUNTIFS( SIP!$D:$D,"RFS", SIP!$C:$C,"SIP", SIP!$U:$U,"NO", SIP!$L:$L,">="&$B$1, SIP!$L:$L,"<"&$C$1+1 ) -> 0 | Q4: =SUM( COUNTIFS( SIP!$D:$D,"RFS", SIP!$C:$C,"SIP", SIP!$I:$I,"Closed", SIP!$U:$U,"NO", SIP!$N:$N,">="&$B$1, SIP!$N:$N,"<"&$C$1+1 ), COUNTIFS( SIP!$D:$D,"RFS", SIP!$C:$C,"SIP", SIP!$I:$I,"Triaged", SIP!$U:$U,"NO", SIP!$N:$N,">="&$B$1, SIP!$N:$N,"<"&$C$1+1 ) ) -> 0 | R4: =COUNTIFS( SIP!$D:$D,"RFS", SIP!$C:$C,"SIP", SIP!$U:$U,"<>YES", SIP!$K:$K,"<"&$B$1, SIP!$N:$N,"" ) + COUNTIFS( SIP!$D:$D,"RFS", SIP!$C:$C,"SIP", SIP!$U:$U,"<>YES", SIP!$K:$K,"<"&$B$1, SIP!$N:$N,">="&$B$1 ) + COUNTIFS( SIP!$D:$D,"RFS", SIP!$C:$C,"SIP", SIP!$U:$U,"<>YES", SIP!$K:$K,">="&$B$1, SIP!$K:$K,"<"&$C$1+1 ) - COUNTIFS( SIP!$D:$D,"RFS", SIP!$C:$C,"SIP", SIP!$I:$I,"Closed", SIP!$U:$U,"<>YES", SIP!$N:$N,">="&$B$1, SIP!$N:$N,"<"&$C$1+1 ) - COUNTIFS( SIP!$D:$D,"RFS", SIP!$C:$C,"SIP", SIP!$I:$I,"Triaged", SIP!$U:$U,"<>YES", SIP!$N:$N,">="&$B$1, SIP!$N:$N,"<"&$C$1+1 ) -> 172 | S4: =SUM( COUNTIFS( SIP!$D:$D,"P_Ticket", SIP!$G:$G,"Low", SIP!$C:$C,"SIP", SIP!$U:$U,"NO", SIP!$L:$L,">="&$B$1, SIP!$L:$L,"<"&$C$1+1 ), COUNTIFS( SIP!$D:$D,"P_Ticket", SIP!$G:$G,"Medium", SIP!$C:$C,"SIP", SIP!$U:$U,"NO", SIP!$L:$L,">="&$B$1, SIP!$L:$L,"<"&$C$1+1 ), COUNTIFS( SIP!$D:$D,"P_Ticket", SIP!$G:$G,"High", SIP!$C:$C,"SIP", SIP!$U:$U,"NO", SIP!$L:$L,">="&$B$1, SIP!$L:$L,"<"&$C$1+1 ) ) -> 0 | T4: =SUM(COUNTIFS(SIP!$D:$D,"P_Ticket",SIP!$G:$G,"Low",SIP!$C:$C,"SIP",SIP!$I:$I,"Closed",SIP!$U:$U,"NO",SIP!$N:$N,"<"&$C$1+1,SIP!$N:$N,">="&$B$1),COUNTIFS(SIP!$D:$D,"P_Ticket",SIP!$G:$G,"Medium",SIP!$C:$C,"SIP",SIP!$I:$I,"Closed",SIP!$U:$U,"NO",SIP!$N:$N,"<"&$C$1+1,SIP!$N:$N,">="&$B$1),COUNTIFS(SIP!$D:$D,"P_Ticket",SIP!$G:$G,"High",SIP!$C:$C,"SIP",SIP!$I:$I,"Closed",SIP!$U:$U,"NO",SIP!$N:$N,"<"&$C$1+1,SIP!$N:$N,">="&$B$1),COUNTIFS(SIP!$D:$D,"P_Ticket",SIP!$G:$G,"Low",SIP!$C:$C,"SIP",SIP!$I:$I,"Triaged",SIP!$U:$U,"NO",SIP!$N:$N,"<"&$C$1+1,SIP!$N:$N,">="&$B$1),COUNTIFS(SIP!$D:$D,"P_Ticket",SIP!$G:$G,"Medium",SIP!$C:$C,"SIP",SIP!$I:$I,"Triaged",SIP!$U:$U,"NO",SIP!$N:$N,"<"&$C$1+1,SIP!$N:$N,">="&$B$1),COUNTIFS(SIP!$D:$D,"P_Ticket",SIP!$G:$G,"High",SIP!$C:$C,"SIP",SIP!$I:$I,"Triaged",SIP!$U:$U,"NO",SIP!$N:$N,"<"&$C$1+1,SIP!$N:$N,">="&$B$1)) -> 0 | W4: =COUNTIFS( SIP!$D:$D,"P_Ticket", SIP!$G:$G,"High", SIP!$C:$C,"SIP", SIP!$U:$U,"NO", SIP!$L:$L,">="&$B$1, SIP!$L:$L,"<"&$C$1+1 ) -> 0 | X4: =SUM( COUNTIFS( SIP!$D:$D,"P_Ticket", SIP!$C:$C,"SIP", SIP!$G:$G,"High", SIP!$I:$I,"Closed", SIP!$U:$U,"NO", SIP!$N:$N,"<"&$C$1+1, SIP!$N:$N,">="&$B$1 ), COUNTIFS( SIP!$D:$D,"P_Ticket", SIP!$C:$C,"SIP", SIP!$G:$G,"High", SIP!$I:$I,"Triaged", SIP!$U:$U,"NO", SIP!$N:$N,"<"&$C$1+1, SIP!$N:$N,">="&$B$1 ) ) -> 0
A5: APPSUP_SPOMGSV APPSUP_POWERAPPS | B5: BA | C5: SharePoint | D5: =COUNTIFS( 'BA BackOffice'!$D:$D,"Incident", 'BA BackOffice'!$G:$G,1, 'BA BackOffice'!$C:$C,"SharePoint", 'BA BackOffice'!$U:$U,"NO", 'BA BackOffice'!$L:$L,">="&$B$1, 'BA BackOffice'!$L:$L,"<"&$C$1+1 ) -> 0 | E5: =SUM( COUNTIFS( 'BA BackOffice'!$D:$D,"Incident", 'BA BackOffice'!$C:$C,"SharePoint", 'BA BackOffice'!$G:$G,1, 'BA BackOffice'!$I:$I,"Closed", 'BA BackOffice'!$U:$U,"NO", 'BA BackOffice'!$N:$N,">="&$B$1, 'BA BackOffice'!$N:$N,"<"&$C$1+1 ), COUNTIFS( 'BA BackOffice'!$D:$D,"Incident", 'BA BackOffice'!$C:$C,"SharePoint", 'BA BackOffice'!$G:$G,1, 'BA BackOffice'!$I:$I,"Triaged", 'BA BackOffice'!$U:$U,"NO", 'BA BackOffice'!$N:$N,">="&$B$1, 'BA BackOffice'!$N:$N,"<"&$C$1+1 ) ) -> 0 | F5: =COUNTIFS( 'BA BackOffice'!$C:$C,"SharePoint", 'BA BackOffice'!$D:$D,"Incident", 'BA BackOffice'!$G:$G,1, 'BA BackOffice'!$U:$U,"<>YES", 'BA BackOffice'!$K:$K,"<"&$B$1, 'BA BackOffice'!$N:$N,"" ) + COUNTIFS( 'BA BackOffice'!$C:$C,"SharePoint", 'BA BackOffice'!$D:$D,"Incident", 'BA BackOffice'!$G:$G,1, 'BA BackOffice'!$U:$U,"<>YES", 'BA BackOffice'!$K:$K,"<"&$B$1, 'BA BackOffice'!$N:$N,">="&$B$1 ) + COUNTIFS( 'BA BackOffice'!$C:$C,"SharePoint", 'BA BackOffice'!$D:$D,"Incident", 'BA BackOffice'!$G:$G,1, 'BA BackOffice'!$U:$U,"<>YES", 'BA BackOffice'!$K:$K,">="&$B$1, 'BA BackOffice'!$K:$K,"<"&$C$1+1 ) - COUNTIFS( 'BA BackOffice'!$C:$C,"SharePoint", 'BA BackOffice'!$D:$D,"Incident", 'BA BackOffice'!$G:$G,1, 'BA BackOffice'!$U:$U,"<>YES", 'BA BackOffice'!$I:$I,"Closed", 'BA BackOffice'!$N:$N,">="&$B$1, 'BA BackOffice'!$N:$N,"<"&$C$1+1 ) - COUNTIFS( 'BA BackOffice'!$C:$C,"SharePoint", 'BA BackOffice'!$D:$D,"Incident", 'BA BackOffice'!$G:$G,1, 'BA BackOffice'!$U:$U,"<>YES", 'BA BackOffice'!$I:$I,"Triaged", 'BA BackOffice'!$N:$N,">="&$B$1, 'BA BackOffice'!$N:$N,"<"&$C$1+1 ) -> 0 | G5: =COUNTIFS( 'BA BackOffice'!$D:$D,"Incident", 'BA BackOffice'!$G:$G,2, 'BA BackOffice'!$C:$C,"SharePoint", 'BA BackOffice'!$U:$U,"NO", 'BA BackOffice'!$L:$L,">="&$B$1, 'BA BackOffice'!$L:$L,"<"&$C$1+1 ) -> 0 | H5: =SUM( COUNTIFS( 'BA BackOffice'!$D:$D,"Incident", 'BA BackOffice'!$C:$C,"SharePoint", 'BA BackOffice'!$G:$G,2, 'BA BackOffice'!$I:$I,"Closed", 'BA BackOffice'!$U:$U,"NO", 'BA BackOffice'!$N:$N,">="&$B$1, 'BA BackOffice'!$N:$N,"<"&$C$1+1 ), COUNTIFS( 'BA BackOffice'!$D:$D,"Incident", 'BA BackOffice'!$C:$C,"SharePoint", 'BA BackOffice'!$G:$G,2, 'BA BackOffice'!$I:$I,"Triaged", 'BA BackOffice'!$U:$U,"NO", 'BA BackOffice'!$N:$N,">="&$B$1, 'BA BackOffice'!$N:$N,"<"&$C$1+1 ) ) -> 0 | I5: =COUNTIFS( 'BA BackOffice'!$C:$C,"SharePoint", 'BA BackOffice'!$D:$D,"Incident", 'BA BackOffice'!$G:$G,2, 'BA BackOffice'!$U:$U,"<>YES", 'BA BackOffice'!$K:$K,"<"&$B$1, 'BA BackOffice'!$N:$N,"" ) + COUNTIFS( 'BA BackOffice'!$C:$C,"SharePoint", 'BA BackOffice'!$D:$D,"Incident", 'BA BackOffice'!$G:$G,2, 'BA BackOffice'!$U:$U,"<>YES", 'BA BackOffice'!$K:$K,"<"&$B$1, 'BA BackOffice'!$N:$N,">="&$B$1 ) + COUNTIFS( 'BA BackOffice'!$C:$C,"SharePoint", 'BA BackOffice'!$D:$D,"Incident", 'BA BackOffice'!$G:$G,2, 'BA BackOffice'!$U:$U,"<>YES", 'BA BackOffice'!$K:$K,">="&$B$1, 'BA BackOffice'!$K:$K,"<"&$C$1+1 ) - COUNTIFS( 'BA BackOffice'!$C:$C,"SharePoint", 'BA BackOffice'!$D:$D,"Incident", 'BA BackOffice'!$G:$G,2, 'BA BackOffice'!$U:$U,"<>YES", 'BA BackOffice'!$I:$I,"Closed", 'BA BackOffice'!$N:$N,">="&$B$1, 'BA BackOffice'!$N:$N,"<"&$C$1+1 ) - COUNTIFS( 'BA BackOffice'!$C:$C,"SharePoint", 'BA BackOffice'!$D:$D,"Incident", 'BA BackOffice'!$G:$G,2, 'BA BackOffice'!$U:$U,"<>YES", 'BA BackOffice'!$I:$I,"Triaged", 'BA BackOffice'!$N:$N,">="&$B$1, 'BA BackOffice'!$N:$N,"<"&$C$1+1 ) -> 0 | J5: =COUNTIFS( 'BA BackOffice'!$D:$D,"Incident", 'BA BackOffice'!$G:$G,3, 'BA BackOffice'!$C:$C,"SharePoint", 'BA BackOffice'!$U:$U,"NO", 'BA BackOffice'!$L:$L,">="&$B$1, 'BA BackOffice'!$L:$L,"<"&$C$1+1 ) -> 1 | K5: =SUM( COUNTIFS( 'BA BackOffice'!$D:$D,"Incident", 'BA BackOffice'!$C:$C,"SharePoint", 'BA BackOffice'!$G:$G,3, 'BA BackOffice'!$I:$I,"Closed", 'BA BackOffice'!$U:$U,"NO", 'BA BackOffice'!$N:$N,">="&$B$1, 'BA BackOffice'!$N:$N,"<"&$C$1+1 ), COUNTIFS( 'BA BackOffice'!$D:$D,"Incident", 'BA BackOffice'!$C:$C,"SharePoint", 'BA BackOffice'!$G:$G,3, 'BA BackOffice'!$I:$I,"Triaged", 'BA BackOffice'!$U:$U,"NO", 'BA BackOffice'!$N:$N,">="&$B$1, 'BA BackOffice'!$N:$N,"<"&$C$1+1 ) ) -> 1 | L5: =COUNTIFS( 'BA BackOffice'!$C:$C,"SharePoint", 'BA BackOffice'!$D:$D,"Incident", 'BA BackOffice'!$G:$G,3, 'BA BackOffice'!$U:$U,"<>YES", 'BA BackOffice'!$K:$K,"<"&$B$1, 'BA BackOffice'!$N:$N,"" ) + COUNTIFS( 'BA BackOffice'!$C:$C,"SharePoint", 'BA BackOffice'!$D:$D,"Incident", 'BA BackOffice'!$G:$G,3, 'BA BackOffice'!$U:$U,"<>YES", 'BA BackOffice'!$K:$K,"<"&$B$1, 'BA BackOffice'!$N:$N,">="&$B$1 ) + COUNTIFS( 'BA BackOffice'!$C:$C,"SharePoint", 'BA BackOffice'!$D:$D,"Incident", 'BA BackOffice'!$G:$G,3, 'BA BackOffice'!$U:$U,"<>YES", 'BA BackOffice'!$K:$K,">="&$B$1, 'BA BackOffice'!$K:$K,"<"&$C$1+1 ) - COUNTIFS( 'BA BackOffice'!$C:$C,"SharePoint", 'BA BackOffice'!$D:$D,"Incident", 'BA BackOffice'!$G:$G,3, 'BA BackOffice'!$U:$U,"<>YES", 'BA BackOffice'!$I:$I,"Closed", 'BA BackOffice'!$N:$N,">="&$B$1, 'BA BackOffice'!$N:$N,"<"&$C$1+1 ) - COUNTIFS( 'BA BackOffice'!$C:$C,"SharePoint", 'BA BackOffice'!$D:$D,"Incident", 'BA BackOffice'!$G:$G,3, 'BA BackOffice'!$U:$U,"<>YES", 'BA BackOffice'!$I:$I,"Triaged", 'BA BackOffice'!$N:$N,">="&$B$1, 'BA BackOffice'!$N:$N,"<"&$C$1+1 ) -> 0 | M5: =COUNTIFS( 'BA BackOffice'!$D:$D,"Incident", 'BA BackOffice'!$G:$G,4, 'BA BackOffice'!$C:$C,"SharePoint", 'BA BackOffice'!$U:$U,"NO", 'BA BackOffice'!$L:$L,">="&$B$1, 'BA BackOffice'!$L:$L,"<"&$C$1+1 ) -> 6 | N5: =SUM( COUNTIFS( 'BA BackOffice'!$D:$D,"Incident", 'BA BackOffice'!$C:$C,"SharePoint", 'BA BackOffice'!$G:$G,4, 'BA BackOffice'!$I:$I,"Closed", 'BA BackOffice'!$U:$U,"NO", 'BA BackOffice'!$N:$N,">="&$B$1, 'BA BackOffice'!$N:$N,"<"&$C$1+1 ), COUNTIFS( 'BA BackOffice'!$D:$D,"Incident", 'BA BackOffice'!$C:$C,"SharePoint", 'BA BackOffice'!$G:$G,4, 'BA BackOffice'!$I:$I,"Triaged", 'BA BackOffice'!$U:$U,"NO", 'BA BackOffice'!$N:$N,">="&$B$1, 'BA BackOffice'!$N:$N,"<"&$C$1+1 ) ) -> 6 | O5: =COUNTIFS( 'BA BackOffice'!$C:$C,"SharePoint", 'BA BackOffice'!$D:$D,"Incident", 'BA BackOffice'!$G:$G,4, 'BA BackOffice'!$U:$U,"<>YES", 'BA BackOffice'!$K:$K,"<"&$B$1, 'BA BackOffice'!$N:$N,"" ) + COUNTIFS( 'BA BackOffice'!$C:$C,"SharePoint", 'BA BackOffice'!$D:$D,"Incident", 'BA BackOffice'!$G:$G,4, 'BA BackOffice'!$U:$U,"<>YES", 'BA BackOffice'!$K:$K,"<"&$B$1, 'BA BackOffice'!$N:$N,">="&$B$1 ) + COUNTIFS( 'BA BackOffice'!$C:$C,"SharePoint", 'BA BackOffice'!$D:$D,"Incident", 'BA BackOffice'!$G:$G,4, 'BA BackOffice'!$U:$U,"<>YES", 'BA BackOffice'!$K:$K,">="&$B$1, 'BA BackOffice'!$K:$K,"<"&$C$1+1 ) - COUNTIFS( 'BA BackOffice'!$C:$C,"SharePoint", 'BA BackOffice'!$D:$D,"Incident", 'BA BackOffice'!$G:$G,4, 'BA BackOffice'!$U:$U,"<>YES", 'BA BackOffice'!$I:$I,"Closed", 'BA BackOffice'!$N:$N,">="&$B$1, 'BA BackOffice'!$N:$N,"<"&$C$1+1 ) - COUNTIFS( 'BA BackOffice'!$C:$C,"SharePoint", 'BA BackOffice'!$D:$D,"Incident", 'BA BackOffice'!$G:$G,4, 'BA BackOffice'!$U:$U,"<>YES", 'BA BackOffice'!$I:$I,"Triaged", 'BA BackOffice'!$N:$N,">="&$B$1, 'BA BackOffice'!$N:$N,"<"&$C$1+1 ) -> 1 | P5: =COUNTIFS( 'BA BackOffice'!$D:$D,"RFS", 'BA BackOffice'!$C:$C,"SharePoint", 'BA BackOffice'!$U:$U,"No", 'BA BackOffice'!$L:$L,">="&$B$1, 'BA BackOffice'!$L:$L,"<"&$C$1+1 ) -> 0 | Q5: =SUM( COUNTIFS( 'BA BackOffice'!$D:$D,"RFS", 'BA BackOffice'!$C:$C,"SharePoint", 'BA BackOffice'!$I:$I,"Closed", 'BA BackOffice'!$U:$U,"NO", 'BA BackOffice'!$N:$N,">="&$B$1, 'BA BackOffice'!$N:$N,"<"&$C$1+1 ), COUNTIFS( 'BA BackOffice'!$D:$D,"RFS", 'BA BackOffice'!$C:$C,"SharePoint", 'BA BackOffice'!$I:$I,"Triaged", 'BA BackOffice'!$U:$U,"NO", 'BA BackOffice'!$N:$N,">="&$B$1, 'BA BackOffice'!$N:$N,"<"&$C$1+1 ) ) -> 7 | R5: =COUNTIFS( 'BA BackOffice'!$D:$D,"RFS", 'BA BackOffice'!$C:$C,"SharePoint", 'BA BackOffice'!$U:$U,"<>YES", 'BA BackOffice'!$K:$K,"<"&$B$1, 'BA BackOffice'!$N:$N,"" ) + COUNTIFS( 'BA BackOffice'!$D:$D,"RFS", 'BA BackOffice'!$C:$C,"SharePoint", 'BA BackOffice'!$U:$U,"<>YES", 'BA BackOffice'!$K:$K,"<"&$B$1, 'BA BackOffice'!$N:$N,">="&$B$1 ) + COUNTIFS( 'BA BackOffice'!$D:$D,"RFS", 'BA BackOffice'!$C:$C,"SharePoint", 'BA BackOffice'!$U:$U,"<>YES", 'BA BackOffice'!$K:$K,">="&$B$1, 'BA BackOffice'!$K:$K,"<"&$C$1+1 ) - COUNTIFS( 'BA BackOffice'!$D:$D,"RFS", 'BA BackOffice'!$C:$C,"SharePoint", 'BA BackOffice'!$I:$I,"Closed", 'BA BackOffice'!$U:$U,"<>YES", 'BA BackOffice'!$N:$N,">="&$B$1, 'BA BackOffice'!$N:$N,"<"&$C$1+1 ) - COUNTIFS( 'BA BackOffice'!$D:$D,"RFS", 'BA BackOffice'!$C:$C,"SharePoint", 'BA BackOffice'!$I:$I,"Triaged", 'BA BackOffice'!$U:$U,"<>YES", 'BA BackOffice'!$N:$N,">="&$B$1, 'BA BackOffice'!$N:$N,"<"&$C$1+1 ) -> 3 | S5: =SUM( COUNTIFS( 'BA BackOffice'!$D:$D,"P_Ticket", 'BA BackOffice'!$G:$G,"Low", 'BA BackOffice'!$C:$C,"SharePoint", 'BA BackOffice'!$U:$U,"NO", 'BA BackOffice'!$L:$L,">="&$B$1, 'BA BackOffice'!$L:$L,"<"&$C$1+1 ), COUNTIFS( 'BA BackOffice'!$D:$D,"P_Ticket", 'BA BackOffice'!$G:$G,"Medium", 'BA BackOffice'!$C:$C,"SharePoint", 'BA BackOffice'!$U:$U,"NO", 'BA BackOffice'!$L:$L,">="&$B$1, 'BA BackOffice'!$L:$L,"<"&$C$1+1 ), COUNTIFS( 'BA BackOffice'!$D:$D,"P_Ticket", 'BA BackOffice'!$G:$G,"High", 'BA BackOffice'!$C:$C,"SharePoint", 'BA BackOffice'!$U:$U,"NO", 'BA BackOffice'!$L:$L,">="&$B$1, 'BA BackOffice'!$L:$L,"<"&$C$1+1 ) ) -> 0 | T5: =SUM(COUNTIFS('BA BackOffice'!$D:$D,"P_Ticket",'BA BackOffice'!$C:$C,"SharePoint",'BA BackOffice'!$G:$G,"Low",'BA BackOffice'!$I:$I,"Closed",'BA BackOffice'!$U:$U,"NO",'BA BackOffice'!$N:$N,"<"&$C$1+1,'BA BackOffice'!$N:$N,">="&$B$1),COUNTIFS('BA BackOffice'!$D:$D,"P_Ticket",'BA BackOffice'!$C:$C,"SharePoint",'BA BackOffice'!$G:$G,"Medium",'BA BackOffice'!$I:$I,"Closed",'BA BackOffice'!$U:$U,"NO",'BA BackOffice'!$N:$N,"<"&$C$1+1,'BA BackOffice'!$N:$N,">="&$B$1),COUNTIFS('BA BackOffice'!$D:$D,"P_Ticket",'BA BackOffice'!$C:$C,"SharePoint",'BA BackOffice'!$G:$G,"High",'BA BackOffice'!$I:$I,"Closed",'BA BackOffice'!$U:$U,"NO",'BA BackOffice'!$N:$N,"<"&$C$1+1,'BA BackOffice'!$N:$N,">="&$B$1),COUNTIFS('BA BackOffice'!$D:$D,"P_Ticket",'BA BackOffice'!$C:$C,"SharePoint",'BA BackOffice'!$G:$G,"Low",'BA BackOffice'!$I:$I,"Triaged",'BA BackOffice'!$U:$U,"NO",'BA BackOffice'!$N:$N,"<"&$C$1+1,'BA BackOffice'!$N:$N,">="&$B$1),COUNTIFS('BA BackOffice'!$D:$D,"P_Ticket",'BA BackOffice'!$C:$C,"SharePoint",'BA BackOffice'!$G:$G,"Medium",'BA BackOffice'!$I:$I,"Triaged",'BA BackOffice'!$U:$U,"NO",'BA BackOffice'!$N:$N,"<"&$C$1+1,'BA BackOffice'!$N:$N,">="&$B$1),COUNTIFS('BA BackOffice'!$D:$D,"P_Ticket",'BA BackOffice'!$C:$C,"SharePoint",'BA BackOffice'!$G:$G,"High",'BA BackOffice'!$I:$I,"Triaged",'BA BackOffice'!$U:$U,"NO",'BA BackOffice'!$N:$N,"<"&$C$1+1,'BA BackOffice'!$N:$N,">="&$B$1)) -> 0 | W5: =COUNTIFS( 'BA BackOffice'!$D:$D,"P_Ticket", 'BA BackOffice'!$G:$G,"High", 'BA BackOffice'!$C:$C,"SharePoint", 'BA BackOffice'!$U:$U,"NO", 'BA BackOffice'!$L:$L,">="&$B$1, 'BA BackOffice'!$L:$L,"<"&$C$1+1 ) -> 0 | X5: =SUM( COUNTIFS( 'BA BackOffice'!$D:$D,"P_Ticket", 'BA BackOffice'!$C:$C,"SharePoint", 'BA BackOffice'!$G:$G,"High", 'BA BackOffice'!$I:$I,"Closed", 'BA BackOffice'!$U:$U,"NO", 'BA BackOffice'!$N:$N,"<"&$C$1+1, 'BA BackOffice'!$N:$N,">="&$B$1 ), COUNTIFS( 'BA BackOffice'!$D:$D,"P_Ticket", 'BA BackOffice'!$C:$C,"SharePoint", 'BA BackOffice'!$G:$G,"High", 'BA BackOffice'!$I:$I,"Triaged", 'BA BackOffice'!$U:$U,"NO", 'BA BackOffice'!$N:$N,"<"&$C$1+1, 'BA BackOffice'!$N:$N,">="&$B$1 ) ) -> 0
A6: APPSUP_APEX | B6: BA | C6: Apex | D6: =COUNTIFS( 'BA BackOffice'!$D:$D,"Incident", 'BA BackOffice'!$G:$G,1, 'BA BackOffice'!$C:$C,"Apex", 'BA BackOffice'!$U:$U,"NO", 'BA BackOffice'!$L:$L,">="&$B$1, 'BA BackOffice'!$L:$L,"<"&$C$1+1 ) -> 0 | E6: =SUM( COUNTIFS( 'BA BackOffice'!$D:$D,"Incident", 'BA BackOffice'!$C:$C,"Apex", 'BA BackOffice'!$G:$G,1, 'BA BackOffice'!$I:$I,"Closed", 'BA BackOffice'!$U:$U,"NO", 'BA BackOffice'!$N:$N,">="&$B$1, 'BA BackOffice'!$N:$N,"<"&$C$1+1 ), COUNTIFS( 'BA BackOffice'!$D:$D,"Incident", 'BA BackOffice'!$C:$C,"Apex", 'BA BackOffice'!$G:$G,1, 'BA BackOffice'!$I:$I,"Triaged", 'BA BackOffice'!$U:$U,"NO", 'BA BackOffice'!$N:$N,">="&$B$1, 'BA BackOffice'!$N:$N,"<"&$C$1+1 ) ) -> 0 | F6: =COUNTIFS( 'BA BackOffice'!$C:$C,"Apex", 'BA BackOffice'!$D:$D,"Incident", 'BA BackOffice'!$G:$G,1, 'BA BackOffice'!$U:$U,"<>YES", 'BA BackOffice'!$K:$K,"<"&$B$1, 'BA BackOffice'!$N:$N,"" ) + COUNTIFS( 'BA BackOffice'!$C:$C,"Apex", 'BA BackOffice'!$D:$D,"Incident", 'BA BackOffice'!$G:$G,1, 'BA BackOffice'!$U:$U,"<>YES", 'BA BackOffice'!$K:$K,"<"&$B$1, 'BA BackOffice'!$N:$N,">="&$B$1 ) + COUNTIFS( 'BA BackOffice'!$C:$C,"Apex", 'BA BackOffice'!$D:$D,"Incident", 'BA BackOffice'!$G:$G,1, 'BA BackOffice'!$U:$U,"<>YES", 'BA BackOffice'!$K:$K,">="&$B$1, 'BA BackOffice'!$K:$K,"<"&$C$1+1 ) - COUNTIFS( 'BA BackOffice'!$C:$C,"Apex", 'BA BackOffice'!$D:$D,"Incident", 'BA BackOffice'!$G:$G,1, 'BA BackOffice'!$U:$U,"<>YES", 'BA BackOffice'!$I:$I,"Closed", 'BA BackOffice'!$N:$N,">="&$B$1, 'BA BackOffice'!$N:$N,"<"&$C$1+1 ) - COUNTIFS( 'BA BackOffice'!$C:$C,"Apex", 'BA BackOffice'!$D:$D,"Incident", 'BA BackOffice'!$G:$G,1, 'BA BackOffice'!$U:$U,"<>YES", 'BA BackOffice'!$I:$I,"Triaged", 'BA BackOffice'!$N:$N,">="&$B$1, 'BA BackOffice'!$N:$N,"<"&$C$1+1 ) -> 0 | G6: =COUNTIFS( 'BA BackOffice'!$D:$D,"Incident", 'BA BackOffice'!$G:$G,2, 'BA BackOffice'!$C:$C,"Apex", 'BA BackOffice'!$U:$U,"NO", 'BA BackOffice'!$L:$L,">="&$B$1, 'BA BackOffice'!$L:$L,"<"&$C$1+1 ) -> 0 | H6: =SUM( COUNTIFS( 'BA BackOffice'!$D:$D,"Incident", 'BA BackOffice'!$C:$C,"Apex", 'BA BackOffice'!$G:$G,2, 'BA BackOffice'!$I:$I,"Closed", 'BA BackOffice'!$U:$U,"NO", 'BA BackOffice'!$N:$N,">="&$B$1, 'BA BackOffice'!$N:$N,"<"&$C$1+1 ), COUNTIFS( 'BA BackOffice'!$D:$D,"Incident", 'BA BackOffice'!$C:$C,"Apex", 'BA BackOffice'!$G:$G,2, 'BA BackOffice'!$I:$I,"Triaged", 'BA BackOffice'!$U:$U,"NO", 'BA BackOffice'!$N:$N,">="&$B$1, 'BA BackOffice'!$N:$N,"<"&$C$1+1 ) ) -> 0 | I6: =COUNTIFS( 'BA BackOffice'!$C:$C,"Apex", 'BA BackOffice'!$D:$D,"Incident", 'BA BackOffice'!$G:$G,2, 'BA BackOffice'!$U:$U,"<>YES", 'BA BackOffice'!$K:$K,"<"&$B$1, 'BA BackOffice'!$N:$N,"" ) + COUNTIFS( 'BA BackOffice'!$C:$C,"Apex", 'BA BackOffice'!$D:$D,"Incident", 'BA BackOffice'!$G:$G,2, 'BA BackOffice'!$U:$U,"<>YES", 'BA BackOffice'!$K:$K,"<"&$B$1, 'BA BackOffice'!$N:$N,">="&$B$1 ) + COUNTIFS( 'BA BackOffice'!$C:$C,"Apex", 'BA BackOffice'!$D:$D,"Incident", 'BA BackOffice'!$G:$G,2, 'BA BackOffice'!$U:$U,"<>YES", 'BA BackOffice'!$K:$K,">="&$B$1, 'BA BackOffice'!$K:$K,"<"&$C$1+1 ) - COUNTIFS( 'BA BackOffice'!$C:$C,"Apex", 'BA BackOffice'!$D:$D,"Incident", 'BA BackOffice'!$G:$G,2, 'BA BackOffice'!$U:$U,"<>YES", 'BA BackOffice'!$I:$I,"Closed", 'BA BackOffice'!$N:$N,">="&$B$1, 'BA BackOffice'!$N:$N,"<"&$C$1+1 ) - COUNTIFS( 'BA BackOffice'!$C:$C,"Apex", 'BA BackOffice'!$D:$D,"Incident", 'BA BackOffice'!$G:$G,2, 'BA BackOffice'!$U:$U,"<>YES", 'BA BackOffice'!$I:$I,"Triaged", 'BA BackOffice'!$N:$N,">="&$B$1, 'BA BackOffice'!$N:$N,"<"&$C$1+1 ) -> 0 | J6: =COUNTIFS( 'BA BackOffice'!$D:$D,"Incident", 'BA BackOffice'!$G:$G,3, 'BA BackOffice'!$C:$C,"Apex", 'BA BackOffice'!$U:$U,"NO", 'BA BackOffice'!$L:$L,">="&$B$1, 'BA BackOffice'!$L:$L,"<"&$C$1+1 ) -> 0 | K6: =SUM( COUNTIFS( 'BA BackOffice'!$D:$D,"Incident", 'BA BackOffice'!$C:$C,"Apex", 'BA BackOffice'!$G:$G,3, 'BA BackOffice'!$I:$I,"Closed", 'BA BackOffice'!$U:$U,"NO", 'BA BackOffice'!$N:$N,">="&$B$1, 'BA BackOffice'!$N:$N,"<"&$C$1+1 ), COUNTIFS( 'BA BackOffice'!$D:$D,"Incident", 'BA BackOffice'!$C:$C,"Apex", 'BA BackOffice'!$G:$G,3, 'BA BackOffice'!$I:$I,"Triaged", 'BA BackOffice'!$U:$U,"NO", 'BA BackOffice'!$N:$N,">="&$B$1, 'BA BackOffice'!$N:$N,"<"&$C$1+1 ) ) -> 0 | L6: =COUNTIFS( 'BA BackOffice'!$C:$C,"Apex", 'BA BackOffice'!$D:$D,"Incident", 'BA BackOffice'!$G:$G,3, 'BA BackOffice'!$U:$U,"<>YES", 'BA BackOffice'!$K:$K,"<"&$B$1, 'BA BackOffice'!$N:$N,"" ) + COUNTIFS( 'BA BackOffice'!$C:$C,"Apex", 'BA BackOffice'!$D:$D,"Incident", 'BA BackOffice'!$G:$G,3, 'BA BackOffice'!$U:$U,"<>YES", 'BA BackOffice'!$K:$K,"<"&$B$1, 'BA BackOffice'!$N:$N,">="&$B$1 ) + COUNTIFS( 'BA BackOffice'!$C:$C,"Apex", 'BA BackOffice'!$D:$D,"Incident", 'BA BackOffice'!$G:$G,3, 'BA BackOffice'!$U:$U,"<>YES", 'BA BackOffice'!$K:$K,">="&$B$1, 'BA BackOffice'!$K:$K,"<"&$C$1+1 ) - COUNTIFS( 'BA BackOffice'!$C:$C,"Apex", 'BA BackOffice'!$D:$D,"Incident", 'BA BackOffice'!$G:$G,3, 'BA BackOffice'!$U:$U,"<>YES", 'BA BackOffice'!$I:$I,"Closed", 'BA BackOffice'!$N:$N,">="&$B$1, 'BA BackOffice'!$N:$N,"<"&$C$1+1 ) - COUNTIFS( 'BA BackOffice'!$C:$C,"Apex", 'BA BackOffice'!$D:$D,"Incident", 'BA BackOffice'!$G:$G,3, 'BA BackOffice'!$U:$U,"<>YES", 'BA BackOffice'!$I:$I,"Triaged", 'BA BackOffice'!$N:$N,">="&$B$1, 'BA BackOffice'!$N:$N,"<"&$C$1+1 ) -> 0 | M6: =COUNTIFS( 'BA BackOffice'!$D:$D,"Incident", 'BA BackOffice'!$G:$G,4, 'BA BackOffice'!$C:$C,"Apex", 'BA BackOffice'!$U:$U,"NO", 'BA BackOffice'!$L:$L,">="&$B$1, 'BA BackOffice'!$L:$L,"<"&$C$1+1 ) -> 0 | N6: =SUM( COUNTIFS( 'BA BackOffice'!$D:$D,"Incident", 'BA BackOffice'!$C:$C,"Apex", 'BA BackOffice'!$G:$G,4, 'BA BackOffice'!$I:$I,"Closed", 'BA BackOffice'!$U:$U,"NO", 'BA BackOffice'!$N:$N,">="&$B$1, 'BA BackOffice'!$N:$N,"<"&$C$1+1 ), COUNTIFS( 'BA BackOffice'!$D:$D,"Incident", 'BA BackOffice'!$C:$C,"Apex", 'BA BackOffice'!$G:$G,4, 'BA BackOffice'!$I:$I,"Triaged", 'BA BackOffice'!$U:$U,"NO", 'BA BackOffice'!$N:$N,">="&$B$1, 'BA BackOffice'!$N:$N,"<"&$C$1+1 ) ) -> 0 | O6: =COUNTIFS( 'BA BackOffice'!$C:$C,"Apex", 'BA BackOffice'!$D:$D,"Incident", 'BA BackOffice'!$G:$G,4, 'BA BackOffice'!$U:$U,"<>YES", 'BA BackOffice'!$K:$K,"<"&$B$1, 'BA BackOffice'!$N:$N,"" ) + COUNTIFS( 'BA BackOffice'!$C:$C,"Apex", 'BA BackOffice'!$D:$D,"Incident", 'BA BackOffice'!$G:$G,4, 'BA BackOffice'!$U:$U,"<>YES", 'BA BackOffice'!$K:$K,"<"&$B$1, 'BA BackOffice'!$N:$N,">="&$B$1 ) + COUNTIFS( 'BA BackOffice'!$C:$C,"Apex", 'BA BackOffice'!$D:$D,"Incident", 'BA BackOffice'!$G:$G,4, 'BA BackOffice'!$U:$U,"<>YES", 'BA BackOffice'!$K:$K,">="&$B$1, 'BA BackOffice'!$K:$K,"<"&$C$1+1 ) - COUNTIFS( 'BA BackOffice'!$C:$C,"Apex", 'BA BackOffice'!$D:$D,"Incident", 'BA BackOffice'!$G:$G,4, 'BA BackOffice'!$U:$U,"<>YES", 'BA BackOffice'!$I:$I,"Closed", 'BA BackOffice'!$N:$N,">="&$B$1, 'BA BackOffice'!$N:$N,"<"&$C$1+1 ) - COUNTIFS( 'BA BackOffice'!$C:$C,"Apex", 'BA BackOffice'!$D:$D,"Incident", 'BA BackOffice'!$G:$G,4, 'BA BackOffice'!$U:$U,"<>YES", 'BA BackOffice'!$I:$I,"Triaged", 'BA BackOffice'!$N:$N,">="&$B$1, 'BA BackOffice'!$N:$N,"<"&$C$1+1 ) -> 0 | P6: =COUNTIFS( 'BA BackOffice'!$D:$D,"RFS", 'BA BackOffice'!$C:$C,"Apex", 'BA BackOffice'!$U:$U,"No", 'BA BackOffice'!$L:$L,">="&$B$1, 'BA BackOffice'!$L:$L,"<"&$C$1+1 ) -> 0 | Q6: =SUM( COUNTIFS( 'BA BackOffice'!$D:$D,"RFS", 'BA BackOffice'!$C:$C,"Apex", 'BA BackOffice'!$I:$I,"Closed", 'BA BackOffice'!$U:$U,"NO", 'BA BackOffice'!$N:$N,">="&$B$1, 'BA BackOffice'!$N:$N,"<"&$C$1+1 ), COUNTIFS( 'BA BackOffice'!$D:$D,"RFS", 'BA BackOffice'!$C:$C,"Apex", 'BA BackOffice'!$I:$I,"Triaged", 'BA BackOffice'!$U:$U,"NO", 'BA BackOffice'!$N:$N,">="&$B$1, 'BA BackOffice'!$N:$N,"<"&$C$1+1 ) ) -> 0 | R6: =COUNTIFS( 'BA BackOffice'!$D:$D,"RFS", 'BA BackOffice'!$C:$C,"Apex", 'BA BackOffice'!$U:$U,"<>YES", 'BA BackOffice'!$K:$K,"<"&$B$1, 'BA BackOffice'!$N:$N,"" ) + COUNTIFS( 'BA BackOffice'!$D:$D,"RFS", 'BA BackOffice'!$C:$C,"Apex", 'BA BackOffice'!$U:$U,"<>YES", 'BA BackOffice'!$K:$K,"<"&$B$1, 'BA BackOffice'!$N:$N,">="&$B$1 ) + COUNTIFS( 'BA BackOffice'!$D:$D,"RFS", 'BA BackOffice'!$C:$C,"Apex", 'BA BackOffice'!$U:$U,"<>YES", 'BA BackOffice'!$K:$K,">="&$B$1, 'BA BackOffice'!$K:$K,"<"&$C$1+1 ) - COUNTIFS( 'BA BackOffice'!$D:$D,"RFS", 'BA BackOffice'!$C:$C,"Apex", 'BA BackOffice'!$I:$I,"Closed", 'BA BackOffice'!$U:$U,"<>YES", 'BA BackOffice'!$N:$N,">="&$B$1, 'BA BackOffice'!$N:$N,"<"&$C$1+1 ) - COUNTIFS( 'BA BackOffice'!$D:$D,"RFS", 'BA BackOffice'!$C:$C,"Apex", 'BA BackOffice'!$I:$I,"Triaged", 'BA BackOffice'!$U:$U,"<>YES", 'BA BackOffice'!$N:$N,">="&$B$1, 'BA BackOffice'!$N:$N,"<"&$C$1+1 ) -> 4 | S6: =SUM( COUNTIFS( 'BA BackOffice'!$D:$D,"P_Ticket", 'BA BackOffice'!$G:$G,"Low", 'BA BackOffice'!$C:$C,"Apex", 'BA BackOffice'!$U:$U,"NO", 'BA BackOffice'!$L:$L,">="&$B$1, 'BA BackOffice'!$L:$L,"<"&$C$1+1 ), COUNTIFS( 'BA BackOffice'!$D:$D,"P_Ticket", 'BA BackOffice'!$G:$G,"Medium", 'BA BackOffice'!$C:$C,"Apex", 'BA BackOffice'!$U:$U,"NO", 'BA BackOffice'!$L:$L,">="&$B$1, 'BA BackOffice'!$L:$L,"<"&$C$1+1 ), COUNTIFS( 'BA BackOffice'!$D:$D,"P_Ticket", 'BA BackOffice'!$G:$G,"High", 'BA BackOffice'!$C:$C,"Apex", 'BA BackOffice'!$U:$U,"NO", 'BA BackOffice'!$L:$L,">="&$B$1, 'BA BackOffice'!$L:$L,"<"&$C$1+1 ) ) -> 0 | T6: =SUM(COUNTIFS('BA BackOffice'!$D:$D,"P_Ticket",'BA BackOffice'!$C:$C,"APEX",'BA BackOffice'!$G:$G,"Low",'BA BackOffice'!$I:$I,"Closed",'BA BackOffice'!$U:$U,"NO",'BA BackOffice'!$N:$N,"<"&$C$1+1,'BA BackOffice'!$N:$N,">="&$B$1),COUNTIFS('BA BackOffice'!$D:$D,"P_Ticket",'BA BackOffice'!$C:$C,"APEX",'BA BackOffice'!$G:$G,"Medium",'BA BackOffice'!$I:$I,"Closed",'BA BackOffice'!$U:$U,"NO",'BA BackOffice'!$N:$N,"<"&$C$1+1,'BA BackOffice'!$N:$N,">="&$B$1),COUNTIFS('BA BackOffice'!$D:$D,"P_Ticket",'BA BackOffice'!$C:$C,"APEX",'BA BackOffice'!$G:$G,"High",'BA BackOffice'!$I:$I,"Closed",'BA BackOffice'!$U:$U,"NO",'BA BackOffice'!$N:$N,"<"&$C$1+1,'BA BackOffice'!$N:$N,">="&$B$1),COUNTIFS('BA BackOffice'!$D:$D,"P_Ticket",'BA BackOffice'!$C:$C,"APEX",'BA BackOffice'!$G:$G,"Low",'BA BackOffice'!$I:$I,"Triaged",'BA BackOffice'!$U:$U,"NO",'BA BackOffice'!$N:$N,"<"&$C$1+1,'BA BackOffice'!$N:$N,">="&$B$1),COUNTIFS('BA BackOffice'!$D:$D,"P_Ticket",'BA BackOffice'!$C:$C,"APEX",'BA BackOffice'!$G:$G,"Medium",'BA BackOffice'!$I:$I,"Triaged",'BA BackOffice'!$U:$U,"NO",'BA BackOffice'!$N:$N,"<"&$C$1+1,'BA BackOffice'!$N:$N,">="&$B$1),COUNTIFS('BA BackOffice'!$D:$D,"P_Ticket",'BA BackOffice'!$C:$C,"APEX",'BA BackOffice'!$G:$G,"High",'BA BackOffice'!$I:$I,"Triaged",'BA BackOffice'!$U:$U,"NO",'BA BackOffice'!$N:$N,"<"&$C$1+1,'BA BackOffice'!$N:$N,">="&$B$1)) -> 0 | W6: =COUNTIFS( 'BA BackOffice'!$D:$D,"P_Ticket", 'BA BackOffice'!$G:$G,"High", 'BA BackOffice'!$C:$C,"Apex", 'BA BackOffice'!$U:$U,"NO", 'BA BackOffice'!$L:$L,">="&$B$1, 'BA BackOffice'!$L:$L,"<"&$C$1+1 ) -> 0 | X6: =SUM( COUNTIFS( 'BA BackOffice'!$D:$D,"P_Ticket", 'BA BackOffice'!$C:$C,"Apex", 'BA BackOffice'!$G:$G,"High", 'BA BackOffice'!$I:$I,"Closed", 'BA BackOffice'!$U:$U,"NO", 'BA BackOffice'!$N:$N,"<"&$C$1+1, 'BA BackOffice'!$N:$N,">="&$B$1 ), COUNTIFS( 'BA BackOffice'!$D:$D,"P_Ticket", 'BA BackOffice'!$C:$C,"Apex", 'BA BackOffice'!$G:$G,"High", 'BA BackOffice'!$I:$I,"Triaged", 'BA BackOffice'!$U:$U,"NO", 'BA BackOffice'!$N:$N,"<"&$C$1+1, 'BA BackOffice'!$N:$N,">="&$B$1 ) ) -> 0
A7: APPSUP_ETL APPSUP_TRILLIUM APPSUP_CRT APPSUP_BOA APPSUP_ICD50 | B7: BA | C7: TechTools | D7: =COUNTIFS( 'BA BackOffice'!$D:$D,"Incident", 'BA BackOffice'!$G:$G,1, 'BA BackOffice'!$C:$C,"TechTools", 'BA BackOffice'!$U:$U,"NO", 'BA BackOffice'!$L:$L,">="&$B$1, 'BA BackOffice'!$L:$L,"<"&$C$1+1 ) -> 0 | E7: =SUM( COUNTIFS( 'BA BackOffice'!$D:$D,"Incident", 'BA BackOffice'!$C:$C,"TechTools", 'BA BackOffice'!$G:$G,1, 'BA BackOffice'!$I:$I,"Closed", 'BA BackOffice'!$U:$U,"NO", 'BA BackOffice'!$N:$N,">="&$B$1, 'BA BackOffice'!$N:$N,"<"&$C$1+1 ), COUNTIFS( 'BA BackOffice'!$D:$D,"Incident", 'BA BackOffice'!$C:$C,"TechTools", 'BA BackOffice'!$G:$G,1, 'BA BackOffice'!$I:$I,"Triaged", 'BA BackOffice'!$U:$U,"NO", 'BA BackOffice'!$N:$N,">="&$B$1, 'BA BackOffice'!$N:$N,"<"&$C$1+1 ) ) -> 0 | F7: =COUNTIFS( 'BA BackOffice'!$C:$C,"TechTools", 'BA BackOffice'!$D:$D,"Incident", 'BA BackOffice'!$G:$G,1, 'BA BackOffice'!$U:$U,"<>YES", 'BA BackOffice'!$K:$K,"<"&$B$1, 'BA BackOffice'!$N:$N,"" ) + COUNTIFS( 'BA BackOffice'!$C:$C,"TechTools", 'BA BackOffice'!$D:$D,"Incident", 'BA BackOffice'!$G:$G,1, 'BA BackOffice'!$U:$U,"<>YES", 'BA BackOffice'!$K:$K,"<"&$B$1, 'BA BackOffice'!$N:$N,">="&$B$1 ) + COUNTIFS( 'BA BackOffice'!$C:$C,"TechTools", 'BA BackOffice'!$D:$D,"Incident", 'BA BackOffice'!$G:$G,1, 'BA BackOffice'!$U:$U,"<>YES", 'BA BackOffice'!$K:$K,">="&$B$1, 'BA BackOffice'!$K:$K,"<"&$C$1+1 ) - COUNTIFS( 'BA BackOffice'!$C:$C,"TechTools", 'BA BackOffice'!$D:$D,"Incident", 'BA BackOffice'!$G:$G,1, 'BA BackOffice'!$U:$U,"<>YES", 'BA BackOffice'!$I:$I,"Closed", 'BA BackOffice'!$N:$N,">="&$B$1, 'BA BackOffice'!$N:$N,"<"&$C$1+1 ) - COUNTIFS( 'BA BackOffice'!$C:$C,"TechTools", 'BA BackOffice'!$D:$D,"Incident", 'BA BackOffice'!$G:$G,1, 'BA BackOffice'!$U:$U,"<>YES", 'BA BackOffice'!$I:$I,"Triaged", 'BA BackOffice'!$N:$N,">="&$B$1, 'BA BackOffice'!$N:$N,"<"&$C$1+1 ) -> 0 | G7: =COUNTIFS( 'BA BackOffice'!$D:$D,"Incident", 'BA BackOffice'!$G:$G,2, 'BA BackOffice'!$C:$C,"TechTools", 'BA BackOffice'!$U:$U,"NO", 'BA BackOffice'!$L:$L,">="&$B$1, 'BA BackOffice'!$L:$L,"<"&$C$1+1 ) -> 0 | H7: =SUM( COUNTIFS( 'BA BackOffice'!$D:$D,"Incident", 'BA BackOffice'!$C:$C,"TechTools", 'BA BackOffice'!$G:$G,2, 'BA BackOffice'!$I:$I,"Closed", 'BA BackOffice'!$U:$U,"NO", 'BA BackOffice'!$N:$N,">="&$B$1, 'BA BackOffice'!$N:$N,"<"&$C$1+1 ), COUNTIFS( 'BA BackOffice'!$D:$D,"Incident", 'BA BackOffice'!$C:$C,"TechTools", 'BA BackOffice'!$G:$G,2, 'BA BackOffice'!$I:$I,"Triaged", 'BA BackOffice'!$U:$U,"NO", 'BA BackOffice'!$N:$N,">="&$B$1, 'BA BackOffice'!$N:$N,"<"&$C$1+1 ) ) -> 0 | I7: =COUNTIFS( 'BA BackOffice'!$C:$C,"TechTools", 'BA BackOffice'!$D:$D,"Incident", 'BA BackOffice'!$G:$G,2, 'BA BackOffice'!$U:$U,"<>YES", 'BA BackOffice'!$K:$K,"<"&$B$1, 'BA BackOffice'!$N:$N,"" ) + COUNTIFS( 'BA BackOffice'!$C:$C,"TechTools", 'BA BackOffice'!$D:$D,"Incident", 'BA BackOffice'!$G:$G,2, 'BA BackOffice'!$U:$U,"<>YES", 'BA BackOffice'!$K:$K,"<"&$B$1, 'BA BackOffice'!$N:$N,">="&$B$1 ) + COUNTIFS( 'BA BackOffice'!$C:$C,"TechTools", 'BA BackOffice'!$D:$D,"Incident", 'BA BackOffice'!$G:$G,2, 'BA BackOffice'!$U:$U,"<>YES", 'BA BackOffice'!$K:$K,">="&$B$1, 'BA BackOffice'!$K:$K,"<"&$C$1+1 ) - COUNTIFS( 'BA BackOffice'!$C:$C,"TechTools", 'BA BackOffice'!$D:$D,"Incident", 'BA BackOffice'!$G:$G,2, 'BA BackOffice'!$U:$U,"<>YES", 'BA BackOffice'!$I:$I,"Closed", 'BA BackOffice'!$N:$N,">="&$B$1, 'BA BackOffice'!$N:$N,"<"&$C$1+1 ) - COUNTIFS( 'BA BackOffice'!$C:$C,"TechTools", 'BA BackOffice'!$D:$D,"Incident", 'BA BackOffice'!$G:$G,2, 'BA BackOffice'!$U:$U,"<>YES", 'BA BackOffice'!$I:$I,"Triaged", 'BA BackOffice'!$N:$N,">="&$B$1, 'BA BackOffice'!$N:$N,"<"&$C$1+1 ) -> 0 | J7: =COUNTIFS( 'BA BackOffice'!$D:$D,"Incident", 'BA BackOffice'!$G:$G,3, 'BA BackOffice'!$C:$C,"TechTools", 'BA BackOffice'!$U:$U,"NO", 'BA BackOffice'!$L:$L,">="&$B$1, 'BA BackOffice'!$L:$L,"<"&$C$1+1 ) -> 6 | K7: =SUM( COUNTIFS( 'BA BackOffice'!$D:$D,"Incident", 'BA BackOffice'!$C:$C,"TechTools", 'BA BackOffice'!$G:$G,3, 'BA BackOffice'!$I:$I,"Closed", 'BA BackOffice'!$U:$U,"NO", 'BA BackOffice'!$N:$N,">="&$B$1, 'BA BackOffice'!$N:$N,"<"&$C$1+1 ), COUNTIFS( 'BA BackOffice'!$D:$D,"Incident", 'BA BackOffice'!$C:$C,"TechTools", 'BA BackOffice'!$G:$G,3, 'BA BackOffice'!$I:$I,"Triaged", 'BA BackOffice'!$U:$U,"NO", 'BA BackOffice'!$N:$N,">="&$B$1, 'BA BackOffice'!$N:$N,"<"&$C$1+1 ) ) -> 8 | L7: =COUNTIFS( 'BA BackOffice'!$C:$C,"TechTools", 'BA BackOffice'!$D:$D,"Incident", 'BA BackOffice'!$G:$G,3, 'BA BackOffice'!$U:$U,"<>YES", 'BA BackOffice'!$K:$K,"<"&$B$1, 'BA BackOffice'!$N:$N,"" ) + COUNTIFS( 'BA BackOffice'!$C:$C,"TechTools", 'BA BackOffice'!$D:$D,"Incident", 'BA BackOffice'!$G:$G,3, 'BA BackOffice'!$U:$U,"<>YES", 'BA BackOffice'!$K:$K,"<"&$B$1, 'BA BackOffice'!$N:$N,">="&$B$1 ) + COUNTIFS( 'BA BackOffice'!$C:$C,"TechTools", 'BA BackOffice'!$D:$D,"Incident", 'BA BackOffice'!$G:$G,3, 'BA BackOffice'!$U:$U,"<>YES", 'BA BackOffice'!$K:$K,">="&$B$1, 'BA BackOffice'!$K:$K,"<"&$C$1+1 ) - COUNTIFS( 'BA BackOffice'!$C:$C,"TechTools", 'BA BackOffice'!$D:$D,"Incident", 'BA BackOffice'!$G:$G,3, 'BA BackOffice'!$U:$U,"<>YES", 'BA BackOffice'!$I:$I,"Closed", 'BA BackOffice'!$N:$N,">="&$B$1, 'BA BackOffice'!$N:$N,"<"&$C$1+1 ) - COUNTIFS( 'BA BackOffice'!$C:$C,"TechTools", 'BA BackOffice'!$D:$D,"Incident", 'BA BackOffice'!$G:$G,3, 'BA BackOffice'!$U:$U,"<>YES", 'BA BackOffice'!$I:$I,"Triaged", 'BA BackOffice'!$N:$N,">="&$B$1, 'BA BackOffice'!$N:$N,"<"&$C$1+1 ) -> 0 | M7: =COUNTIFS( 'BA BackOffice'!$D:$D,"Incident", 'BA BackOffice'!$G:$G,4, 'BA BackOffice'!$C:$C,"TechTools", 'BA BackOffice'!$U:$U,"NO", 'BA BackOffice'!$L:$L,">="&$B$1, 'BA BackOffice'!$L:$L,"<"&$C$1+1 ) -> 7 | N7: =SUM( COUNTIFS( 'BA BackOffice'!$D:$D,"Incident", 'BA BackOffice'!$C:$C,"TechTools", 'BA BackOffice'!$G:$G,4, 'BA BackOffice'!$I:$I,"Closed", 'BA BackOffice'!$U:$U,"NO", 'BA BackOffice'!$N:$N,">="&$B$1, 'BA BackOffice'!$N:$N,"<"&$C$1+1 ), COUNTIFS( 'BA BackOffice'!$D:$D,"Incident", 'BA BackOffice'!$C:$C,"TechTools", 'BA BackOffice'!$G:$G,4, 'BA BackOffice'!$I:$I,"Triaged", 'BA BackOffice'!$U:$U,"NO", 'BA BackOffice'!$N:$N,">="&$B$1, 'BA BackOffice'!$N:$N,"<"&$C$1+1 ) ) -> 7 | O7: =COUNTIFS( 'BA BackOffice'!$C:$C,"TechTools", 'BA BackOffice'!$D:$D,"Incident", 'BA BackOffice'!$G:$G,4, 'BA BackOffice'!$U:$U,"<>YES", 'BA BackOffice'!$K:$K,"<"&$B$1, 'BA BackOffice'!$N:$N,"" ) + COUNTIFS( 'BA BackOffice'!$C:$C,"TechTools", 'BA BackOffice'!$D:$D,"Incident", 'BA BackOffice'!$G:$G,4, 'BA BackOffice'!$U:$U,"<>YES", 'BA BackOffice'!$K:$K,"<"&$B$1, 'BA BackOffice'!$N:$N,">="&$B$1 ) + COUNTIFS( 'BA BackOffice'!$C:$C,"TechTools", 'BA BackOffice'!$D:$D,"Incident", 'BA BackOffice'!$G:$G,4, 'BA BackOffice'!$U:$U,"<>YES", 'BA BackOffice'!$K:$K,">="&$B$1, 'BA BackOffice'!$K:$K,"<"&$C$1+1 ) - COUNTIFS( 'BA BackOffice'!$C:$C,"TechTools", 'BA BackOffice'!$D:$D,"Incident", 'BA BackOffice'!$G:$G,4, 'BA BackOffice'!$U:$U,"<>YES", 'BA BackOffice'!$I:$I,"Closed", 'BA BackOffice'!$N:$N,">="&$B$1, 'BA BackOffice'!$N:$N,"<"&$C$1+1 ) - COUNTIFS( 'BA BackOffice'!$C:$C,"TechTools", 'BA BackOffice'!$D:$D,"Incident", 'BA BackOffice'!$G:$G,4, 'BA BackOffice'!$U:$U,"<>YES", 'BA BackOffice'!$I:$I,"Triaged", 'BA BackOffice'!$N:$N,">="&$B$1, 'BA BackOffice'!$N:$N,"<"&$C$1+1 ) -> 0 | P7: =COUNTIFS( 'BA BackOffice'!$D:$D,"RFS", 'BA BackOffice'!$C:$C,"TechTools", 'BA BackOffice'!$U:$U,"No", 'BA BackOffice'!$L:$L,">="&$B$1, 'BA BackOffice'!$L:$L,"<"&$C$1+1 ) -> 0 | Q7: =SUM( COUNTIFS( 'BA BackOffice'!$D:$D,"RFS", 'BA BackOffice'!$C:$C,"TechTools", 'BA BackOffice'!$I:$I,"Closed", 'BA BackOffice'!$U:$U,"NO", 'BA BackOffice'!$N:$N,">="&$B$1, 'BA BackOffice'!$N:$N,"<"&$C$1+1 ), COUNTIFS( 'BA BackOffice'!$D:$D,"RFS", 'BA BackOffice'!$C:$C,"TechTools", 'BA BackOffice'!$I:$I,"Triaged", 'BA BackOffice'!$U:$U,"NO", 'BA BackOffice'!$N:$N,">="&$B$1, 'BA BackOffice'!$N:$N,"<"&$C$1+1 ) ) -> 3 | R7: =COUNTIFS( 'BA BackOffice'!$D:$D,"RFS", 'BA BackOffice'!$C:$C,"TechTools", 'BA BackOffice'!$U:$U,"<>YES", 'BA BackOffice'!$K:$K,"<"&$B$1, 'BA BackOffice'!$N:$N,"" ) + COUNTIFS( 'BA BackOffice'!$D:$D,"RFS", 'BA BackOffice'!$C:$C,"TechTools", 'BA BackOffice'!$U:$U,"<>YES", 'BA BackOffice'!$K:$K,"<"&$B$1, 'BA BackOffice'!$N:$N,">="&$B$1 ) + COUNTIFS( 'BA BackOffice'!$D:$D,"RFS", 'BA BackOffice'!$C:$C,"TechTools", 'BA BackOffice'!$U:$U,"<>YES", 'BA BackOffice'!$K:$K,">="&$B$1, 'BA BackOffice'!$K:$K,"<"&$C$1+1 ) - COUNTIFS( 'BA BackOffice'!$D:$D,"RFS", 'BA BackOffice'!$C:$C,"TechTools", 'BA BackOffice'!$I:$I,"Closed", 'BA BackOffice'!$U:$U,"<>YES", 'BA BackOffice'!$N:$N,">="&$B$1, 'BA BackOffice'!$N:$N,"<"&$C$1+1 ) - COUNTIFS( 'BA BackOffice'!$D:$D,"RFS", 'BA BackOffice'!$C:$C,"TechTools", 'BA BackOffice'!$I:$I,"Triaged", 'BA BackOffice'!$U:$U,"<>YES", 'BA BackOffice'!$N:$N,">="&$B$1, 'BA BackOffice'!$N:$N,"<"&$C$1+1 ) -> 1 | S7: =SUM( COUNTIFS( 'BA BackOffice'!$D:$D,"P_Ticket", 'BA BackOffice'!$G:$G,"Low", 'BA BackOffice'!$C:$C,"TechTools", 'BA BackOffice'!$U:$U,"NO", 'BA BackOffice'!$L:$L,">="&$B$1, 'BA BackOffice'!$L:$L,"<"&$C$1+1 ), COUNTIFS( 'BA BackOffice'!$D:$D,"P_Ticket", 'BA BackOffice'!$G:$G,"Medium", 'BA BackOffice'!$C:$C,"TechTools", 'BA BackOffice'!$U:$U,"NO", 'BA BackOffice'!$L:$L,">="&$B$1, 'BA BackOffice'!$L:$L,"<"&$C$1+1 ), COUNTIFS( 'BA BackOffice'!$D:$D,"P_Ticket", 'BA BackOffice'!$G:$G,"High", 'BA BackOffice'!$C:$C,"TechTools", 'BA BackOffice'!$U:$U,"NO", 'BA BackOffice'!$L:$L,">="&$B$1, 'BA BackOffice'!$L:$L,"<"&$C$1+1 ) ) -> 0 | T7: =SUM(COUNTIFS('BA BackOffice'!$D:$D,"P_Ticket",'BA BackOffice'!$C:$C,"TechTools",'BA BackOffice'!$G:$G,"Low",'BA BackOffice'!$I:$I,"Closed",'BA BackOffice'!$U:$U,"NO",'BA BackOffice'!$N:$N,"<"&$C$1+1,'BA BackOffice'!$N:$N,">="&$B$1),COUNTIFS('BA BackOffice'!$D:$D,"P_Ticket",'BA BackOffice'!$C:$C,"TechTools",'BA BackOffice'!$G:$G,"Medium",'BA BackOffice'!$I:$I,"Closed",'BA BackOffice'!$U:$U,"NO",'BA BackOffice'!$N:$N,"<"&$C$1+1,'BA BackOffice'!$N:$N,">="&$B$1),COUNTIFS('BA BackOffice'!$D:$D,"P_Ticket",'BA BackOffice'!$C:$C,"TechTools",'BA BackOffice'!$G:$G,"High",'BA BackOffice'!$I:$I,"Closed",'BA BackOffice'!$U:$U,"NO",'BA BackOffice'!$N:$N,"<"&$C$1+1,'BA BackOffice'!$N:$N,">="&$B$1),COUNTIFS('BA BackOffice'!$D:$D,"P_Ticket",'BA BackOffice'!$C:$C,"TechTools",'BA BackOffice'!$G:$G,"Low",'BA BackOffice'!$I:$I,"Triaged",'BA BackOffice'!$U:$U,"NO",'BA BackOffice'!$N:$N,"<"&$C$1+1,'BA BackOffice'!$N:$N,">="&$B$1),COUNTIFS('BA BackOffice'!$D:$D,"P_Ticket",'BA BackOffice'!$C:$C,"TechTools",'BA BackOffice'!$G:$G,"Medium",'BA BackOffice'!$I:$I,"Triaged",'BA BackOffice'!$U:$U,"NO",'BA BackOffice'!$N:$N,"<"&$C$1+1,'BA BackOffice'!$N:$N,">="&$B$1),COUNTIFS('BA BackOffice'!$D:$D,"P_Ticket",'BA BackOffice'!$C:$C,"TechTools",'BA BackOffice'!$G:$G,"High",'BA BackOffice'!$I:$I,"Triaged",'BA BackOffice'!$U:$U,"NO",'BA BackOffice'!$N:$N,"<"&$C$1+1,'BA BackOffice'!$N:$N,">="&$B$1)) -> 0 | W7: =COUNTIFS( 'BA BackOffice'!$D:$D,"P_Ticket", 'BA BackOffice'!$G:$G,"High", 'BA BackOffice'!$C:$C,"TechTools", 'BA BackOffice'!$U:$U,"NO", 'BA BackOffice'!$L:$L,">="&$B$1, 'BA BackOffice'!$L:$L,"<"&$C$1+1 ) -> 0 | X7: =SUM( COUNTIFS( 'BA BackOffice'!$D:$D,"P_Ticket", 'BA BackOffice'!$C:$C,"TechTools", 'BA BackOffice'!$G:$G,"High", 'BA BackOffice'!$I:$I,"Closed", 'BA BackOffice'!$U:$U,"NO", 'BA BackOffice'!$N:$N,"<"&$C$1+1, 'BA BackOffice'!$N:$N,">="&$B$1 ), COUNTIFS( 'BA BackOffice'!$D:$D,"P_Ticket", 'BA BackOffice'!$C:$C,"TechTools", 'BA BackOffice'!$G:$G,"High", 'BA BackOffice'!$I:$I,"Triaged", 'BA BackOffice'!$U:$U,"NO", 'BA BackOffice'!$N:$N,"<"&$C$1+1, 'BA BackOffice'!$N:$N,">="&$B$1 ) ) -> 0
A8: APPSUP_INFORM APPSUP_OPSDASHBOARD APPSUP_AIRPORTOPS APPSUP_AIMSLOUNGES APPSUP_OSCS APPSUP_BAGS APPSUP_RIBI APPSUP_PLUTO | B8: BA | C8: AO | D8: =COUNTIFS( 'BA AO'!$D:$D,"Incident", 'BA AO'!$G:$G,1, 'BA AO'!$U:$U,"NO", 'BA AO'!$L:$L,">="&$B$1, 'BA AO'!$L:$L,"<"&$C$1+1 ) -> 0 | E8: =SUM( COUNTIFS( 'BA AO'!$D:$D,"Incident", 'BA AO'!$G:$G,1, 'BA AO'!$I:$I,"Closed", 'BA AO'!$U:$U,"NO", 'BA AO'!$N:$N,">="&$B$1, 'BA AO'!$N:$N,"<"&$C$1+1 ), COUNTIFS( 'BA AO'!$D:$D,"Incident", 'BA AO'!$G:$G,1, 'BA AO'!$I:$I,"Triaged", 'BA AO'!$U:$U,"NO", 'BA AO'!$N:$N,">="&$B$1, 'BA AO'!$N:$N,"<"&$C$1+1 ) ) -> 0 | F8: =COUNTIFS( 'BA AO'!$D:$D,"Incident", 'BA AO'!$G:$G,1, 'BA AO'!$U:$U,"<>YES", 'BA AO'!$K:$K,"<"&$B$1, 'BA AO'!$N:$N,"" ) + COUNTIFS( 'BA AO'!$D:$D,"Incident", 'BA AO'!$G:$G,1, 'BA AO'!$U:$U,"<>YES", 'BA AO'!$K:$K,"<"&$B$1, 'BA AO'!$N:$N,">="&$B$1 ) + COUNTIFS( 'BA AO'!$D:$D,"Incident", 'BA AO'!$G:$G,1, 'BA AO'!$U:$U,"<>YES", 'BA AO'!$K:$K,">="&$B$1, 'BA AO'!$K:$K,"<"&$C$1+1 ) - COUNTIFS( 'BA AO'!$D:$D,"Incident", 'BA AO'!$G:$G,1, 'BA AO'!$U:$U,"<>YES", 'BA AO'!$I:$I,"Closed", 'BA AO'!$N:$N,">="&$B$1, 'BA AO'!$N:$N,"<"&$C$1+1 ) - COUNTIFS( 'BA AO'!$D:$D,"Incident", 'BA AO'!$G:$G,1, 'BA AO'!$U:$U,"<>YES", 'BA AO'!$I:$I,"Triaged", 'BA AO'!$N:$N,">="&$B$1, 'BA AO'!$N:$N,"<"&$C$1+1 ) -> 0 | G8: =COUNTIFS( 'BA AO'!$D:$D,"Incident", 'BA AO'!$G:$G,2, 'BA AO'!$U:$U,"NO", 'BA AO'!$L:$L,">="&$B$1, 'BA AO'!$L:$L,"<"&$C$1+1 ) -> 0 | H8: =SUM( COUNTIFS( 'BA AO'!$D:$D,"Incident", 'BA AO'!$G:$G,2, 'BA AO'!$I:$I,"Closed", 'BA AO'!$U:$U,"NO", 'BA AO'!$N:$N,">="&$B$1, 'BA AO'!$N:$N,"<"&$C$1+1 ), COUNTIFS( 'BA AO'!$D:$D,"Incident", 'BA AO'!$G:$G,2, 'BA AO'!$I:$I,"Triaged", 'BA AO'!$U:$U,"NO", 'BA AO'!$N:$N,">="&$B$1, 'BA AO'!$N:$N,"<"&$C$1+1 ) ) -> 0 | I8: =COUNTIFS( 'BA AO'!$D:$D,"Incident", 'BA AO'!$G:$G,2, 'BA AO'!$U:$U,"<>YES", 'BA AO'!$K:$K,"<"&$B$1, 'BA AO'!$N:$N,"" ) + COUNTIFS( 'BA AO'!$D:$D,"Incident", 'BA AO'!$G:$G,2, 'BA AO'!$U:$U,"<>YES", 'BA AO'!$K:$K,"<"&$B$1, 'BA AO'!$N:$N,">="&$B$1 ) + COUNTIFS( 'BA AO'!$D:$D,"Incident", 'BA AO'!$G:$G,2, 'BA AO'!$U:$U,"<>YES", 'BA AO'!$K:$K,">="&$B$1, 'BA AO'!$K:$K,"<"&$C$1+1 ) - COUNTIFS( 'BA AO'!$D:$D,"Incident", 'BA AO'!$G:$G,2, 'BA AO'!$U:$U,"<>YES", 'BA AO'!$I:$I,"Closed", 'BA AO'!$N:$N,">="&$B$1, 'BA AO'!$N:$N,"<"&$C$1+1 ) - COUNTIFS( 'BA AO'!$D:$D,"Incident", 'BA AO'!$G:$G,2, 'BA AO'!$U:$U,"<>YES", 'BA AO'!$I:$I,"Triaged", 'BA AO'!$N:$N,">="&$B$1, 'BA AO'!$N:$N,"<"&$C$1+1 ) -> 0 | J8: =COUNTIFS( 'BA AO'!$D:$D,"Incident", 'BA AO'!$G:$G,3, 'BA AO'!$U:$U,"NO", 'BA AO'!$L:$L,">="&$B$1, 'BA AO'!$L:$L,"<"&$C$1+1 ) -> 0 | K8: =SUM( COUNTIFS( 'BA AO'!$D:$D,"Incident", 'BA AO'!$G:$G,3, 'BA AO'!$I:$I,"Closed", 'BA AO'!$U:$U,"NO", 'BA AO'!$N:$N,">="&$B$1, 'BA AO'!$N:$N,"<"&$C$1+1 ), COUNTIFS( 'BA AO'!$D:$D,"Incident", 'BA AO'!$G:$G,3, 'BA AO'!$I:$I,"Triaged", 'BA AO'!$U:$U,"NO", 'BA AO'!$N:$N,">="&$B$1, 'BA AO'!$N:$N,"<"&$C$1+1 ) ) -> 2 | L8: =COUNTIFS( 'BA AO'!$D:$D,"Incident", 'BA AO'!$G:$G,3, 'BA AO'!$U:$U,"<>YES", 'BA AO'!$K:$K,"<"&$B$1, 'BA AO'!$N:$N,"" ) + COUNTIFS( 'BA AO'!$D:$D,"Incident", 'BA AO'!$G:$G,3, 'BA AO'!$U:$U,"<>YES", 'BA AO'!$K:$K,"<"&$B$1, 'BA AO'!$N:$N,">="&$B$1 ) + COUNTIFS( 'BA AO'!$D:$D,"Incident", 'BA AO'!$G:$G,3, 'BA AO'!$U:$U,"<>YES", 'BA AO'!$K:$K,">="&$B$1, 'BA AO'!$K:$K,"<"&$C$1+1 ) - COUNTIFS( 'BA AO'!$D:$D,"Incident", 'BA AO'!$G:$G,3, 'BA AO'!$U:$U,"<>YES", 'BA AO'!$I:$I,"Closed", 'BA AO'!$N:$N,">="&$B$1, 'BA AO'!$N:$N,"<"&$C$1+1 ) - COUNTIFS( 'BA AO'!$D:$D,"Incident", 'BA AO'!$G:$G,3, 'BA AO'!$U:$U,"<>YES", 'BA AO'!$I:$I,"Triaged", 'BA AO'!$N:$N,">="&$B$1, 'BA AO'!$N:$N,"<"&$C$1+1 ) -> 55 | M8: =COUNTIFS( 'BA AO'!$D:$D,"Incident", 'BA AO'!$G:$G,4, 'BA AO'!$U:$U,"NO", 'BA AO'!$L:$L,">="&$B$1, 'BA AO'!$L:$L,"<"&$C$1+1 ) -> 4 | N8: =SUM( COUNTIFS( 'BA AO'!$D:$D,"Incident", 'BA AO'!$G:$G,4, 'BA AO'!$I:$I,"Closed", 'BA AO'!$U:$U,"NO", 'BA AO'!$N:$N,">="&$B$1, 'BA AO'!$N:$N,"<"&$C$1+1 ), COUNTIFS( 'BA AO'!$D:$D,"Incident", 'BA AO'!$G:$G,4, 'BA AO'!$I:$I,"Triaged", 'BA AO'!$U:$U,"NO", 'BA AO'!$N:$N,">="&$B$1, 'BA AO'!$N:$N,"<"&$C$1+1 ) ) -> 3 | O8: =COUNTIFS( 'BA AO'!$D:$D,"Incident", 'BA AO'!$G:$G,4, 'BA AO'!$U:$U,"<>YES", 'BA AO'!$K:$K,"<"&$B$1, 'BA AO'!$N:$N,"" ) + COUNTIFS( 'BA AO'!$D:$D,"Incident", 'BA AO'!$G:$G,4, 'BA AO'!$U:$U,"<>YES", 'BA AO'!$K:$K,"<"&$B$1, 'BA AO'!$N:$N,">="&$B$1 ) + COUNTIFS( 'BA AO'!$D:$D,"Incident", 'BA AO'!$G:$G,4, 'BA AO'!$U:$U,"<>YES", 'BA AO'!$K:$K,">="&$B$1, 'BA AO'!$K:$K,"<"&$C$1+1 ) - COUNTIFS( 'BA AO'!$D:$D,"Incident", 'BA AO'!$G:$G,4, 'BA AO'!$U:$U,"<>YES", 'BA AO'!$I:$I,"Closed", 'BA AO'!$N:$N,">="&$B$1, 'BA AO'!$N:$N,"<"&$C$1+1 ) - COUNTIFS( 'BA AO'!$D:$D,"Incident", 'BA AO'!$G:$G,4, 'BA AO'!$U:$U,"<>YES", 'BA AO'!$I:$I,"Triaged", 'BA AO'!$N:$N,">="&$B$1, 'BA AO'!$N:$N,"<"&$C$1+1 ) -> 56 | P8: =COUNTIFS( 'BA AO'!$D:$D,"RFS", 'BA AO'!$U:$U,"NO", 'BA AO'!$L:$L,">="&$B$1, 'BA AO'!$L:$L,"<"&$C$1+1 ) -> 0 | Q8: =SUM( COUNTIFS( 'BA AO'!$D:$D,"RFS", 'BA AO'!$I:$I,"Closed", 'BA AO'!$U:$U,"NO", 'BA AO'!$N:$N,">="&$B$1, 'BA AO'!$N:$N,"<"&$C$1+1 ), COUNTIFS( 'BA AO'!$D:$D,"RFS", 'BA AO'!$I:$I,"Triaged", 'BA AO'!$U:$U,"NO", 'BA AO'!$N:$N,">="&$B$1, 'BA AO'!$N:$N,"<"&$C$1+1 ) ) -> 1 | R8: =COUNTIFS( 'BA AO'!$D:$D,"RFS", 'BA AO'!$U:$U,"<>YES", 'BA AO'!$K:$K,"<"&$B$1, 'BA AO'!$N:$N,"" ) + COUNTIFS( 'BA AO'!$D:$D,"RFS", 'BA AO'!$U:$U,"<>YES", 'BA AO'!$K:$K,"<"&$B$1, 'BA AO'!$N:$N,">="&$B$1 ) + COUNTIFS( 'BA AO'!$D:$D,"RFS", 'BA AO'!$U:$U,"<>YES", 'BA AO'!$K:$K,">="&$B$1, 'BA AO'!$K:$K,"<"&$C$1+1 ) - COUNTIFS( 'BA AO'!$D:$D,"RFS", 'BA AO'!$I:$I,"Closed", 'BA AO'!$U:$U,"<>YES", 'BA AO'!$N:$N,">="&$B$1, 'BA AO'!$N:$N,"<"&$C$1+1 ) - COUNTIFS( 'BA AO'!$D:$D,"RFS", 'BA AO'!$I:$I,"Triaged", 'BA AO'!$U:$U,"<>YES", 'BA AO'!$N:$N,">="&$B$1, 'BA AO'!$N:$N,"<"&$C$1+1 ) -> 79 | S8: =SUM( COUNTIFS( 'BA AO'!$D:$D,"P_Ticket", 'BA AO'!$G:$G,"Low", 'BA AO'!$U:$U,"NO", 'BA AO'!$L:$L,">="&$B$1, 'BA AO'!$L:$L,"<"&$C$1+1 ), COUNTIFS( 'BA AO'!$D:$D,"P_Ticket", 'BA AO'!$G:$G,"Medium", 'BA AO'!$U:$U,"NO", 'BA AO'!$L:$L,">="&$B$1, 'BA AO'!$L:$L,"<"&$C$1+1 ), COUNTIFS( 'BA AO'!$D:$D,"P_Ticket", 'BA AO'!$G:$G,"High", 'BA AO'!$U:$U,"NO", 'BA AO'!$L:$L,">="&$B$1, 'BA AO'!$L:$L,"<"&$C$1+1 ) ) -> 0 | T8: =SUM(COUNTIFS('BA AO'!$D:$D,"P_Ticket",'BA AO'!$G:$G,"Low",'BA AO'!$I:$I,"Closed",'BA AO'!$U:$U,"NO",'BA AO'!$N:$N,"<"&$C$1+1,'BA AO'!$N:$N,">="&$B$1),COUNTIFS('BA AO'!$D:$D,"P_Ticket",'BA AO'!$G:$G,"Medium",'BA AO'!$I:$I,"Closed",'BA AO'!$U:$U,"NO",'BA AO'!$N:$N,"<"&$C$1+1,'BA AO'!$N:$N,">="&$B$1),COUNTIFS('BA AO'!$D:$D,"P_Ticket",'BA AO'!$G:$G,"High",'BA AO'!$I:$I,"Closed",'BA AO'!$U:$U,"NO",'BA AO'!$N:$N,"<"&$C$1+1,'BA AO'!$N:$N,">="&$B$1),COUNTIFS('BA AO'!$D:$D,"P_Ticket",'BA AO'!$G:$G,"Low",'BA AO'!$I:$I,"Triaged",'BA AO'!$U:$U,"NO",'BA AO'!$N:$N,"<"&$C$1+1,'BA AO'!$N:$N,">="&$B$1),COUNTIFS('BA AO'!$D:$D,"P_Ticket",'BA AO'!$G:$G,"Medium",'BA AO'!$I:$I,"Triaged",'BA AO'!$U:$U,"NO",'BA AO'!$N:$N,"<"&$C$1+1,'BA AO'!$N:$N,">="&$B$1),COUNTIFS('BA AO'!$D:$D,"P_Ticket",'BA AO'!$G:$G,"High",'BA AO'!$I:$I,"Triaged",'BA AO'!$U:$U,"NO",'BA AO'!$N:$N,"<"&$C$1+1,'BA AO'!$N:$N,">="&$B$1)) -> 0 | W8: =COUNTIFS( 'BA AO'!$D:$D,"P_Ticket", 'BA AO'!$G:$G,"High", 'BA AO'!$U:$U,"NO", 'BA AO'!$L:$L,">="&$B$1, 'BA AO'!$L:$L,"<"&$C$1+1 ) -> 0 | X8: =SUM( COUNTIFS( 'BA AO'!$D:$D,"P_Ticket", 'BA AO'!$G:$G,"High", 'BA AO'!$I:$I,"Closed", 'BA AO'!$U:$U,"NO", 'BA AO'!$N:$N,"<"&$C$1+1, 'BA AO'!$N:$N,">="&$B$1 ), COUNTIFS( 'BA AO'!$D:$D,"P_Ticket", 'BA AO'!$G:$G,"High", 'BA AO'!$I:$I,"Triaged", 'BA AO'!$U:$U,"NO", 'BA AO'!$N:$N,"<"&$C$1+1, 'BA AO'!$N:$N,">="&$B$1 ) ) -> 0
A9: APPSUP_BAENTMOBAPPS | B9: BA | C9: Mobile | D9: =COUNTIFS( 'BA Mobile'!$D:$D,"Incident", 'BA Mobile'!$G:$G,1, 'BA Mobile'!$U:$U,"NO", 'BA Mobile'!$L:$L,">="&$B$1, 'BA Mobile'!$L:$L,"<"&$C$1+1 ) -> 0 | E9: =SUM( COUNTIFS( 'BA Mobile'!$D:$D,"Incident", 'BA Mobile'!$G:$G,1, 'BA Mobile'!$I:$I,"Closed", 'BA Mobile'!$U:$U,"NO", 'BA Mobile'!$N:$N,">="&$B$1, 'BA Mobile'!$N:$N,"<"&$C$1+1 ), COUNTIFS( 'BA Mobile'!$D:$D,"Incident", 'BA Mobile'!$G:$G,1, 'BA Mobile'!$I:$I,"Triaged", 'BA Mobile'!$U:$U,"NO", 'BA Mobile'!$N:$N,">="&$B$1, 'BA Mobile'!$N:$N,"<"&$C$1+1 ) ) -> 0 | F9: =COUNTIFS( 'BA Mobile'!$D:$D,"Incident", 'BA Mobile'!$G:$G,1, 'BA Mobile'!$U:$U,"<>YES", 'BA Mobile'!$K:$K,"<"&$B$1, 'BA Mobile'!$N:$N,"" ) + COUNTIFS( 'BA Mobile'!$D:$D,"Incident", 'BA Mobile'!$G:$G,1, 'BA Mobile'!$U:$U,"<>YES", 'BA Mobile'!$K:$K,"<"&$B$1, 'BA Mobile'!$N:$N,">="&$B$1 ) + COUNTIFS( 'BA Mobile'!$D:$D,"Incident", 'BA Mobile'!$G:$G,1, 'BA Mobile'!$U:$U,"<>YES", 'BA Mobile'!$K:$K,">="&$B$1, 'BA Mobile'!$K:$K,"<"&$C$1+1 ) - COUNTIFS( 'BA Mobile'!$D:$D,"Incident", 'BA Mobile'!$G:$G,1, 'BA Mobile'!$U:$U,"<>YES", 'BA Mobile'!$I:$I,"Closed", 'BA Mobile'!$N:$N,">="&$B$1, 'BA Mobile'!$N:$N,"<"&$C$1+1 ) - COUNTIFS( 'BA Mobile'!$D:$D,"Incident", 'BA Mobile'!$G:$G,1, 'BA Mobile'!$U:$U,"<>YES", 'BA Mobile'!$I:$I,"Triaged", 'BA Mobile'!$N:$N,">="&$B$1, 'BA Mobile'!$N:$N,"<"&$C$1+1 ) -> 0 | G9: =COUNTIFS( 'BA Mobile'!$D:$D,"Incident", 'BA Mobile'!$G:$G,2, 'BA Mobile'!$U:$U,"NO", 'BA Mobile'!$L:$L,">="&$B$1, 'BA Mobile'!$L:$L,"<"&$C$1+1 ) -> 0 | H9: =SUM( COUNTIFS( 'BA Mobile'!$D:$D,"Incident", 'BA Mobile'!$G:$G,2, 'BA Mobile'!$I:$I,"Closed", 'BA Mobile'!$U:$U,"NO", 'BA Mobile'!$N:$N,">="&$B$1, 'BA Mobile'!$N:$N,"<"&$C$1+1 ), COUNTIFS( 'BA Mobile'!$D:$D,"Incident", 'BA Mobile'!$G:$G,2, 'BA Mobile'!$I:$I,"Triaged", 'BA Mobile'!$U:$U,"NO", 'BA Mobile'!$N:$N,">="&$B$1, 'BA Mobile'!$N:$N,"<"&$C$1+1 ) ) -> 0 | I9: =COUNTIFS( 'BA Mobile'!$D:$D,"Incident", 'BA Mobile'!$G:$G,2, 'BA Mobile'!$U:$U,"<>YES", 'BA Mobile'!$K:$K,"<"&$B$1, 'BA Mobile'!$N:$N,"" ) + COUNTIFS( 'BA Mobile'!$D:$D,"Incident", 'BA Mobile'!$G:$G,2, 'BA Mobile'!$U:$U,"<>YES", 'BA Mobile'!$K:$K,"<"&$B$1, 'BA Mobile'!$N:$N,">="&$B$1 ) + COUNTIFS( 'BA Mobile'!$D:$D,"Incident", 'BA Mobile'!$G:$G,2, 'BA Mobile'!$U:$U,"<>YES", 'BA Mobile'!$K:$K,">="&$B$1, 'BA Mobile'!$K:$K,"<"&$C$1+1 ) - COUNTIFS( 'BA Mobile'!$D:$D,"Incident", 'BA Mobile'!$G:$G,2, 'BA Mobile'!$U:$U,"<>YES", 'BA Mobile'!$I:$I,"Closed", 'BA Mobile'!$N:$N,">="&$B$1, 'BA Mobile'!$N:$N,"<"&$C$1+1 ) - COUNTIFS( 'BA Mobile'!$D:$D,"Incident", 'BA Mobile'!$G:$G,2, 'BA Mobile'!$U:$U,"<>YES", 'BA Mobile'!$I:$I,"Triaged", 'BA Mobile'!$N:$N,">="&$B$1, 'BA Mobile'!$N:$N,"<"&$C$1+1 ) -> 0 | J9: =COUNTIFS( 'BA Mobile'!$D:$D,"Incident", 'BA Mobile'!$G:$G,3, 'BA Mobile'!$U:$U,"NO", 'BA Mobile'!$L:$L,">="&$B$1, 'BA Mobile'!$L:$L,"<"&$C$1+1 ) -> 0 | K9: =SUM( COUNTIFS( 'BA Mobile'!$D:$D,"Incident", 'BA Mobile'!$G:$G,3, 'BA Mobile'!$I:$I,"Closed", 'BA Mobile'!$U:$U,"NO", 'BA Mobile'!$N:$N,">="&$B$1, 'BA Mobile'!$N:$N,"<"&$C$1+1 ), COUNTIFS( 'BA Mobile'!$D:$D,"Incident", 'BA Mobile'!$G:$G,3, 'BA Mobile'!$I:$I,"Triaged", 'BA Mobile'!$U:$U,"NO", 'BA Mobile'!$N:$N,">="&$B$1, 'BA Mobile'!$N:$N,"<"&$C$1+1 ) ) -> 0 | L9: =COUNTIFS( 'BA Mobile'!$D:$D,"Incident", 'BA Mobile'!$G:$G,3, 'BA Mobile'!$U:$U,"<>YES", 'BA Mobile'!$K:$K,"<"&$B$1, 'BA Mobile'!$N:$N,"" ) + COUNTIFS( 'BA Mobile'!$D:$D,"Incident", 'BA Mobile'!$G:$G,3, 'BA Mobile'!$U:$U,"<>YES", 'BA Mobile'!$K:$K,"<"&$B$1, 'BA Mobile'!$N:$N,">="&$B$1 ) + COUNTIFS( 'BA Mobile'!$D:$D,"Incident", 'BA Mobile'!$G:$G,3, 'BA Mobile'!$U:$U,"<>YES", 'BA Mobile'!$K:$K,">="&$B$1, 'BA Mobile'!$K:$K,"<"&$C$1+1 ) - COUNTIFS( 'BA Mobile'!$D:$D,"Incident", 'BA Mobile'!$G:$G,3, 'BA Mobile'!$U:$U,"<>YES", 'BA Mobile'!$I:$I,"Closed", 'BA Mobile'!$N:$N,">="&$B$1, 'BA Mobile'!$N:$N,"<"&$C$1+1 ) - COUNTIFS( 'BA Mobile'!$D:$D,"Incident", 'BA Mobile'!$G:$G,3, 'BA Mobile'!$U:$U,"<>YES", 'BA Mobile'!$I:$I,"Triaged", 'BA Mobile'!$N:$N,">="&$B$1, 'BA Mobile'!$N:$N,"<"&$C$1+1 ) -> 5 | M9: =COUNTIFS( 'BA Mobile'!$D:$D,"Incident", 'BA Mobile'!$G:$G,4, 'BA Mobile'!$U:$U,"NO", 'BA Mobile'!$L:$L,">="&$B$1, 'BA Mobile'!$L:$L,"<"&$C$1+1 ) -> 0 | N9: =SUM( COUNTIFS( 'BA Mobile'!$D:$D,"Incident", 'BA Mobile'!$G:$G,4, 'BA Mobile'!$I:$I,"Closed", 'BA Mobile'!$U:$U,"NO", 'BA Mobile'!$N:$N,">="&$B$1, 'BA Mobile'!$N:$N,"<"&$C$1+1 ), COUNTIFS( 'BA Mobile'!$D:$D,"Incident", 'BA Mobile'!$G:$G,4, 'BA Mobile'!$I:$I,"Triaged", 'BA Mobile'!$U:$U,"NO", 'BA Mobile'!$N:$N,">="&$B$1, 'BA Mobile'!$N:$N,"<"&$C$1+1 ) ) -> 1 | O9: =COUNTIFS( 'BA Mobile'!$D:$D,"Incident", 'BA Mobile'!$G:$G,4, 'BA Mobile'!$U:$U,"<>YES", 'BA Mobile'!$K:$K,"<"&$B$1, 'BA Mobile'!$N:$N,"" ) + COUNTIFS( 'BA Mobile'!$D:$D,"Incident", 'BA Mobile'!$G:$G,4, 'BA Mobile'!$U:$U,"<>YES", 'BA Mobile'!$K:$K,"<"&$B$1, 'BA Mobile'!$N:$N,">="&$B$1 ) + COUNTIFS( 'BA Mobile'!$D:$D,"Incident", 'BA Mobile'!$G:$G,4, 'BA Mobile'!$U:$U,"<>YES", 'BA Mobile'!$K:$K,">="&$B$1, 'BA Mobile'!$K:$K,"<"&$C$1+1 ) - COUNTIFS( 'BA Mobile'!$D:$D,"Incident", 'BA Mobile'!$G:$G,4, 'BA Mobile'!$U:$U,"<>YES", 'BA Mobile'!$I:$I,"Closed", 'BA Mobile'!$N:$N,">="&$B$1, 'BA Mobile'!$N:$N,"<"&$C$1+1 ) - COUNTIFS( 'BA Mobile'!$D:$D,"Incident", 'BA Mobile'!$G:$G,4, 'BA Mobile'!$U:$U,"<>YES", 'BA Mobile'!$I:$I,"Triaged", 'BA Mobile'!$N:$N,">="&$B$1, 'BA Mobile'!$N:$N,"<"&$C$1+1 ) -> 55 | P9: =COUNTIFS( 'BA Mobile'!$D:$D,"RFS", 'BA Mobile'!$U:$U,"NO", 'BA Mobile'!$L:$L,">="&$B$1, 'BA Mobile'!$L:$L,"<"&$C$1+1 ) -> 0 | Q9: =SUM( COUNTIFS( 'BA Mobile'!$D:$D,"RFS", 'BA Mobile'!$I:$I,"Closed", 'BA Mobile'!$U:$U,"NO", 'BA Mobile'!$N:$N,">="&$B$1, 'BA Mobile'!$N:$N,"<"&$C$1+1 ), COUNTIFS( 'BA Mobile'!$D:$D,"RFS", 'BA Mobile'!$I:$I,"Triaged", 'BA Mobile'!$U:$U,"NO", 'BA Mobile'!$N:$N,">="&$B$1, 'BA Mobile'!$N:$N,"<"&$C$1+1 ) ) -> 0 | R9: =COUNTIFS( 'BA Mobile'!$D:$D,"RFS", 'BA Mobile'!$U:$U,"<>YES", 'BA Mobile'!$K:$K,"<"&$B$1, 'BA Mobile'!$N:$N,"" ) + COUNTIFS( 'BA Mobile'!$D:$D,"RFS", 'BA Mobile'!$U:$U,"<>YES", 'BA Mobile'!$K:$K,"<"&$B$1, 'BA Mobile'!$N:$N,">="&$B$1 ) + COUNTIFS( 'BA Mobile'!$D:$D,"RFS", 'BA Mobile'!$U:$U,"<>YES", 'BA Mobile'!$K:$K,">="&$B$1, 'BA Mobile'!$K:$K,"<"&$C$1+1 ) - COUNTIFS( 'BA Mobile'!$D:$D,"RFS", 'BA Mobile'!$I:$I,"Closed", 'BA Mobile'!$U:$U,"<>YES", 'BA Mobile'!$N:$N,">="&$B$1, 'BA Mobile'!$N:$N,"<"&$C$1+1 ) - COUNTIFS( 'BA Mobile'!$D:$D,"RFS", 'BA Mobile'!$I:$I,"Triaged", 'BA Mobile'!$U:$U,"<>YES", 'BA Mobile'!$N:$N,">="&$B$1, 'BA Mobile'!$N:$N,"<"&$C$1+1 ) -> 7 | S9: =SUM( COUNTIFS( 'BA Mobile'!$D:$D,"P_Ticket", 'BA Mobile'!$G:$G,"Low", 'BA Mobile'!$U:$U,"NO", 'BA Mobile'!$L:$L,">="&$B$1, 'BA Mobile'!$L:$L,"<"&$C$1+1 ), COUNTIFS( 'BA Mobile'!$D:$D,"P_Ticket", 'BA Mobile'!$G:$G,"Medium", 'BA Mobile'!$U:$U,"NO", 'BA Mobile'!$L:$L,">="&$B$1, 'BA Mobile'!$L:$L,"<"&$C$1+1 ), COUNTIFS( 'BA Mobile'!$D:$D,"P_Ticket", 'BA Mobile'!$G:$G,"High", 'BA Mobile'!$U:$U,"NO", 'BA Mobile'!$L:$L,">="&$B$1, 'BA Mobile'!$L:$L,"<"&$C$1+1 ) ) -> 0 | T9: =SUM(COUNTIFS('BA Mobile'!$D:$D,"P_Ticket",'BA Mobile'!$G:$G,"Low",'BA Mobile'!$I:$I,"Closed",'BA Mobile'!$U:$U,"NO",'BA Mobile'!$N:$N,"<"&$C$1+1,'BA Mobile'!$N:$N,">="&$B$1),COUNTIFS('BA Mobile'!$D:$D,"P_Ticket",'BA Mobile'!$G:$G,"Medium",'BA Mobile'!$I:$I,"Closed",'BA Mobile'!$U:$U,"NO",'BA Mobile'!$N:$N,"<"&$C$1+1,'BA Mobile'!$N:$N,">="&$B$1),COUNTIFS('BA Mobile'!$D:$D,"P_Ticket",'BA Mobile'!$G:$G,"High",'BA Mobile'!$I:$I,"Closed",'BA Mobile'!$U:$U,"NO",'BA Mobile'!$N:$N,"<"&$C$1+1,'BA Mobile'!$N:$N,">="&$B$1),COUNTIFS('BA Mobile'!$D:$D,"P_Ticket",'BA Mobile'!$G:$G,"Low",'BA Mobile'!$I:$I,"Triaged",'BA Mobile'!$U:$U,"NO",'BA Mobile'!$N:$N,"<"&$C$1+1,'BA Mobile'!$N:$N,">="&$B$1),COUNTIFS('BA Mobile'!$D:$D,"P_Ticket",'BA Mobile'!$G:$G,"Medium",'BA Mobile'!$I:$I,"Triaged",'BA Mobile'!$U:$U,"NO",'BA Mobile'!$N:$N,"<"&$C$1+1,'BA Mobile'!$N:$N,">="&$B$1),COUNTIFS('BA Mobile'!$D:$D,"P_Ticket",'BA Mobile'!$G:$G,"High",'BA Mobile'!$I:$I,"Triaged",'BA Mobile'!$U:$U,"NO",'BA Mobile'!$N:$N,"<"&$C$1+1,'BA Mobile'!$N:$N,">="&$B$1)) -> 0 | W9: =COUNTIFS( 'BA Mobile'!$D:$D,"P_Ticket", 'BA Mobile'!$G:$G,"High", 'BA Mobile'!$U:$U,"NO", 'BA Mobile'!$L:$L,">="&$B$1, 'BA Mobile'!$L:$L,"<"&$C$1+1 ) -> 0 | X9: =SUM( COUNTIFS( 'BA Mobile'!$D:$D,"P_Ticket", 'BA Mobile'!$G:$G,"High", 'BA Mobile'!$I:$I,"Closed", 'BA Mobile'!$U:$U,"NO", 'BA Mobile'!$N:$N,"<"&$C$1+1, 'BA Mobile'!$N:$N,">="&$B$1 ), COUNTIFS( 'BA Mobile'!$D:$D,"P_Ticket", 'BA Mobile'!$G:$G,"High", 'BA Mobile'!$I:$I,"Triaged", 'BA Mobile'!$U:$U,"NO", 'BA Mobile'!$N:$N,"<"&$C$1+1, 'BA Mobile'!$N:$N,">="&$B$1 ) ) -> 0
A10: APPSUP_FUSION APPSUP_LIDO4D_INTEGRATION | B10: BA | C10: LIP | D10: =COUNTIFS( LIP!$D:$D,"Incident", LIP!$G:$G,1, LIP!$U:$U,"NO", LIP!$L:$L,">="&$B$1, LIP!$L:$L,"<"&$C$1+1 ) -> 0 | E10: =SUM( COUNTIFS( LIP!$D:$D,"Incident", LIP!$G:$G,1, LIP!$I:$I,"Closed", LIP!$U:$U,"NO", LIP!$N:$N,">="&$B$1, LIP!$N:$N,"<"&$C$1+1 ), COUNTIFS( LIP!$D:$D,"Incident", LIP!$G:$G,1, LIP!$I:$I,"Triaged", LIP!$U:$U,"NO", LIP!$N:$N,">="&$B$1, LIP!$N:$N,"<"&$C$1+1 ) ) -> 0 | F10: =COUNTIFS( LIP!$D:$D,"Incident", LIP!$G:$G,1, LIP!$U:$U,"<>YES", LIP!$K:$K,"<"&$B$1, LIP!$N:$N,"" ) + COUNTIFS( LIP!$D:$D,"Incident", LIP!$G:$G,1, LIP!$U:$U,"<>YES", LIP!$K:$K,"<"&$B$1, LIP!$N:$N,">="&$B$1 ) + COUNTIFS( LIP!$D:$D,"Incident", LIP!$G:$G,1, LIP!$U:$U,"<>YES", LIP!$K:$K,">="&$B$1, LIP!$K:$K,"<"&$C$1+1 ) - COUNTIFS( LIP!$D:$D,"Incident", LIP!$G:$G,1, LIP!$I:$I,"Closed", LIP!$U:$U,"<>YES", LIP!$N:$N,">="&$B$1, LIP!$N:$N,"<"&$C$1+1 ) - COUNTIFS( LIP!$D:$D,"Incident", LIP!$G:$G,1, LIP!$I:$I,"Triaged", LIP!$U:$U,"<>YES", LIP!$N:$N,">="&$B$1, LIP!$N:$N,"<"&$C$1+1 ) -> 0 | G10: =COUNTIFS( LIP!$D:$D,"Incident", LIP!$G:$G,2, LIP!$U:$U,"NO", LIP!$L:$L,">="&$B$1, LIP!$L:$L,"<"&$C$1+1 ) -> 0 | H10: =SUM( COUNTIFS( LIP!$D:$D,"Incident", LIP!$G:$G,2, LIP!$I:$I,"Closed", LIP!$U:$U,"NO", LIP!$N:$N,">="&$B$1, LIP!$N:$N,"<"&$C$1+1 ), COUNTIFS( LIP!$D:$D,"Incident", LIP!$G:$G,2, LIP!$I:$I,"Triaged", LIP!$U:$U,"NO", LIP!$N:$N,">="&$B$1, LIP!$N:$N,"<"&$C$1+1 ) ) -> 0 | I10: =COUNTIFS( LIP!$D:$D,"Incident", LIP!$G:$G,2, LIP!$U:$U,"<>YES", LIP!$K:$K,"<"&$B$1, LIP!$N:$N,"" ) + COUNTIFS( LIP!$D:$D,"Incident", LIP!$G:$G,2, LIP!$U:$U,"<>YES", LIP!$K:$K,"<"&$B$1, LIP!$N:$N,">="&$B$1 ) + COUNTIFS( LIP!$D:$D,"Incident", LIP!$G:$G,2, LIP!$U:$U,"<>YES", LIP!$K:$K,">="&$B$1, LIP!$K:$K,"<"&$C$1+1 ) - COUNTIFS( LIP!$D:$D,"Incident", LIP!$G:$G,2, LIP!$I:$I,"Closed", LIP!$U:$U,"<>YES", LIP!$N:$N,">="&$B$1, LIP!$N:$N,"<"&$C$1+1 ) - COUNTIFS( LIP!$D:$D,"Incident", LIP!$G:$G,2, LIP!$I:$I,"Triaged", LIP!$U:$U,"<>YES", LIP!$N:$N,">="&$B$1, LIP!$N:$N,"<"&$C$1+1 ) -> 0 | J10: =COUNTIFS( LIP!$D:$D,"Incident", LIP!$G:$G,3, LIP!$U:$U,"NO", LIP!$L:$L,">="&$B$1, LIP!$L:$L,"<"&$C$1+1 ) -> 1 | K10: =SUM( COUNTIFS( LIP!$D:$D,"Incident", LIP!$G:$G,3, LIP!$I:$I,"Closed", LIP!$U:$U,"NO", LIP!$N:$N,">="&$B$1, LIP!$N:$N,"<"&$C$1+1 ), COUNTIFS( LIP!$D:$D,"Incident", LIP!$G:$G,3, LIP!$I:$I,"Triaged", LIP!$U:$U,"NO", LIP!$N:$N,">="&$B$1, LIP!$N:$N,"<"&$C$1+1 ) ) -> 1 | L10: =COUNTIFS( LIP!$D:$D,"Incident", LIP!$G:$G,3, LIP!$U:$U,"<>YES", LIP!$K:$K,"<"&$B$1, LIP!$N:$N,"" ) + COUNTIFS( LIP!$D:$D,"Incident", LIP!$G:$G,3, LIP!$U:$U,"<>YES", LIP!$K:$K,"<"&$B$1, LIP!$N:$N,">="&$B$1 ) + COUNTIFS( LIP!$D:$D,"Incident", LIP!$G:$G,3, LIP!$U:$U,"<>YES", LIP!$K:$K,">="&$B$1, LIP!$K:$K,"<"&$C$1+1 ) - COUNTIFS( LIP!$D:$D,"Incident", LIP!$G:$G,3, LIP!$I:$I,"Closed", LIP!$U:$U,"<>YES", LIP!$N:$N,">="&$B$1, LIP!$N:$N,"<"&$C$1+1 ) - COUNTIFS( LIP!$D:$D,"Incident", LIP!$G:$G,3, LIP!$I:$I,"Triaged", LIP!$U:$U,"<>YES", LIP!$N:$N,">="&$B$1, LIP!$N:$N,"<"&$C$1+1 ) -> 1 | M10: =COUNTIFS( LIP!$D:$D,"Incident", LIP!$G:$G,4, LIP!$U:$U,"NO", LIP!$L:$L,">="&$B$1, LIP!$L:$L,"<"&$C$1+1 ) -> 26 | N10: =SUM( COUNTIFS( LIP!$D:$D,"Incident", LIP!$G:$G,4, LIP!$I:$I,"Closed", LIP!$U:$U,"NO", LIP!$N:$N,">="&$B$1, LIP!$N:$N,"<"&$C$1+1 ), COUNTIFS( LIP!$D:$D,"Incident", LIP!$G:$G,4, LIP!$I:$I,"Triaged", LIP!$U:$U,"NO", LIP!$N:$N,">="&$B$1, LIP!$N:$N,"<"&$C$1+1 ) ) -> 27 | O10: =COUNTIFS( LIP!$D:$D,"Incident", LIP!$G:$G,4, LIP!$U:$U,"<>YES", LIP!$K:$K,"<"&$B$1, LIP!$N:$N,"" ) + COUNTIFS( LIP!$D:$D,"Incident", LIP!$G:$G,4, LIP!$U:$U,"<>YES", LIP!$K:$K,"<"&$B$1, LIP!$N:$N,">="&$B$1 ) + COUNTIFS( LIP!$D:$D,"Incident", LIP!$G:$G,4, LIP!$U:$U,"<>YES", LIP!$K:$K,">="&$B$1, LIP!$K:$K,"<"&$C$1+1 ) - COUNTIFS( LIP!$D:$D,"Incident", LIP!$G:$G,4, LIP!$I:$I,"Closed", LIP!$U:$U,"<>YES", LIP!$N:$N,">="&$B$1, LIP!$N:$N,"<"&$C$1+1 ) - COUNTIFS( LIP!$D:$D,"Incident", LIP!$G:$G,4, LIP!$I:$I,"Triaged", LIP!$U:$U,"<>YES", LIP!$N:$N,">="&$B$1, LIP!$N:$N,"<"&$C$1+1 ) -> 0 | P10: =COUNTIFS( LIP!$D:$D,"RFS", LIP!$U:$U,"NO", LIP!$L:$L,">="&$B$1, LIP!$L:$L,"<"&$C$1+1 ) -> 0 | Q10: =SUM( COUNTIFS( LIP!$D:$D,"RFS", LIP!$I:$I,"Closed", LIP!$U:$U,"NO", LIP!$N:$N,">="&$B$1, LIP!$N:$N,"<"&$C$1+1 ), COUNTIFS( LIP!$D:$D,"RFS", LIP!$I:$I,"Triaged", LIP!$U:$U,"NO", LIP!$N:$N,">="&$B$1, LIP!$N:$N,"<"&$C$1+1 ) ) -> 0 | R10: =COUNTIFS( LIP!$D:$D,"RFS", LIP!$U:$U,"<>YES", LIP!$K:$K,"<"&$B$1, LIP!$N:$N,"" ) + COUNTIFS( LIP!$D:$D,"RFS", LIP!$U:$U,"<>YES", LIP!$K:$K,"<"&$B$1, LIP!$N:$N,">="&$B$1 ) + COUNTIFS( LIP!$D:$D,"RFS", LIP!$U:$U,"<>YES", LIP!$K:$K,">="&$B$1, LIP!$K:$K,"<"&$C$1+1 ) - COUNTIFS( LIP!$D:$D,"RFS", LIP!$I:$I,"Closed", LIP!$U:$U,"<>YES", LIP!$N:$N,">="&$B$1, LIP!$N:$N,"<"&$C$1+1 ) - COUNTIFS( LIP!$D:$D,"RFS", LIP!$I:$I,"Triaged", LIP!$U:$U,"<>YES", LIP!$N:$N,">="&$B$1, LIP!$N:$N,"<"&$C$1+1 ) -> 3 | S10: =SUM( COUNTIFS( LIP!$D:$D,"P_Ticket", LIP!$G:$G,"Low", LIP!$U:$U,"NO", LIP!$L:$L,">="&$B$1, LIP!$L:$L,"<"&$C$1+1 ), COUNTIFS( LIP!$D:$D,"P_Ticket", LIP!$G:$G,"Medium", LIP!$U:$U,"NO", LIP!$L:$L,">="&$B$1, LIP!$L:$L,"<"&$C$1+1 ), COUNTIFS( LIP!$D:$D,"P_Ticket", LIP!$G:$G,"High", LIP!$U:$U,"NO", LIP!$L:$L,">="&$B$1, LIP!$L:$L,"<"&$C$1+1 ) ) -> 0 | T10: =SUM(COUNTIFS(LIP!$D:$D,"P_Ticket",LIP!$G:$G,"Low",LIP!$I:$I,"Closed",LIP!$U:$U,"NO",LIP!$N:$N,"<"&$C$1+1,LIP!$N:$N,">="&$B$1),COUNTIFS(LIP!$D:$D,"P_Ticket",LIP!$G:$G,"Medium",LIP!$I:$I,"Closed",LIP!$U:$U,"NO",LIP!$N:$N,"<"&$C$1+1,LIP!$N:$N,">="&$B$1),COUNTIFS(LIP!$D:$D,"P_Ticket",LIP!$G:$G,"High",LIP!$I:$I,"Closed",LIP!$U:$U,"NO",LIP!$N:$N,"<"&$C$1+1,LIP!$N:$N,">="&$B$1),COUNTIFS(LIP!$D:$D,"P_Ticket",LIP!$G:$G,"Low",LIP!$I:$I,"Triaged",LIP!$U:$U,"NO",LIP!$N:$N,"<"&$C$1+1,LIP!$N:$N,">="&$B$1),COUNTIFS(LIP!$D:$D,"P_Ticket",LIP!$G:$G,"Medium",LIP!$I:$I,"Triaged",LIP!$U:$U,"NO",LIP!$N:$N,"<"&$C$1+1,LIP!$N:$N,">="&$B$1),COUNTIFS(LIP!$D:$D,"P_Ticket",LIP!$G:$G,"High",LIP!$I:$I,"Triaged",LIP!$U:$U,"NO",LIP!$N:$N,"<"&$C$1+1,LIP!$N:$N,">="&$B$1)) -> 0 | W10: =COUNTIFS( LIP!$D:$D,"P_Ticket", LIP!$G:$G,"High", LIP!$U:$U,"NO", LIP!$L:$L,">="&$B$1, LIP!$L:$L,"<"&$C$1+1 ) -> 0 | X10: =SUM( COUNTIFS( LIP!$D:$D,"P_Ticket", LIP!$G:$G,"High", LIP!$I:$I,"Closed", LIP!$U:$U,"NO", LIP!$N:$N,"<"&$C$1+1, LIP!$N:$N,">="&$B$1 ), COUNTIFS( LIP!$D:$D,"P_Ticket", LIP!$G:$G,"High", LIP!$I:$I,"Triaged", LIP!$U:$U,"NO", LIP!$N:$N,"<"&$C$1+1, LIP!$N:$N,">="&$B$1 ) ) -> 0
A11: APPSUP_QUANTUM | B11: BA | C11: QIP | D11: =COUNTIFS( QIP!$D:$D,"Incident", QIP!$G:$G,1, QIP!$U:$U,"NO", QIP!$L:$L,">="&$B$1, QIP!$L:$L,"<"&$C$1+1 ) -> 0 | E11: =SUM( COUNTIFS( QIP!$D:$D,"Incident", QIP!$G:$G,1, QIP!$I:$I,"Closed", QIP!$U:$U,"NO", QIP!$N:$N,">="&$B$1, QIP!$N:$N,"<"&$C$1+1 ), COUNTIFS( QIP!$D:$D,"Incident", QIP!$G:$G,1, QIP!$I:$I,"Triaged", QIP!$U:$U,"NO", QIP!$N:$N,">="&$B$1, QIP!$N:$N,"<"&$C$1+1 ) ) -> 0 | F11: =COUNTIFS( QIP!$D:$D,"Incident", QIP!$G:$G,1, QIP!$U:$U,"<>YES", QIP!$K:$K,"<"&$B$1, QIP!$N:$N,"" ) + COUNTIFS( QIP!$D:$D,"Incident", QIP!$G:$G,1, QIP!$U:$U,"<>YES", QIP!$K:$K,"<"&$B$1, QIP!$N:$N,">="&$B$1 ) + COUNTIFS( QIP!$D:$D,"Incident", QIP!$G:$G,1, QIP!$U:$U,"<>YES", QIP!$K:$K,">="&$B$1, QIP!$K:$K,"<"&$C$1+1 ) - COUNTIFS( QIP!$D:$D,"Incident", QIP!$G:$G,1, QIP!$I:$I,"Closed", QIP!$U:$U,"<>YES", QIP!$N:$N,">="&$B$1, QIP!$N:$N,"<"&$C$1+1 ) - COUNTIFS( QIP!$D:$D,"Incident", QIP!$G:$G,1, QIP!$I:$I,"Triaged", QIP!$U:$U,"<>YES", QIP!$N:$N,">="&$B$1, QIP!$N:$N,"<"&$C$1+1 ) -> 0 | G11: =COUNTIFS( QIP!$D:$D,"Incident", QIP!$G:$G,2, QIP!$U:$U,"NO", QIP!$L:$L,">="&$B$1, QIP!$L:$L,"<"&$C$1+1 ) -> 0 | H11: =SUM( COUNTIFS( QIP!$D:$D,"Incident", QIP!$G:$G,2, QIP!$I:$I,"Closed", QIP!$U:$U,"NO", QIP!$N:$N,">="&$B$1, QIP!$N:$N,"<"&$C$1+1 ), COUNTIFS( QIP!$D:$D,"Incident", QIP!$G:$G,2, QIP!$I:$I,"Triaged", QIP!$U:$U,"NO", QIP!$N:$N,">="&$B$1, QIP!$N:$N,"<"&$C$1+1 ) ) -> 0 | I11: =COUNTIFS( QIP!$D:$D,"Incident", QIP!$G:$G,2, QIP!$U:$U,"<>YES", QIP!$K:$K,"<"&$B$1, QIP!$N:$N,"" ) + COUNTIFS( QIP!$D:$D,"Incident", QIP!$G:$G,2, QIP!$U:$U,"<>YES", QIP!$K:$K,"<"&$B$1, QIP!$N:$N,">="&$B$1 ) + COUNTIFS( QIP!$D:$D,"Incident", QIP!$G:$G,2, QIP!$U:$U,"<>YES", QIP!$K:$K,">="&$B$1, QIP!$K:$K,"<"&$C$1+1 ) - COUNTIFS( QIP!$D:$D,"Incident", QIP!$G:$G,2, QIP!$I:$I,"Closed", QIP!$U:$U,"<>YES", QIP!$N:$N,">="&$B$1, QIP!$N:$N,"<"&$C$1+1 ) - COUNTIFS( QIP!$D:$D,"Incident", QIP!$G:$G,2, QIP!$I:$I,"Triaged", QIP!$U:$U,"<>YES", QIP!$N:$N,">="&$B$1, QIP!$N:$N,"<"&$C$1+1 ) -> 0 | J11: =COUNTIFS( QIP!$D:$D,"Incident", QIP!$G:$G,3, QIP!$U:$U,"NO", QIP!$L:$L,">="&$B$1, QIP!$L:$L,"<"&$C$1+1 ) -> 5 | K11: =SUM( COUNTIFS( QIP!$D:$D,"Incident", QIP!$G:$G,3, QIP!$I:$I,"Closed", QIP!$U:$U,"NO", QIP!$N:$N,">="&$B$1, QIP!$N:$N,"<"&$C$1+1 ), COUNTIFS( QIP!$D:$D,"Incident", QIP!$G:$G,3, QIP!$I:$I,"Triaged", QIP!$U:$U,"NO", QIP!$N:$N,">="&$B$1, QIP!$N:$N,"<"&$C$1+1 ) ) -> 7 | L11: =COUNTIFS( QIP!$D:$D,"Incident", QIP!$G:$G,3, QIP!$U:$U,"<>YES", QIP!$K:$K,"<"&$B$1, QIP!$N:$N,"" ) + COUNTIFS( QIP!$D:$D,"Incident", QIP!$G:$G,3, QIP!$U:$U,"<>YES", QIP!$K:$K,"<"&$B$1, QIP!$N:$N,">="&$B$1 ) + COUNTIFS( QIP!$D:$D,"Incident", QIP!$G:$G,3, QIP!$U:$U,"<>YES", QIP!$K:$K,">="&$B$1, QIP!$K:$K,"<"&$C$1+1 ) - COUNTIFS( QIP!$D:$D,"Incident", QIP!$G:$G,3, QIP!$I:$I,"Closed", QIP!$U:$U,"<>YES", QIP!$N:$N,">="&$B$1, QIP!$N:$N,"<"&$C$1+1 ) - COUNTIFS( QIP!$D:$D,"Incident", QIP!$G:$G,3, QIP!$I:$I,"Triaged", QIP!$U:$U,"<>YES", QIP!$N:$N,">="&$B$1, QIP!$N:$N,"<"&$C$1+1 ) -> 2 | M11: =COUNTIFS( QIP!$D:$D,"Incident", QIP!$G:$G,4, QIP!$U:$U,"NO", QIP!$L:$L,">="&$B$1, QIP!$L:$L,"<"&$C$1+1 ) -> 42 | N11: =SUM( COUNTIFS( QIP!$D:$D,"Incident", QIP!$G:$G,4, QIP!$I:$I,"Closed", QIP!$U:$U,"NO", QIP!$N:$N,">="&$B$1, QIP!$N:$N,"<"&$C$1+1 ), COUNTIFS( QIP!$D:$D,"Incident", QIP!$G:$G,4, QIP!$I:$I,"Triaged", QIP!$U:$U,"NO", QIP!$N:$N,">="&$B$1, QIP!$N:$N,"<"&$C$1+1 ) ) -> 49 | O11: =COUNTIFS( QIP!$D:$D,"Incident", QIP!$G:$G,4, QIP!$U:$U,"<>YES", QIP!$K:$K,"<"&$B$1, QIP!$N:$N,"" ) + COUNTIFS( QIP!$D:$D,"Incident", QIP!$G:$G,4, QIP!$U:$U,"<>YES", QIP!$K:$K,"<"&$B$1, QIP!$N:$N,">="&$B$1 ) + COUNTIFS( QIP!$D:$D,"Incident", QIP!$G:$G,4, QIP!$U:$U,"<>YES", QIP!$K:$K,">="&$B$1, QIP!$K:$K,"<"&$C$1+1 ) - COUNTIFS( QIP!$D:$D,"Incident", QIP!$G:$G,4, QIP!$I:$I,"Closed", QIP!$U:$U,"<>YES", QIP!$N:$N,">="&$B$1, QIP!$N:$N,"<"&$C$1+1 ) - COUNTIFS( QIP!$D:$D,"Incident", QIP!$G:$G,4, QIP!$I:$I,"Triaged", QIP!$U:$U,"<>YES", QIP!$N:$N,">="&$B$1, QIP!$N:$N,"<"&$C$1+1 ) -> 3 | P11: =COUNTIFS( QIP!$D:$D,"RFS", QIP!$U:$U,"NO", QIP!$L:$L,">="&$B$1, QIP!$L:$L,"<"&$C$1+1 ) -> 8 | Q11: =SUM( COUNTIFS( QIP!$D:$D,"RFS", QIP!$I:$I,"Closed", QIP!$U:$U,"NO", QIP!$N:$N,">="&$B$1, QIP!$N:$N,"<"&$C$1+1 ), COUNTIFS( QIP!$D:$D,"RFS", QIP!$I:$I,"Triaged", QIP!$U:$U,"NO", QIP!$N:$N,">="&$B$1, QIP!$N:$N,"<"&$C$1+1 ) ) -> 9 | R11: =COUNTIFS( QIP!$D:$D,"RFS", QIP!$U:$U,"<>YES", QIP!$K:$K,"<"&$B$1, QIP!$N:$N,"" ) + COUNTIFS( QIP!$D:$D,"RFS", QIP!$U:$U,"<>YES", QIP!$K:$K,"<"&$B$1, QIP!$N:$N,">="&$B$1 ) + COUNTIFS( QIP!$D:$D,"RFS", QIP!$U:$U,"<>YES", QIP!$K:$K,">="&$B$1, QIP!$K:$K,"<"&$C$1+1 ) - COUNTIFS( QIP!$D:$D,"RFS", QIP!$I:$I,"Closed", QIP!$U:$U,"<>YES", QIP!$N:$N,">="&$B$1, QIP!$N:$N,"<"&$C$1+1 ) - COUNTIFS( QIP!$D:$D,"RFS", QIP!$I:$I,"Triaged", QIP!$U:$U,"<>YES", QIP!$N:$N,">="&$B$1, QIP!$N:$N,"<"&$C$1+1 ) -> 4 | S11: =SUM( COUNTIFS( QIP!$D:$D,"P_Ticket", QIP!$G:$G,"Low", QIP!$U:$U,"NO", QIP!$L:$L,">="&$B$1, QIP!$L:$L,"<"&$C$1+1 ), COUNTIFS( QIP!$D:$D,"P_Ticket", QIP!$G:$G,"Medium", QIP!$U:$U,"NO", QIP!$L:$L,">="&$B$1, QIP!$L:$L,"<"&$C$1+1 ), COUNTIFS( QIP!$D:$D,"P_Ticket", QIP!$G:$G,"High", QIP!$U:$U,"NO", QIP!$L:$L,">="&$B$1, QIP!$L:$L,"<"&$C$1+1 ) ) -> 0 | T11: =SUM(COUNTIFS(QIP!$D:$D,"P_Ticket",QIP!$G:$G,"Low",QIP!$I:$I,"Closed",QIP!$U:$U,"NO",QIP!$N:$N,"<"&$C$1+1,QIP!$N:$N,">="&$B$1),COUNTIFS(QIP!$D:$D,"P_Ticket",QIP!$G:$G,"Medium",QIP!$I:$I,"Closed",QIP!$U:$U,"NO",QIP!$N:$N,"<"&$C$1+1,QIP!$N:$N,">="&$B$1),COUNTIFS(QIP!$D:$D,"P_Ticket",QIP!$G:$G,"High",QIP!$I:$I,"Closed",QIP!$U:$U,"NO",QIP!$N:$N,"<"&$C$1+1,QIP!$N:$N,">="&$B$1),COUNTIFS(QIP!$D:$D,"P_Ticket",QIP!$G:$G,"Low",QIP!$I:$I,"Triaged",QIP!$U:$U,"NO",QIP!$N:$N,"<"&$C$1+1,QIP!$N:$N,">="&$B$1),COUNTIFS(QIP!$D:$D,"P_Ticket",QIP!$G:$G,"Medium",QIP!$I:$I,"Triaged",QIP!$U:$U,"NO",QIP!$N:$N,"<"&$C$1+1,QIP!$N:$N,">="&$B$1),COUNTIFS(QIP!$D:$D,"P_Ticket",QIP!$G:$G,"High",QIP!$I:$I,"Triaged",QIP!$U:$U,"NO",QIP!$N:$N,"<"&$C$1+1,QIP!$N:$N,">="&$B$1)) -> 0 | W11: =COUNTIFS( QIP!$D:$D,"P_Ticket", QIP!$G:$G,"High", QIP!$U:$U,"NO", QIP!$L:$L,">="&$B$1, QIP!$L:$L,"<"&$C$1+1 ) -> 0 | X11: =SUM( COUNTIFS( QIP!$D:$D,"P_Ticket", QIP!$G:$G,"High", QIP!$I:$I,"Closed", QIP!$U:$U,"NO", QIP!$N:$N,"<"&$C$1+1, QIP!$N:$N,">="&$B$1 ), COUNTIFS( QIP!$D:$D,"P_Ticket", QIP!$G:$G,"High", QIP!$I:$I,"Triaged", QIP!$U:$U,"NO", QIP!$N:$N,"<"&$C$1+1, QIP!$N:$N,">="&$B$1 ) ) -> 0
B12: BA | C12: MRO | D12: =COUNTIFS( 'BA MRO'!$D:$D,"Incident", 'BA MRO'!$G:$G,1, 'BA MRO'!$U:$U,"NO", 'BA MRO'!$L:$L,">="&$B$1, 'BA MRO'!$L:$L,"<"&$C$1+1 ) -> 0 | E12: =SUM( COUNTIFS( 'BA MRO'!$D:$D,"Incident", 'BA MRO'!$G:$G,1, 'BA MRO'!$I:$I,"Closed", 'BA MRO'!$U:$U,"NO", 'BA MRO'!$N:$N,">="&$B$1, 'BA MRO'!$N:$N,"<"&$C$1+1 ), COUNTIFS( 'BA MRO'!$D:$D,"Incident", 'BA MRO'!$G:$G,1, 'BA MRO'!$I:$I,"Triaged", 'BA MRO'!$U:$U,"NO", 'BA MRO'!$N:$N,">="&$B$1, 'BA MRO'!$N:$N,"<"&$C$1+1 ) ) -> 0 | F12: =COUNTIFS( 'BA MRO'!$D:$D,"Incident", 'BA MRO'!$G:$G,1, 'BA MRO'!$U:$U,"<>YES", 'BA MRO'!$K:$K,"<"&$B$1, 'BA MRO'!$N:$N,"" ) + COUNTIFS( 'BA MRO'!$D:$D,"Incident", 'BA MRO'!$G:$G,1, 'BA MRO'!$U:$U,"<>YES", 'BA MRO'!$K:$K,"<"&$B$1, 'BA MRO'!$N:$N,">="&$B$1 ) + COUNTIFS( 'BA MRO'!$D:$D,"Incident", 'BA MRO'!$G:$G,1, 'BA MRO'!$U:$U,"<>YES", 'BA MRO'!$K:$K,">="&$B$1, 'BA MRO'!$K:$K,"<"&$C$1+1 ) - COUNTIFS( 'BA MRO'!$D:$D,"Incident", 'BA MRO'!$G:$G,1, 'BA MRO'!$U:$U,"<>YES", 'BA MRO'!$I:$I,"Closed", 'BA MRO'!$N:$N,">="&$B$1, 'BA MRO'!$N:$N,"<"&$C$1+1 ) - COUNTIFS( 'BA MRO'!$D:$D,"Incident", 'BA MRO'!$G:$G,1, 'BA MRO'!$U:$U,"<>YES", 'BA MRO'!$I:$I,"Triaged", 'BA MRO'!$N:$N,">="&$B$1, 'BA MRO'!$N:$N,"<"&$C$1+1 ) -> 0 | G12: =COUNTIFS( 'BA MRO'!$D:$D,"Incident", 'BA MRO'!$G:$G,2, 'BA MRO'!$U:$U,"NO", 'BA MRO'!$L:$L,">="&$B$1, 'BA MRO'!$L:$L,"<"&$C$1+1 ) -> 0 | H12: =SUM( COUNTIFS( 'BA MRO'!$D:$D,"Incident", 'BA MRO'!$G:$G,2, 'BA MRO'!$I:$I,"Closed", 'BA MRO'!$U:$U,"NO", 'BA MRO'!$N:$N,">="&$B$1, 'BA MRO'!$N:$N,"<"&$C$1+1 ), COUNTIFS( 'BA MRO'!$D:$D,"Incident", 'BA MRO'!$G:$G,2, 'BA MRO'!$I:$I,"Triaged", 'BA MRO'!$U:$U,"NO", 'BA MRO'!$N:$N,">="&$B$1, 'BA MRO'!$N:$N,"<"&$C$1+1 ) ) -> 0 | I12: =COUNTIFS( 'BA MRO'!$D:$D,"Incident", 'BA MRO'!$G:$G,2, 'BA MRO'!$U:$U,"<>YES", 'BA MRO'!$K:$K,"<"&$B$1, 'BA MRO'!$N:$N,"" ) + COUNTIFS( 'BA MRO'!$D:$D,"Incident", 'BA MRO'!$G:$G,2, 'BA MRO'!$U:$U,"<>YES", 'BA MRO'!$K:$K,"<"&$B$1, 'BA MRO'!$N:$N,">="&$B$1 ) + COUNTIFS( 'BA MRO'!$D:$D,"Incident", 'BA MRO'!$G:$G,2, 'BA MRO'!$U:$U,"<>YES", 'BA MRO'!$K:$K,">="&$B$1, 'BA MRO'!$K:$K,"<"&$C$1+1 ) - COUNTIFS( 'BA MRO'!$D:$D,"Incident", 'BA MRO'!$G:$G,2, 'BA MRO'!$U:$U,"<>YES", 'BA MRO'!$I:$I,"Closed", 'BA MRO'!$N:$N,">="&$B$1, 'BA MRO'!$N:$N,"<"&$C$1+1 ) - COUNTIFS( 'BA MRO'!$D:$D,"Incident", 'BA MRO'!$G:$G,2, 'BA MRO'!$U:$U,"<>YES", 'BA MRO'!$I:$I,"Triaged", 'BA MRO'!$N:$N,">="&$B$1, 'BA MRO'!$N:$N,"<"&$C$1+1 ) -> 0 | J12: =COUNTIFS( 'BA MRO'!$D:$D,"Incident", 'BA MRO'!$G:$G,3, 'BA MRO'!$U:$U,"NO", 'BA MRO'!$L:$L,">="&$B$1, 'BA MRO'!$L:$L,"<"&$C$1+1 ) -> 0 | K12: =SUM( COUNTIFS( 'BA MRO'!$D:$D,"Incident", 'BA MRO'!$G:$G,3, 'BA MRO'!$I:$I,"Closed", 'BA MRO'!$U:$U,"NO", 'BA MRO'!$N:$N,">="&$B$1, 'BA MRO'!$N:$N,"<"&$C$1+1 ), COUNTIFS( 'BA MRO'!$D:$D,"Incident", 'BA MRO'!$G:$G,3, 'BA MRO'!$I:$I,"Triaged", 'BA MRO'!$U:$U,"NO", 'BA MRO'!$N:$N,">="&$B$1, 'BA MRO'!$N:$N,"<"&$C$1+1 ) ) -> 0 | L12: =COUNTIFS( 'BA MRO'!$D:$D,"Incident", 'BA MRO'!$G:$G,3, 'BA MRO'!$U:$U,"<>YES", 'BA MRO'!$K:$K,"<"&$B$1, 'BA MRO'!$N:$N,"" ) + COUNTIFS( 'BA MRO'!$D:$D,"Incident", 'BA MRO'!$G:$G,3, 'BA MRO'!$U:$U,"<>YES", 'BA MRO'!$K:$K,"<"&$B$1, 'BA MRO'!$N:$N,">="&$B$1 ) + COUNTIFS( 'BA MRO'!$D:$D,"Incident", 'BA MRO'!$G:$G,3, 'BA MRO'!$U:$U,"<>YES", 'BA MRO'!$K:$K,">="&$B$1, 'BA MRO'!$K:$K,"<"&$C$1+1 ) - COUNTIFS( 'BA MRO'!$D:$D,"Incident", 'BA MRO'!$G:$G,3, 'BA MRO'!$U:$U,"<>YES", 'BA MRO'!$I:$I,"Closed", 'BA MRO'!$N:$N,">="&$B$1, 'BA MRO'!$N:$N,"<"&$C$1+1 ) - COUNTIFS( 'BA MRO'!$D:$D,"Incident", 'BA MRO'!$G:$G,3, 'BA MRO'!$U:$U,"<>YES", 'BA MRO'!$I:$I,"Triaged", 'BA MRO'!$N:$N,">="&$B$1, 'BA MRO'!$N:$N,"<"&$C$1+1 ) -> 0 | M12: =COUNTIFS( 'BA MRO'!$D:$D,"Incident", 'BA MRO'!$G:$G,4, 'BA MRO'!$U:$U,"NO", 'BA MRO'!$L:$L,">="&$B$1, 'BA MRO'!$L:$L,"<"&$C$1+1 ) -> 0 | N12: =SUM( COUNTIFS( 'BA MRO'!$D:$D,"Incident", 'BA MRO'!$G:$G,4, 'BA MRO'!$I:$I,"Closed", 'BA MRO'!$U:$U,"NO", 'BA MRO'!$N:$N,">="&$B$1, 'BA MRO'!$N:$N,"<"&$C$1+1 ), COUNTIFS( 'BA MRO'!$D:$D,"Incident", 'BA MRO'!$G:$G,4, 'BA MRO'!$I:$I,"Triaged", 'BA MRO'!$U:$U,"NO", 'BA MRO'!$N:$N,">="&$B$1, 'BA MRO'!$N:$N,"<"&$C$1+1 ) ) -> 0 | O12: =COUNTIFS( 'BA MRO'!$D:$D,"Incident", 'BA MRO'!$G:$G,4, 'BA MRO'!$U:$U,"<>YES", 'BA MRO'!$K:$K,"<"&$B$1, 'BA MRO'!$N:$N,"" ) + COUNTIFS( 'BA MRO'!$D:$D,"Incident", 'BA MRO'!$G:$G,4, 'BA MRO'!$U:$U,"<>YES", 'BA MRO'!$K:$K,"<"&$B$1, 'BA MRO'!$N:$N,">="&$B$1 ) + COUNTIFS( 'BA MRO'!$D:$D,"Incident", 'BA MRO'!$G:$G,4, 'BA MRO'!$U:$U,"<>YES", 'BA MRO'!$K:$K,">="&$B$1, 'BA MRO'!$K:$K,"<"&$C$1+1 ) - COUNTIFS( 'BA MRO'!$D:$D,"Incident", 'BA MRO'!$G:$G,4, 'BA MRO'!$U:$U,"<>YES", 'BA MRO'!$I:$I,"Closed", 'BA MRO'!$N:$N,">="&$B$1, 'BA MRO'!$N:$N,"<"&$C$1+1 ) - COUNTIFS( 'BA MRO'!$D:$D,"Incident", 'BA MRO'!$G:$G,4, 'BA MRO'!$U:$U,"<>YES", 'BA MRO'!$I:$I,"Triaged", 'BA MRO'!$N:$N,">="&$B$1, 'BA MRO'!$N:$N,"<"&$C$1+1 ) -> 0 | P12: =COUNTIFS( 'BA MRO'!$D:$D,"RFS", 'BA MRO'!$U:$U,"NO", 'BA MRO'!$L:$L,">="&$B$1, 'BA MRO'!$L:$L,"<"&$C$1+1 ) -> 0 | Q12: =SUM( COUNTIFS( 'BA MRO'!$D:$D,"RFS", 'BA MRO'!$I:$I,"Closed", 'BA MRO'!$U:$U,"NO", 'BA MRO'!$N:$N,">="&$B$1, 'BA MRO'!$N:$N,"<"&$C$1+1 ), COUNTIFS( 'BA MRO'!$D:$D,"RFS", 'BA MRO'!$I:$I,"Triaged", 'BA MRO'!$U:$U,"NO", 'BA MRO'!$N:$N,">="&$B$1, 'BA MRO'!$N:$N,"<"&$C$1+1 ) ) -> 0 | R12: =COUNTIFS( 'BA MRO'!$D:$D,"RFS", 'BA MRO'!$U:$U,"<>YES", 'BA MRO'!$K:$K,"<"&$B$1, 'BA MRO'!$N:$N,"" ) + COUNTIFS( 'BA MRO'!$D:$D,"RFS", 'BA MRO'!$U:$U,"<>YES", 'BA MRO'!$K:$K,"<"&$B$1, 'BA MRO'!$N:$N,">="&$B$1 ) + COUNTIFS( 'BA MRO'!$D:$D,"RFS", 'BA MRO'!$U:$U,"<>YES", 'BA MRO'!$K:$K,">="&$B$1, 'BA MRO'!$K:$K,"<"&$C$1+1 ) - COUNTIFS( 'BA MRO'!$D:$D,"RFS", 'BA MRO'!$I:$I,"Closed", 'BA MRO'!$U:$U,"<>YES", 'BA MRO'!$N:$N,">="&$B$1, 'BA MRO'!$N:$N,"<"&$C$1+1 ) - COUNTIFS( 'BA MRO'!$D:$D,"RFS", 'BA MRO'!$I:$I,"Triaged", 'BA MRO'!$U:$U,"<>YES", 'BA MRO'!$N:$N,">="&$B$1, 'BA MRO'!$N:$N,"<"&$C$1+1 ) -> 0 | S12: =SUM( COUNTIFS( 'BA MRO'!$D:$D,"P_Ticket", 'BA MRO'!$G:$G,"Low", 'BA MRO'!$U:$U,"NO", 'BA MRO'!$L:$L,">="&$B$1, 'BA MRO'!$L:$L,"<"&$C$1+1 ), COUNTIFS( 'BA MRO'!$D:$D,"P_Ticket", 'BA MRO'!$G:$G,"Medium", 'BA MRO'!$U:$U,"NO", 'BA MRO'!$L:$L,">="&$B$1, 'BA MRO'!$L:$L,"<"&$C$1+1 ), COUNTIFS( 'BA MRO'!$D:$D,"P_Ticket", 'BA MRO'!$G:$G,"High", 'BA MRO'!$U:$U,"NO", 'BA MRO'!$L:$L,">="&$B$1, 'BA MRO'!$L:$L,"<"&$C$1+1 ) ) -> 0 | T12: =SUM(COUNTIFS('BA MRO'!$D:$D,"P_Ticket",'BA MRO'!$G:$G,"Low",'BA MRO'!$I:$I,"Closed",'BA MRO'!$U:$U,"NO",'BA MRO'!$N:$N,"<"&$C$1+1,'BA MRO'!$N:$N,">="&$B$1),COUNTIFS('BA MRO'!$D:$D,"P_Ticket",'BA MRO'!$G:$G,"Medium",'BA MRO'!$I:$I,"Closed",'BA MRO'!$U:$U,"NO",'BA MRO'!$N:$N,"<"&$C$1+1,'BA MRO'!$N:$N,">="&$B$1),COUNTIFS('BA MRO'!$D:$D,"P_Ticket",'BA MRO'!$G:$G,"High",'BA MRO'!$I:$I,"Closed",'BA MRO'!$U:$U,"NO",'BA MRO'!$N:$N,"<"&$C$1+1,'BA MRO'!$N:$N,">="&$B$1),COUNTIFS('BA MRO'!$D:$D,"P_Ticket",'BA MRO'!$G:$G,"Low",'BA MRO'!$I:$I,"Triaged",'BA MRO'!$U:$U,"NO",'BA MRO'!$N:$N,"<"&$C$1+1,'BA MRO'!$N:$N,">="&$B$1),COUNTIFS('BA MRO'!$D:$D,"P_Ticket",'BA MRO'!$G:$G,"Medium",'BA MRO'!$I:$I,"Triaged",'BA MRO'!$U:$U,"NO",'BA MRO'!$N:$N,"<"&$C$1+1,'BA MRO'!$N:$N,">="&$B$1),COUNTIFS('BA MRO'!$D:$D,"P_Ticket",'BA MRO'!$G:$G,"High",'BA MRO'!$I:$I,"Triaged",'BA MRO'!$U:$U,"NO",'BA MRO'!$N:$N,"<"&$C$1+1,'BA MRO'!$N:$N,">="&$B$1)) -> 0 | W12: =COUNTIFS( 'BA MRO'!$D:$D,"P_Ticket", 'BA MRO'!$G:$G,"High", 'BA MRO'!$U:$U,"NO", 'BA MRO'!$L:$L,">="&$B$1, 'BA MRO'!$L:$L,"<"&$C$1+1 ) -> 0 | X12: =SUM( COUNTIFS( 'BA MRO'!$D:$D,"P_Ticket", 'BA MRO'!$G:$G,"High", 'BA MRO'!$I:$I,"Closed", 'BA MRO'!$U:$U,"NO", 'BA MRO'!$N:$N,"<"&$C$1+1, 'BA MRO'!$N:$N,">="&$B$1 ), COUNTIFS( 'BA MRO'!$D:$D,"P_Ticket", 'BA MRO'!$G:$G,"High", 'BA MRO'!$I:$I,"Triaged", 'BA MRO'!$U:$U,"NO", 'BA MRO'!$N:$N,"<"&$C$1+1, 'BA MRO'!$N:$N,">="&$B$1 ) ) -> 0
A13: APPSUP_CRPDIR APPSUP_MGZE | B13: BA | C13: Pathway | D13: =COUNTIFS( Pathway!$D:$D,"Incident", Pathway!$G:$G,1, Pathway!$U:$U,"NO", Pathway!$L:$L,">="&$B$1, Pathway!$L:$L,"<"&$C$1+1 ) -> 0 | E13: =SUM( COUNTIFS( Pathway!$D:$D,"Incident", Pathway!$G:$G,1, Pathway!$I:$I,"Closed", Pathway!$U:$U,"NO", Pathway!$N:$N,">="&$B$1, Pathway!$N:$N,"<"&$C$1+1 ), COUNTIFS( Pathway!$D:$D,"Incident", Pathway!$G:$G,1, Pathway!$I:$I,"Triaged", Pathway!$U:$U,"NO", Pathway!$N:$N,">="&$B$1, Pathway!$N:$N,"<"&$C$1+1 ) ) -> 0 | F13: =COUNTIFS( Pathway!$D:$D,"Incident", Pathway!$G:$G,1, Pathway!$U:$U,"<>YES", Pathway!$K:$K,"<"&$B$1, Pathway!$N:$N,"" ) + COUNTIFS( Pathway!$D:$D,"Incident", Pathway!$G:$G,1, Pathway!$U:$U,"<>YES", Pathway!$K:$K,"<"&$B$1, Pathway!$N:$N,">="&$B$1 ) + COUNTIFS( Pathway!$D:$D,"Incident", Pathway!$G:$G,1, Pathway!$U:$U,"<>YES", Pathway!$K:$K,">="&$B$1, Pathway!$K:$K,"<"&$C$1+1 ) - COUNTIFS( Pathway!$D:$D,"Incident", Pathway!$G:$G,1, Pathway!$I:$I,"Closed", Pathway!$U:$U,"<>YES", Pathway!$N:$N,">="&$B$1, Pathway!$N:$N,"<"&$C$1+1 ) - COUNTIFS( Pathway!$D:$D,"Incident", Pathway!$G:$G,1, Pathway!$I:$I,"Triaged", Pathway!$U:$U,"<>YES", Pathway!$N:$N,">="&$B$1, Pathway!$N:$N,"<"&$C$1+1 ) -> 0 | G13: =COUNTIFS( Pathway!$D:$D,"Incident", Pathway!$G:$G,2, Pathway!$U:$U,"NO", Pathway!$L:$L,">="&$B$1, Pathway!$L:$L,"<"&$C$1+1 ) -> 0 | H13: =SUM( COUNTIFS( Pathway!$D:$D,"Incident", Pathway!$G:$G,2, Pathway!$I:$I,"Closed", Pathway!$U:$U,"NO", Pathway!$N:$N,">="&$B$1, Pathway!$N:$N,"<"&$C$1+1 ), COUNTIFS( Pathway!$D:$D,"Incident", Pathway!$G:$G,2, Pathway!$I:$I,"Triaged", Pathway!$U:$U,"NO", Pathway!$N:$N,">="&$B$1, Pathway!$N:$N,"<"&$C$1+1 ) ) -> 0 | I13: =COUNTIFS( Pathway!$D:$D,"Incident", Pathway!$G:$G,2, Pathway!$U:$U,"<>YES", Pathway!$K:$K,"<"&$B$1, Pathway!$N:$N,"" ) + COUNTIFS( Pathway!$D:$D,"Incident", Pathway!$G:$G,2, Pathway!$U:$U,"<>YES", Pathway!$K:$K,"<"&$B$1, Pathway!$N:$N,">="&$B$1 ) + COUNTIFS( Pathway!$D:$D,"Incident", Pathway!$G:$G,2, Pathway!$U:$U,"<>YES", Pathway!$K:$K,">="&$B$1, Pathway!$K:$K,"<"&$C$1+1 ) - COUNTIFS( Pathway!$D:$D,"Incident", Pathway!$G:$G,2, Pathway!$I:$I,"Closed", Pathway!$U:$U,"<>YES", Pathway!$N:$N,">="&$B$1, Pathway!$N:$N,"<"&$C$1+1 ) - COUNTIFS( Pathway!$D:$D,"Incident", Pathway!$G:$G,2, Pathway!$I:$I,"Triaged", Pathway!$U:$U,"<>YES", Pathway!$N:$N,">="&$B$1, Pathway!$N:$N,"<"&$C$1+1 ) -> 0 | J13: =COUNTIFS( Pathway!$D:$D,"Incident", Pathway!$G:$G,3, Pathway!$U:$U,"NO", Pathway!$L:$L,">="&$B$1, Pathway!$L:$L,"<"&$C$1+1 ) -> 3 | K13: =SUM( COUNTIFS( Pathway!$D:$D,"Incident", Pathway!$G:$G,3, Pathway!$I:$I,"Closed", Pathway!$U:$U,"NO", Pathway!$N:$N,">="&$B$1, Pathway!$N:$N,"<"&$C$1+1 ), COUNTIFS( Pathway!$D:$D,"Incident", Pathway!$G:$G,3, Pathway!$I:$I,"Triaged", Pathway!$U:$U,"NO", Pathway!$N:$N,">="&$B$1, Pathway!$N:$N,"<"&$C$1+1 ) ) -> 8 | L13: =COUNTIFS( Pathway!$D:$D,"Incident", Pathway!$G:$G,3, Pathway!$U:$U,"<>YES", Pathway!$K:$K,"<"&$B$1, Pathway!$N:$N,"" ) + COUNTIFS( Pathway!$D:$D,"Incident", Pathway!$G:$G,3, Pathway!$U:$U,"<>YES", Pathway!$K:$K,"<"&$B$1, Pathway!$N:$N,">="&$B$1 ) + COUNTIFS( Pathway!$D:$D,"Incident", Pathway!$G:$G,3, Pathway!$U:$U,"<>YES", Pathway!$K:$K,">="&$B$1, Pathway!$K:$K,"<"&$C$1+1 ) - COUNTIFS( Pathway!$D:$D,"Incident", Pathway!$G:$G,3, Pathway!$I:$I,"Closed", Pathway!$U:$U,"<>YES", Pathway!$N:$N,">="&$B$1, Pathway!$N:$N,"<"&$C$1+1 ) - COUNTIFS( Pathway!$D:$D,"Incident", Pathway!$G:$G,3, Pathway!$I:$I,"Triaged", Pathway!$U:$U,"<>YES", Pathway!$N:$N,">="&$B$1, Pathway!$N:$N,"<"&$C$1+1 ) -> 6 | M13: =COUNTIFS( Pathway!$D:$D,"Incident", Pathway!$G:$G,4, Pathway!$U:$U,"NO", Pathway!$L:$L,">="&$B$1, Pathway!$L:$L,"<"&$C$1+1 ) -> 5 | N13: =SUM( COUNTIFS( Pathway!$D:$D,"Incident", Pathway!$G:$G,4, Pathway!$I:$I,"Closed", Pathway!$U:$U,"NO", Pathway!$N:$N,">="&$B$1, Pathway!$N:$N,"<"&$C$1+1 ), COUNTIFS( Pathway!$D:$D,"Incident", Pathway!$G:$G,4, Pathway!$I:$I,"Triaged", Pathway!$U:$U,"NO", Pathway!$N:$N,">="&$B$1, Pathway!$N:$N,"<"&$C$1+1 ) ) -> 3 | O13: =COUNTIFS( Pathway!$D:$D,"Incident", Pathway!$G:$G,4, Pathway!$U:$U,"<>YES", Pathway!$K:$K,"<"&$B$1, Pathway!$N:$N,"" ) + COUNTIFS( Pathway!$D:$D,"Incident", Pathway!$G:$G,4, Pathway!$U:$U,"<>YES", Pathway!$K:$K,"<"&$B$1, Pathway!$N:$N,">="&$B$1 ) + COUNTIFS( Pathway!$D:$D,"Incident", Pathway!$G:$G,4, Pathway!$U:$U,"<>YES", Pathway!$K:$K,">="&$B$1, Pathway!$K:$K,"<"&$C$1+1 ) - COUNTIFS( Pathway!$D:$D,"Incident", Pathway!$G:$G,4, Pathway!$I:$I,"Closed", Pathway!$U:$U,"<>YES", Pathway!$N:$N,">="&$B$1, Pathway!$N:$N,"<"&$C$1+1 ) - COUNTIFS( Pathway!$D:$D,"Incident", Pathway!$G:$G,4, Pathway!$I:$I,"Triaged", Pathway!$U:$U,"<>YES", Pathway!$N:$N,">="&$B$1, Pathway!$N:$N,"<"&$C$1+1 ) -> 19 | P13: =COUNTIFS( Pathway!$D:$D,"RFS", Pathway!$U:$U,"NO", Pathway!$L:$L,">="&$B$1, Pathway!$L:$L,"<"&$C$1+1 ) -> 5 | Q13: =SUM( COUNTIFS( Pathway!$D:$D,"RFS", Pathway!$I:$I,"Closed", Pathway!$U:$U,"NO", Pathway!$N:$N,">="&$B$1, Pathway!$N:$N,"<"&$C$1+1 ), COUNTIFS( Pathway!$D:$D,"RFS", Pathway!$I:$I,"Triaged", Pathway!$U:$U,"NO", Pathway!$N:$N,">="&$B$1, Pathway!$N:$N,"<"&$C$1+1 ) ) -> 13 | R13: =COUNTIFS( Pathway!$D:$D,"RFS", Pathway!$U:$U,"<>YES", Pathway!$K:$K,"<"&$B$1, Pathway!$N:$N,"" ) + COUNTIFS( Pathway!$D:$D,"RFS", Pathway!$U:$U,"<>YES", Pathway!$K:$K,"<"&$B$1, Pathway!$N:$N,">="&$B$1 ) + COUNTIFS( Pathway!$D:$D,"RFS", Pathway!$U:$U,"<>YES", Pathway!$K:$K,">="&$B$1, Pathway!$K:$K,"<"&$C$1+1 ) - COUNTIFS( Pathway!$D:$D,"RFS", Pathway!$I:$I,"Closed", Pathway!$U:$U,"<>YES", Pathway!$N:$N,">="&$B$1, Pathway!$N:$N,"<"&$C$1+1 ) - COUNTIFS( Pathway!$D:$D,"RFS", Pathway!$I:$I,"Triaged", Pathway!$U:$U,"<>YES", Pathway!$N:$N,">="&$B$1, Pathway!$N:$N,"<"&$C$1+1 ) -> 28 | S13: =SUM( COUNTIFS( Pathway!$D:$D,"P_Ticket", Pathway!$G:$G,"Low", Pathway!$U:$U,"NO", Pathway!$L:$L,">="&$B$1, Pathway!$L:$L,"<"&$C$1+1 ), COUNTIFS( Pathway!$D:$D,"P_Ticket", Pathway!$G:$G,"Medium", Pathway!$U:$U,"NO", Pathway!$L:$L,">="&$B$1, Pathway!$L:$L,"<"&$C$1+1 ), COUNTIFS( Pathway!$D:$D,"P_Ticket", Pathway!$G:$G,"High", Pathway!$U:$U,"NO", Pathway!$L:$L,">="&$B$1, Pathway!$L:$L,"<"&$C$1+1 ) ) -> 0 | T13: =SUM( COUNTIFS( Pathway!$D:$D,"P_Ticket", Pathway!$G:$G,"Low", Pathway!$I:$I,"Closed", Pathway!$U:$U,"NO", Pathway!$N:$N,"<"&$C$1+1, Pathway!$N:$N,">="&$B$1 ), COUNTIFS( Pathway!$D:$D,"P_Ticket", Pathway!$G:$G,"Medium", Pathway!$I:$I,"Closed", Pathway!$U:$U,"NO", Pathway!$N:$N,"<"&$C$1+1, Pathway!$N:$N,">="&$B$1 ), COUNTIFS( Pathway!$D:$D,"P_Ticket", Pathway!$G:$G,"High", Pathway!$I:$I,"Closed", Pathway!$U:$U,"NO", Pathway!$N:$N,"<"&$C$1+1, Pathway!$N:$N,">="&$B$1 ), COUNTIFS( Pathway!$D:$D,"P_Ticket", Pathway!$G:$G,"Low", Pathway!$I:$I,"Triaged", Pathway!$U:$U,"NO", Pathway!$N:$N,"<"&$C$1+1, Pathway!$N:$N,">="&$B$1 ), COUNTIFS( Pathway!$D:$D,"P_Ticket", Pathway!$G:$G,"Medium", Pathway!$I:$I,"Triaged", Pathway!$U:$U,"NO", Pathway!$N:$N,"<"&$C$1+1, Pathway!$N:$N,">="&$B$1 ), COUNTIFS( Pathway!$D:$D,"P_Ticket", Pathway!$G:$G,"High", Pathway!$I:$I,"Triaged", Pathway!$U:$U,"NO", Pathway!$N:$N,"<"&$C$1+1, Pathway!$N:$N,">="&$B$1 ) ) -> 0 | W13: =COUNTIFS( Pathway!$D:$D,"P_Ticket", Pathway!$G:$G,"High", Pathway!$U:$U,"NO", Pathway!$L:$L,">="&$B$1, Pathway!$L:$L,"<"&$C$1+1 ) -> 0 | X13: =SUM( COUNTIFS( Pathway!$D:$D,"P_Ticket", Pathway!$G:$G,"High", Pathway!$I:$I,"Closed", Pathway!$U:$U,"NO", Pathway!$N:$N,"<"&$C$1+1, Pathway!$N:$N,">="&$B$1 ), COUNTIFS( Pathway!$D:$D,"P_Ticket", Pathway!$G:$G,"High", Pathway!$I:$I,"Triaged", Pathway!$U:$U,"NO", Pathway!$N:$N,"<"&$C$1+1, Pathway!$N:$N,">="&$B$1 ) ) -> 0
A14: APPSUP_HDL_CORA | B14: IB | C14: Mobile | D14: =COUNTIFS( 'IB MOBILE'!$D:$D,"Incident", 'IB MOBILE'!$G:$G,1, 'IB MOBILE'!$U:$U,"NO", 'IB MOBILE'!$L:$L,">="&$B$1, 'IB MOBILE'!$L:$L,"<"&$C$1+1 ) -> 0 | E14: =SUM( COUNTIFS( 'IB MOBILE'!$D:$D,"Incident", 'IB MOBILE'!$G:$G,1, 'IB MOBILE'!$I:$I,"Closed", 'IB MOBILE'!$U:$U,"NO", 'IB MOBILE'!$N:$N,">="&$B$1, 'IB MOBILE'!$N:$N,"<"&$C$1+1 ), COUNTIFS( 'IB MOBILE'!$D:$D,"Incident", 'IB MOBILE'!$G:$G,1, 'IB MOBILE'!$I:$I,"Triaged", 'IB MOBILE'!$U:$U,"NO", 'IB MOBILE'!$N:$N,">="&$B$1, 'IB MOBILE'!$N:$N,"<"&$C$1+1 ) ) -> 0 | F14: =COUNTIFS( 'IB MOBILE'!$D:$D,"Incident", 'IB MOBILE'!$G:$G,1, 'IB MOBILE'!$U:$U,"<>YES", 'IB MOBILE'!$K:$K,"<"&$B$1, 'IB MOBILE'!$N:$N,"" ) + COUNTIFS( 'IB MOBILE'!$D:$D,"Incident", 'IB MOBILE'!$G:$G,1, 'IB MOBILE'!$U:$U,"<>YES", 'IB MOBILE'!$K:$K,"<"&$B$1, 'IB MOBILE'!$N:$N,">="&$B$1 ) + COUNTIFS( 'IB MOBILE'!$D:$D,"Incident", 'IB MOBILE'!$G:$G,1, 'IB MOBILE'!$U:$U,"<>YES", 'IB MOBILE'!$K:$K,">="&$B$1, 'IB MOBILE'!$K:$K,"<"&$C$1+1 ) - COUNTIFS( 'IB MOBILE'!$D:$D,"Incident", 'IB MOBILE'!$G:$G,1, 'IB MOBILE'!$U:$U,"<>YES", 'IB MOBILE'!$I:$I,"Closed", 'IB MOBILE'!$N:$N,">="&$B$1, 'IB MOBILE'!$N:$N,"<"&$C$1+1 ) - COUNTIFS( 'IB MOBILE'!$D:$D,"Incident", 'IB MOBILE'!$G:$G,1, 'IB MOBILE'!$U:$U,"<>YES", 'IB MOBILE'!$I:$I,"Triaged", 'IB MOBILE'!$N:$N,">="&$B$1, 'IB MOBILE'!$N:$N,"<"&$C$1+1 ) -> 0 | G14: =COUNTIFS( 'IB MOBILE'!$D:$D,"Incident", 'IB MOBILE'!$G:$G,2, 'IB MOBILE'!$U:$U,"NO", 'IB MOBILE'!$L:$L,">="&$B$1, 'IB MOBILE'!$L:$L,"<"&$C$1+1 ) -> 0 | H14: =SUM( COUNTIFS( 'IB MOBILE'!$D:$D,"Incident", 'IB MOBILE'!$G:$G,2, 'IB MOBILE'!$I:$I,"Closed", 'IB MOBILE'!$U:$U,"NO", 'IB MOBILE'!$N:$N,">="&$B$1, 'IB MOBILE'!$N:$N,"<"&$C$1+1 ), COUNTIFS( 'IB MOBILE'!$D:$D,"Incident", 'IB MOBILE'!$G:$G,2, 'IB MOBILE'!$I:$I,"Triaged", 'IB MOBILE'!$U:$U,"NO", 'IB MOBILE'!$N:$N,">="&$B$1, 'IB MOBILE'!$N:$N,"<"&$C$1+1 ) ) -> 0 | I14: =COUNTIFS( 'IB MOBILE'!$D:$D,"Incident", 'IB MOBILE'!$G:$G,2, 'IB MOBILE'!$U:$U,"<>YES", 'IB MOBILE'!$K:$K,"<"&$B$1, 'IB MOBILE'!$N:$N,"" ) + COUNTIFS( 'IB MOBILE'!$D:$D,"Incident", 'IB MOBILE'!$G:$G,2, 'IB MOBILE'!$U:$U,"<>YES", 'IB MOBILE'!$K:$K,"<"&$B$1, 'IB MOBILE'!$N:$N,">="&$B$1 ) + COUNTIFS( 'IB MOBILE'!$D:$D,"Incident", 'IB MOBILE'!$G:$G,2, 'IB MOBILE'!$U:$U,"<>YES", 'IB MOBILE'!$K:$K,">="&$B$1, 'IB MOBILE'!$K:$K,"<"&$C$1+1 ) - COUNTIFS( 'IB MOBILE'!$D:$D,"Incident", 'IB MOBILE'!$G:$G,2, 'IB MOBILE'!$U:$U,"<>YES", 'IB MOBILE'!$I:$I,"Closed", 'IB MOBILE'!$N:$N,">="&$B$1, 'IB MOBILE'!$N:$N,"<"&$C$1+1 ) - COUNTIFS( 'IB MOBILE'!$D:$D,"Incident", 'IB MOBILE'!$G:$G,2, 'IB MOBILE'!$U:$U,"<>YES", 'IB MOBILE'!$I:$I,"Triaged", 'IB MOBILE'!$N:$N,">="&$B$1, 'IB MOBILE'!$N:$N,"<"&$C$1+1 ) -> 0 | J14: =COUNTIFS( 'IB MOBILE'!$D:$D,"Incident", 'IB MOBILE'!$G:$G,3, 'IB MOBILE'!$U:$U,"NO", 'IB MOBILE'!$L:$L,">="&$B$1, 'IB MOBILE'!$L:$L,"<"&$C$1+1 ) -> 0 | K14: =SUM( COUNTIFS( 'IB MOBILE'!$D:$D,"Incident", 'IB MOBILE'!$G:$G,3, 'IB MOBILE'!$I:$I,"Closed", 'IB MOBILE'!$U:$U,"NO", 'IB MOBILE'!$N:$N,">="&$B$1, 'IB MOBILE'!$N:$N,"<"&$C$1+1 ), COUNTIFS( 'IB MOBILE'!$D:$D,"Incident", 'IB MOBILE'!$G:$G,3, 'IB MOBILE'!$I:$I,"Triaged", 'IB MOBILE'!$U:$U,"NO", 'IB MOBILE'!$N:$N,">="&$B$1, 'IB MOBILE'!$N:$N,"<"&$C$1+1 ) ) -> 0 | L14: =COUNTIFS( 'IB MOBILE'!$D:$D,"Incident", 'IB MOBILE'!$G:$G,3, 'IB MOBILE'!$U:$U,"<>YES", 'IB MOBILE'!$K:$K,"<"&$B$1, 'IB MOBILE'!$N:$N,"" ) + COUNTIFS( 'IB MOBILE'!$D:$D,"Incident", 'IB MOBILE'!$G:$G,3, 'IB MOBILE'!$U:$U,"<>YES", 'IB MOBILE'!$K:$K,"<"&$B$1, 'IB MOBILE'!$N:$N,">="&$B$1 ) + COUNTIFS( 'IB MOBILE'!$D:$D,"Incident", 'IB MOBILE'!$G:$G,3, 'IB MOBILE'!$U:$U,"<>YES", 'IB MOBILE'!$K:$K,">="&$B$1, 'IB MOBILE'!$K:$K,"<"&$C$1+1 ) - COUNTIFS( 'IB MOBILE'!$D:$D,"Incident", 'IB MOBILE'!$G:$G,3, 'IB MOBILE'!$U:$U,"<>YES", 'IB MOBILE'!$I:$I,"Closed", 'IB MOBILE'!$N:$N,">="&$B$1, 'IB MOBILE'!$N:$N,"<"&$C$1+1 ) - COUNTIFS( 'IB MOBILE'!$D:$D,"Incident", 'IB MOBILE'!$G:$G,3, 'IB MOBILE'!$U:$U,"<>YES", 'IB MOBILE'!$I:$I,"Triaged", 'IB MOBILE'!$N:$N,">="&$B$1, 'IB MOBILE'!$N:$N,"<"&$C$1+1 ) -> 0 | M14: =COUNTIFS( 'IB MOBILE'!$D:$D,"Incident", 'IB MOBILE'!$G:$G,4, 'IB MOBILE'!$U:$U,"NO", 'IB MOBILE'!$L:$L,">="&$B$1, 'IB MOBILE'!$L:$L,"<"&$C$1+1 ) -> 0 | N14: =SUM( COUNTIFS( 'IB MOBILE'!$D:$D,"Incident", 'IB MOBILE'!$G:$G,4, 'IB MOBILE'!$I:$I,"Closed", 'IB MOBILE'!$U:$U,"NO", 'IB MOBILE'!$N:$N,">="&$B$1, 'IB MOBILE'!$N:$N,"<"&$C$1+1 ), COUNTIFS( 'IB MOBILE'!$D:$D,"Incident", 'IB MOBILE'!$G:$G,4, 'IB MOBILE'!$I:$I,"Triaged", 'IB MOBILE'!$U:$U,"NO", 'IB MOBILE'!$N:$N,">="&$B$1, 'IB MOBILE'!$N:$N,"<"&$C$1+1 ) ) -> 0 | O14: =COUNTIFS( 'IB MOBILE'!$D:$D,"Incident", 'IB MOBILE'!$G:$G,4, 'IB MOBILE'!$U:$U,"<>YES", 'IB MOBILE'!$K:$K,"<"&$B$1, 'IB MOBILE'!$N:$N,"" ) + COUNTIFS( 'IB MOBILE'!$D:$D,"Incident", 'IB MOBILE'!$G:$G,4, 'IB MOBILE'!$U:$U,"<>YES", 'IB MOBILE'!$K:$K,"<"&$B$1, 'IB MOBILE'!$N:$N,">="&$B$1 ) + COUNTIFS( 'IB MOBILE'!$D:$D,"Incident", 'IB MOBILE'!$G:$G,4, 'IB MOBILE'!$U:$U,"<>YES", 'IB MOBILE'!$K:$K,">="&$B$1, 'IB MOBILE'!$K:$K,"<"&$C$1+1 ) - COUNTIFS( 'IB MOBILE'!$D:$D,"Incident", 'IB MOBILE'!$G:$G,4, 'IB MOBILE'!$U:$U,"<>YES", 'IB MOBILE'!$I:$I,"Closed", 'IB MOBILE'!$N:$N,">="&$B$1, 'IB MOBILE'!$N:$N,"<"&$C$1+1 ) - COUNTIFS( 'IB MOBILE'!$D:$D,"Incident", 'IB MOBILE'!$G:$G,4, 'IB MOBILE'!$U:$U,"<>YES", 'IB MOBILE'!$I:$I,"Triaged", 'IB MOBILE'!$N:$N,">="&$B$1, 'IB MOBILE'!$N:$N,"<"&$C$1+1 ) -> 0 | P14: =COUNTIFS( 'IB MOBILE'!$D:$D,"RFS", 'IB MOBILE'!$U:$U,"NO", 'IB MOBILE'!$L:$L,">="&$B$1, 'IB MOBILE'!$L:$L,"<"&$C$1+1 ) -> 0 | Q14: =SUM( COUNTIFS( 'IB MOBILE'!$D:$D,"RFS", 'IB MOBILE'!$I:$I,"Closed", 'IB MOBILE'!$U:$U,"NO", 'IB MOBILE'!$N:$N,">="&$B$1, 'IB MOBILE'!$N:$N,"<"&$C$1+1 ), COUNTIFS( 'IB MOBILE'!$D:$D,"RFS", 'IB MOBILE'!$I:$I,"Triaged", 'IB MOBILE'!$U:$U,"NO", 'IB MOBILE'!$N:$N,">="&$B$1, 'IB MOBILE'!$N:$N,"<"&$C$1+1 ) ) -> 0 | R14: =COUNTIFS( 'IB MOBILE'!$D:$D,"RFS", 'IB MOBILE'!$U:$U,"<>YES", 'IB MOBILE'!$K:$K,"<"&$B$1, 'IB MOBILE'!$N:$N,"" ) + COUNTIFS( 'IB MOBILE'!$D:$D,"RFS", 'IB MOBILE'!$U:$U,"<>YES", 'IB MOBILE'!$K:$K,"<"&$B$1, 'IB MOBILE'!$N:$N,">="&$B$1 ) + COUNTIFS( 'IB MOBILE'!$D:$D,"RFS", 'IB MOBILE'!$U:$U,"<>YES", 'IB MOBILE'!$K:$K,">="&$B$1, 'IB MOBILE'!$K:$K,"<"&$C$1+1 ) - COUNTIFS( 'IB MOBILE'!$D:$D,"RFS", 'IB MOBILE'!$I:$I,"Closed", 'IB MOBILE'!$U:$U,"<>YES", 'IB MOBILE'!$N:$N,">="&$B$1, 'IB MOBILE'!$N:$N,"<"&$C$1+1 ) - COUNTIFS( 'IB MOBILE'!$D:$D,"RFS", 'IB MOBILE'!$I:$I,"Triaged", 'IB MOBILE'!$U:$U,"<>YES", 'IB MOBILE'!$N:$N,">="&$B$1, 'IB MOBILE'!$N:$N,"<"&$C$1+1 ) -> 0 | S14: =SUM( COUNTIFS( 'IB MOBILE'!$D:$D,"P_Ticket", 'IB MOBILE'!$G:$G,"Low", 'IB MOBILE'!$U:$U,"NO", 'IB MOBILE'!$L:$L,">="&$B$1, 'IB MOBILE'!$L:$L,"<"&$C$1+1 ), COUNTIFS( 'IB MOBILE'!$D:$D,"P_Ticket", 'IB MOBILE'!$G:$G,"Medium", 'IB MOBILE'!$U:$U,"NO", 'IB MOBILE'!$L:$L,">="&$B$1, 'IB MOBILE'!$L:$L,"<"&$C$1+1 ), COUNTIFS( 'IB MOBILE'!$D:$D,"P_Ticket", 'IB MOBILE'!$G:$G,"High", 'IB MOBILE'!$U:$U,"NO", 'IB MOBILE'!$L:$L,">="&$B$1, 'IB MOBILE'!$L:$L,"<"&$C$1+1 ) ) -> 0 | T14: =SUM( COUNTIFS( 'IB MOBILE'!$D:$D,"P_Ticket", 'IB MOBILE'!$G:$G,"Low", 'IB MOBILE'!$I:$I,"Closed", 'IB MOBILE'!$U:$U,"NO", 'IB MOBILE'!$N:$N,"<"&$C$1+1, 'IB MOBILE'!$N:$N,">="&$B$1 ), COUNTIFS( 'IB MOBILE'!$D:$D,"P_Ticket", 'IB MOBILE'!$G:$G,"Medium", 'IB MOBILE'!$I:$I,"Closed", 'IB MOBILE'!$U:$U,"NO", 'IB MOBILE'!$N:$N,"<"&$C$1+1, 'IB MOBILE'!$N:$N,">="&$B$1 ), COUNTIFS( 'IB MOBILE'!$D:$D,"P_Ticket", 'IB MOBILE'!$G:$G,"High", 'IB MOBILE'!$I:$I,"Closed", 'IB MOBILE'!$U:$U,"NO", 'IB MOBILE'!$N:$N,"<"&$C$1+1, 'IB MOBILE'!$N:$N,">="&$B$1 ), COUNTIFS( 'IB MOBILE'!$D:$D,"P_Ticket", 'IB MOBILE'!$G:$G,"Low", 'IB MOBILE'!$I:$I,"Triaged", 'IB MOBILE'!$U:$U,"NO", 'IB MOBILE'!$N:$N,"<"&$C$1+1, 'IB MOBILE'!$N:$N,">="&$B$1 ), COUNTIFS( 'IB MOBILE'!$D:$D,"P_Ticket", 'IB MOBILE'!$G:$G,"Medium", 'IB MOBILE'!$I:$I,"Triaged", 'IB MOBILE'!$U:$U,"NO", 'IB MOBILE'!$N:$N,"<"&$C$1+1, 'IB MOBILE'!$N:$N,">="&$B$1 ), COUNTIFS( 'IB MOBILE'!$D:$D,"P_Ticket", 'IB MOBILE'!$G:$G,"High", 'IB MOBILE'!$I:$I,"Triaged", 'IB MOBILE'!$U:$U,"NO", 'IB MOBILE'!$N:$N,"<"&$C$1+1, 'IB MOBILE'!$N:$N,">="&$B$1 ) ) -> 0 | W14: =COUNTIFS( 'IB MOBILE'!$D:$D,"P_Ticket", 'IB MOBILE'!$G:$G,"High", 'IB MOBILE'!$U:$U,"NO", 'IB MOBILE'!$L:$L,">="&$B$1, 'IB MOBILE'!$L:$L,"<"&$C$1+1 ) -> 0 | X14: =SUM( COUNTIFS( 'IB MOBILE'!$D:$D,"P_Ticket", 'IB MOBILE'!$G:$G,"High", 'IB MOBILE'!$I:$I,"Closed", 'IB MOBILE'!$U:$U,"NO", 'IB MOBILE'!$N:$N,"<"&$C$1+1, 'IB MOBILE'!$N:$N,">="&$B$1 ), COUNTIFS( 'IB MOBILE'!$D:$D,"P_Ticket", 'IB MOBILE'!$G:$G,"High", 'IB MOBILE'!$I:$I,"Triaged", 'IB MOBILE'!$U:$U,"NO", 'IB MOBILE'!$N:$N,"<"&$C$1+1, 'IB MOBILE'!$N:$N,">="&$B$1 ) ) -> 0
A15: APPSUP_IBIS, APPSUP_IBCOM_3P | B15: IB | C15: Commercial Services | D15: =COUNTIFS( 'IB COMMERCIAL'!$D:$D,"Incident", 'IB COMMERCIAL'!$G:$G,1, 'IB COMMERCIAL'!$U:$U,"NO", 'IB COMMERCIAL'!$L:$L,">="&$B$1, 'IB COMMERCIAL'!$L:$L,"<"&$C$1+1 ) -> 0 | E15: =SUM( COUNTIFS( 'IB COMMERCIAL'!$D:$D,"Incident", 'IB COMMERCIAL'!$G:$G,1, 'IB COMMERCIAL'!$I:$I,"Closed", 'IB COMMERCIAL'!$U:$U,"NO", 'IB COMMERCIAL'!$N:$N,">="&$B$1, 'IB COMMERCIAL'!$N:$N,"<"&$C$1+1 ), COUNTIFS( 'IB COMMERCIAL'!$D:$D,"Incident", 'IB COMMERCIAL'!$G:$G,1, 'IB COMMERCIAL'!$I:$I,"Triaged", 'IB COMMERCIAL'!$U:$U,"NO", 'IB COMMERCIAL'!$N:$N,">="&$B$1, 'IB COMMERCIAL'!$N:$N,"<"&$C$1+1 ) ) -> 0 | F15: =COUNTIFS( 'IB COMMERCIAL'!$D:$D,"Incident", 'IB COMMERCIAL'!$G:$G,1, 'IB COMMERCIAL'!$U:$U,"<>YES", 'IB COMMERCIAL'!$K:$K,"<"&$B$1, 'IB COMMERCIAL'!$N:$N,"" ) + COUNTIFS( 'IB COMMERCIAL'!$D:$D,"Incident", 'IB COMMERCIAL'!$G:$G,1, 'IB COMMERCIAL'!$U:$U,"<>YES", 'IB COMMERCIAL'!$K:$K,"<"&$B$1, 'IB COMMERCIAL'!$N:$N,">="&$B$1 ) + COUNTIFS( 'IB COMMERCIAL'!$D:$D,"Incident", 'IB COMMERCIAL'!$G:$G,1, 'IB COMMERCIAL'!$U:$U,"<>YES", 'IB COMMERCIAL'!$K:$K,">="&$B$1, 'IB COMMERCIAL'!$K:$K,"<"&$C$1+1 ) - COUNTIFS( 'IB COMMERCIAL'!$D:$D,"Incident", 'IB COMMERCIAL'!$G:$G,1, 'IB COMMERCIAL'!$U:$U,"<>YES", 'IB COMMERCIAL'!$I:$I,"Closed", 'IB COMMERCIAL'!$N:$N,">="&$B$1, 'IB COMMERCIAL'!$N:$N,"<"&$C$1+1 ) - COUNTIFS( 'IB COMMERCIAL'!$D:$D,"Incident", 'IB COMMERCIAL'!$G:$G,1, 'IB COMMERCIAL'!$U:$U,"<>YES", 'IB COMMERCIAL'!$I:$I,"Triaged", 'IB COMMERCIAL'!$N:$N,">="&$B$1, 'IB COMMERCIAL'!$N:$N,"<"&$C$1+1 ) -> 0 | G15: =COUNTIFS( 'IB COMMERCIAL'!$D:$D,"Incident", 'IB COMMERCIAL'!$G:$G,2, 'IB COMMERCIAL'!$U:$U,"NO", 'IB COMMERCIAL'!$L:$L,">="&$B$1, 'IB COMMERCIAL'!$L:$L,"<"&$C$1+1 ) -> 0 | H15: =SUM( COUNTIFS( 'IB COMMERCIAL'!$D:$D,"Incident", 'IB COMMERCIAL'!$G:$G,2, 'IB COMMERCIAL'!$I:$I,"Closed", 'IB COMMERCIAL'!$U:$U,"NO", 'IB COMMERCIAL'!$N:$N,">="&$B$1, 'IB COMMERCIAL'!$N:$N,"<"&$C$1+1 ), COUNTIFS( 'IB COMMERCIAL'!$D:$D,"Incident", 'IB COMMERCIAL'!$G:$G,2, 'IB COMMERCIAL'!$I:$I,"Triaged", 'IB COMMERCIAL'!$U:$U,"NO", 'IB COMMERCIAL'!$N:$N,">="&$B$1, 'IB COMMERCIAL'!$N:$N,"<"&$C$1+1 ) ) -> 0 | I15: =COUNTIFS( 'IB COMMERCIAL'!$D:$D,"Incident", 'IB COMMERCIAL'!$G:$G,2, 'IB COMMERCIAL'!$U:$U,"<>YES", 'IB COMMERCIAL'!$K:$K,"<"&$B$1, 'IB COMMERCIAL'!$N:$N,"" ) + COUNTIFS( 'IB COMMERCIAL'!$D:$D,"Incident", 'IB COMMERCIAL'!$G:$G,2, 'IB COMMERCIAL'!$U:$U,"<>YES", 'IB COMMERCIAL'!$K:$K,"<"&$B$1, 'IB COMMERCIAL'!$N:$N,">="&$B$1 ) + COUNTIFS( 'IB COMMERCIAL'!$D:$D,"Incident", 'IB COMMERCIAL'!$G:$G,2, 'IB COMMERCIAL'!$U:$U,"<>YES", 'IB COMMERCIAL'!$K:$K,">="&$B$1, 'IB COMMERCIAL'!$K:$K,"<"&$C$1+1 ) - COUNTIFS( 'IB COMMERCIAL'!$D:$D,"Incident", 'IB COMMERCIAL'!$G:$G,2, 'IB COMMERCIAL'!$U:$U,"<>YES", 'IB COMMERCIAL'!$I:$I,"Closed", 'IB COMMERCIAL'!$N:$N,">="&$B$1, 'IB COMMERCIAL'!$N:$N,"<"&$C$1+1 ) - COUNTIFS( 'IB COMMERCIAL'!$D:$D,"Incident", 'IB COMMERCIAL'!$G:$G,2, 'IB COMMERCIAL'!$U:$U,"<>YES", 'IB COMMERCIAL'!$I:$I,"Triaged", 'IB COMMERCIAL'!$N:$N,">="&$B$1, 'IB COMMERCIAL'!$N:$N,"<"&$C$1+1 ) -> 0 | J15: =COUNTIFS( 'IB COMMERCIAL'!$D:$D,"Incident", 'IB COMMERCIAL'!$G:$G,3, 'IB COMMERCIAL'!$U:$U,"NO", 'IB COMMERCIAL'!$L:$L,">="&$B$1, 'IB COMMERCIAL'!$L:$L,"<"&$C$1+1 ) -> 0 | K15: =SUM( COUNTIFS( 'IB COMMERCIAL'!$D:$D,"Incident", 'IB COMMERCIAL'!$G:$G,3, 'IB COMMERCIAL'!$I:$I,"Closed", 'IB COMMERCIAL'!$U:$U,"NO", 'IB COMMERCIAL'!$N:$N,">="&$B$1, 'IB COMMERCIAL'!$N:$N,"<"&$C$1+1 ), COUNTIFS( 'IB COMMERCIAL'!$D:$D,"Incident", 'IB COMMERCIAL'!$G:$G,3, 'IB COMMERCIAL'!$I:$I,"Triaged", 'IB COMMERCIAL'!$U:$U,"NO", 'IB COMMERCIAL'!$N:$N,">="&$B$1, 'IB COMMERCIAL'!$N:$N,"<"&$C$1+1 ) ) -> 0 | L15: =COUNTIFS( 'IB COMMERCIAL'!$D:$D,"Incident", 'IB COMMERCIAL'!$G:$G,3, 'IB COMMERCIAL'!$U:$U,"<>YES", 'IB COMMERCIAL'!$K:$K,"<"&$B$1, 'IB COMMERCIAL'!$N:$N,"" ) + COUNTIFS( 'IB COMMERCIAL'!$D:$D,"Incident", 'IB COMMERCIAL'!$G:$G,3, 'IB COMMERCIAL'!$U:$U,"<>YES", 'IB COMMERCIAL'!$K:$K,"<"&$B$1, 'IB COMMERCIAL'!$N:$N,">="&$B$1 ) + COUNTIFS( 'IB COMMERCIAL'!$D:$D,"Incident", 'IB COMMERCIAL'!$G:$G,3, 'IB COMMERCIAL'!$U:$U,"<>YES", 'IB COMMERCIAL'!$K:$K,">="&$B$1, 'IB COMMERCIAL'!$K:$K,"<"&$C$1+1 ) - COUNTIFS( 'IB COMMERCIAL'!$D:$D,"Incident", 'IB COMMERCIAL'!$G:$G,3, 'IB COMMERCIAL'!$U:$U,"<>YES", 'IB COMMERCIAL'!$I:$I,"Closed", 'IB COMMERCIAL'!$N:$N,">="&$B$1, 'IB COMMERCIAL'!$N:$N,"<"&$C$1+1 ) - COUNTIFS( 'IB COMMERCIAL'!$D:$D,"Incident", 'IB COMMERCIAL'!$G:$G,3, 'IB COMMERCIAL'!$U:$U,"<>YES", 'IB COMMERCIAL'!$I:$I,"Triaged", 'IB COMMERCIAL'!$N:$N,">="&$B$1, 'IB COMMERCIAL'!$N:$N,"<"&$C$1+1 ) -> 0 | M15: =COUNTIFS( 'IB COMMERCIAL'!$D:$D,"Incident", 'IB COMMERCIAL'!$G:$G,4, 'IB COMMERCIAL'!$U:$U,"NO", 'IB COMMERCIAL'!$L:$L,">="&$B$1, 'IB COMMERCIAL'!$L:$L,"<"&$C$1+1 ) -> 0 | N15: =SUM( COUNTIFS( 'IB COMMERCIAL'!$D:$D,"Incident", 'IB COMMERCIAL'!$G:$G,4, 'IB COMMERCIAL'!$I:$I,"Closed", 'IB COMMERCIAL'!$U:$U,"NO", 'IB COMMERCIAL'!$N:$N,">="&$B$1, 'IB COMMERCIAL'!$N:$N,"<"&$C$1+1 ), COUNTIFS( 'IB COMMERCIAL'!$D:$D,"Incident", 'IB COMMERCIAL'!$G:$G,4, 'IB COMMERCIAL'!$I:$I,"Triaged", 'IB COMMERCIAL'!$U:$U,"NO", 'IB COMMERCIAL'!$N:$N,">="&$B$1, 'IB COMMERCIAL'!$N:$N,"<"&$C$1+1 ) ) -> 0 | O15: =COUNTIFS( 'IB COMMERCIAL'!$D:$D,"Incident", 'IB COMMERCIAL'!$G:$G,4, 'IB COMMERCIAL'!$U:$U,"<>YES", 'IB COMMERCIAL'!$K:$K,"<"&$B$1, 'IB COMMERCIAL'!$N:$N,"" ) + COUNTIFS( 'IB COMMERCIAL'!$D:$D,"Incident", 'IB COMMERCIAL'!$G:$G,4, 'IB COMMERCIAL'!$U:$U,"<>YES", 'IB COMMERCIAL'!$K:$K,"<"&$B$1, 'IB COMMERCIAL'!$N:$N,">="&$B$1 ) + COUNTIFS( 'IB COMMERCIAL'!$D:$D,"Incident", 'IB COMMERCIAL'!$G:$G,4, 'IB COMMERCIAL'!$U:$U,"<>YES", 'IB COMMERCIAL'!$K:$K,">="&$B$1, 'IB COMMERCIAL'!$K:$K,"<"&$C$1+1 ) - COUNTIFS( 'IB COMMERCIAL'!$D:$D,"Incident", 'IB COMMERCIAL'!$G:$G,4, 'IB COMMERCIAL'!$U:$U,"<>YES", 'IB COMMERCIAL'!$I:$I,"Closed", 'IB COMMERCIAL'!$N:$N,">="&$B$1, 'IB COMMERCIAL'!$N:$N,"<"&$C$1+1 ) - COUNTIFS( 'IB COMMERCIAL'!$D:$D,"Incident", 'IB COMMERCIAL'!$G:$G,4, 'IB COMMERCIAL'!$U:$U,"<>YES", 'IB COMMERCIAL'!$I:$I,"Triaged", 'IB COMMERCIAL'!$N:$N,">="&$B$1, 'IB COMMERCIAL'!$N:$N,"<"&$C$1+1 ) -> 0 | P15: =COUNTIFS( 'IB COMMERCIAL'!$D:$D,"RFS", 'IB COMMERCIAL'!$U:$U,"NO", 'IB COMMERCIAL'!$L:$L,">="&$B$1, 'IB COMMERCIAL'!$L:$L,"<"&$C$1+1 ) -> 0 | Q15: =SUM( COUNTIFS( 'IB COMMERCIAL'!$D:$D,"RFS", 'IB COMMERCIAL'!$I:$I,"Closed", 'IB COMMERCIAL'!$U:$U,"NO", 'IB COMMERCIAL'!$N:$N,">="&$B$1, 'IB COMMERCIAL'!$N:$N,"<"&$C$1+1 ), COUNTIFS( 'IB COMMERCIAL'!$D:$D,"RFS", 'IB COMMERCIAL'!$I:$I,"Triaged", 'IB COMMERCIAL'!$U:$U,"NO", 'IB COMMERCIAL'!$N:$N,">="&$B$1, 'IB COMMERCIAL'!$N:$N,"<"&$C$1+1 ) ) -> 0 | R15: =COUNTIFS( 'IB COMMERCIAL'!$D:$D,"RFS", 'IB COMMERCIAL'!$U:$U,"<>YES", 'IB COMMERCIAL'!$K:$K,"<"&$B$1, 'IB COMMERCIAL'!$N:$N,"" ) + COUNTIFS( 'IB COMMERCIAL'!$D:$D,"RFS", 'IB COMMERCIAL'!$U:$U,"<>YES", 'IB COMMERCIAL'!$K:$K,"<"&$B$1, 'IB COMMERCIAL'!$N:$N,">="&$B$1 ) + COUNTIFS( 'IB COMMERCIAL'!$D:$D,"RFS", 'IB COMMERCIAL'!$U:$U,"<>YES", 'IB COMMERCIAL'!$K:$K,">="&$B$1, 'IB COMMERCIAL'!$K:$K,"<"&$C$1+1 ) - COUNTIFS( 'IB COMMERCIAL'!$D:$D,"RFS", 'IB COMMERCIAL'!$I:$I,"Closed", 'IB COMMERCIAL'!$U:$U,"<>YES", 'IB COMMERCIAL'!$N:$N,">="&$B$1, 'IB COMMERCIAL'!$N:$N,"<"&$C$1+1 ) - COUNTIFS( 'IB COMMERCIAL'!$D:$D,"RFS", 'IB COMMERCIAL'!$I:$I,"Triaged", 'IB COMMERCIAL'!$U:$U,"<>YES", 'IB COMMERCIAL'!$N:$N,">="&$B$1, 'IB COMMERCIAL'!$N:$N,"<"&$C$1+1 ) -> 0 | S15: =SUM( COUNTIFS( 'IB COMMERCIAL'!$D:$D,"P_Ticket", 'IB COMMERCIAL'!$G:$G,"Low", 'IB COMMERCIAL'!$U:$U,"NO", 'IB COMMERCIAL'!$L:$L,">="&$B$1, 'IB COMMERCIAL'!$L:$L,"<"&$C$1+1 ), COUNTIFS( 'IB COMMERCIAL'!$D:$D,"P_Ticket", 'IB COMMERCIAL'!$G:$G,"Medium", 'IB COMMERCIAL'!$U:$U,"NO", 'IB COMMERCIAL'!$L:$L,">="&$B$1, 'IB COMMERCIAL'!$L:$L,"<"&$C$1+1 ), COUNTIFS( 'IB COMMERCIAL'!$D:$D,"P_Ticket", 'IB COMMERCIAL'!$G:$G,"High", 'IB COMMERCIAL'!$U:$U,"NO", 'IB COMMERCIAL'!$L:$L,">="&$B$1, 'IB COMMERCIAL'!$L:$L,"<"&$C$1+1 ) ) -> 0 | T15: =SUM( COUNTIFS( 'IB COMMERCIAL'!$D:$D,"P_Ticket", 'IB COMMERCIAL'!$G:$G,"Low", 'IB COMMERCIAL'!$I:$I,"Closed", 'IB COMMERCIAL'!$U:$U,"NO", 'IB COMMERCIAL'!$N:$N,"<"&$C$1+1, 'IB COMMERCIAL'!$N:$N,">="&$B$1 ), COUNTIFS( 'IB COMMERCIAL'!$D:$D,"P_Ticket", 'IB COMMERCIAL'!$G:$G,"Medium", 'IB COMMERCIAL'!$I:$I,"Closed", 'IB COMMERCIAL'!$U:$U,"NO", 'IB COMMERCIAL'!$N:$N,"<"&$C$1+1, 'IB COMMERCIAL'!$N:$N,">="&$B$1 ), COUNTIFS( 'IB COMMERCIAL'!$D:$D,"P_Ticket", 'IB COMMERCIAL'!$G:$G,"High", 'IB COMMERCIAL'!$I:$I,"Closed", 'IB COMMERCIAL'!$U:$U,"NO", 'IB COMMERCIAL'!$N:$N,"<"&$C$1+1, 'IB COMMERCIAL'!$N:$N,">="&$B$1 ), COUNTIFS( 'IB COMMERCIAL'!$D:$D,"P_Ticket", 'IB COMMERCIAL'!$G:$G,"Low", 'IB COMMERCIAL'!$I:$I,"Triaged", 'IB COMMERCIAL'!$U:$U,"NO", 'IB COMMERCIAL'!$N:$N,"<"&$C$1+1, 'IB COMMERCIAL'!$N:$N,">="&$B$1 ), COUNTIFS( 'IB COMMERCIAL'!$D:$D,"P_Ticket", 'IB COMMERCIAL'!$G:$G,"Medium", 'IB COMMERCIAL'!$I:$I,"Triaged", 'IB COMMERCIAL'!$U:$U,"NO", 'IB COMMERCIAL'!$N:$N,"<"&$C$1+1, 'IB COMMERCIAL'!$N:$N,">="&$B$1 ), COUNTIFS( 'IB COMMERCIAL'!$D:$D,"P_Ticket", 'IB COMMERCIAL'!$G:$G,"High", 'IB COMMERCIAL'!$I:$I,"Triaged", 'IB COMMERCIAL'!$U:$U,"NO", 'IB COMMERCIAL'!$N:$N,"<"&$C$1+1, 'IB COMMERCIAL'!$N:$N,">="&$B$1 ) ) -> 0 | W15: =COUNTIFS( 'IB COMMERCIAL'!$D:$D,"P_Ticket", 'IB COMMERCIAL'!$G:$G,"High", 'IB COMMERCIAL'!$U:$U,"NO", 'IB COMMERCIAL'!$L:$L,">="&$B$1, 'IB COMMERCIAL'!$L:$L,"<"&$C$1+1 ) -> 0 | X15: =SUM( COUNTIFS( 'IB COMMERCIAL'!$D:$D,"P_Ticket", 'IB COMMERCIAL'!$G:$G,"High", 'IB COMMERCIAL'!$I:$I,"Closed", 'IB COMMERCIAL'!$U:$U,"NO", 'IB COMMERCIAL'!$N:$N,"<"&$C$1+1, 'IB COMMERCIAL'!$N:$N,">="&$B$1 ), COUNTIFS( 'IB COMMERCIAL'!$D:$D,"P_Ticket", 'IB COMMERCIAL'!$G:$G,"High", 'IB COMMERCIAL'!$I:$I,"Triaged", 'IB COMMERCIAL'!$U:$U,"NO", 'IB COMMERCIAL'!$N:$N,"<"&$C$1+1, 'IB COMMERCIAL'!$N:$N,">="&$B$1 ) ) -> 0
A16: APPSUP_MRO_NOSAP | B16: IB | C16: MRO | D16: =COUNTIFS( 'IB MRO'!$D:$D,"Incident", 'IB MRO'!$G:$G,1, 'IB MRO'!$U:$U,"NO", 'IB MRO'!$L:$L,">="&$B$1, 'IB MRO'!$L:$L,"<"&$C$1+1 ) -> 0 | E16: =SUM( COUNTIFS( 'IB MRO'!$D:$D,"Incident", 'IB MRO'!$G:$G,1, 'IB MRO'!$I:$I,"Closed", 'IB MRO'!$U:$U,"NO", 'IB MRO'!$N:$N,">="&$B$1, 'IB MRO'!$N:$N,"<"&$C$1+1 ), COUNTIFS( 'IB MRO'!$D:$D,"Incident", 'IB MRO'!$G:$G,1, 'IB MRO'!$I:$I,"Triaged", 'IB MRO'!$U:$U,"NO", 'IB MRO'!$N:$N,">="&$B$1, 'IB MRO'!$N:$N,"<"&$C$1+1 ) ) -> 0 | F16: =COUNTIFS( 'IB MRO'!$D:$D,"Incident", 'IB MRO'!$G:$G,1, 'IB MRO'!$U:$U,"<>YES", 'IB MRO'!$K:$K,"<"&$B$1, 'IB MRO'!$N:$N,"" ) + COUNTIFS( 'IB MRO'!$D:$D,"Incident", 'IB MRO'!$G:$G,1, 'IB MRO'!$U:$U,"<>YES", 'IB MRO'!$K:$K,"<"&$B$1, 'IB MRO'!$N:$N,">="&$B$1 ) + COUNTIFS( 'IB MRO'!$D:$D,"Incident", 'IB MRO'!$G:$G,1, 'IB MRO'!$U:$U,"<>YES", 'IB MRO'!$K:$K,">="&$B$1, 'IB MRO'!$K:$K,"<"&$C$1+1 ) - COUNTIFS( 'IB MRO'!$D:$D,"Incident", 'IB MRO'!$G:$G,1, 'IB MRO'!$U:$U,"<>YES", 'IB MRO'!$I:$I,"Closed", 'IB MRO'!$N:$N,">="&$B$1, 'IB MRO'!$N:$N,"<"&$C$1+1 ) - COUNTIFS( 'IB MRO'!$D:$D,"Incident", 'IB MRO'!$G:$G,1, 'IB MRO'!$U:$U,"<>YES", 'IB MRO'!$I:$I,"Triaged", 'IB MRO'!$N:$N,">="&$B$1, 'IB MRO'!$N:$N,"<"&$C$1+1 ) -> 0 | G16: =COUNTIFS( 'IB MRO'!$D:$D,"Incident", 'IB MRO'!$G:$G,2, 'IB MRO'!$U:$U,"NO", 'IB MRO'!$L:$L,">="&$B$1, 'IB MRO'!$L:$L,"<"&$C$1+1 ) -> 0 | H16: =SUM( COUNTIFS( 'IB MRO'!$D:$D,"Incident", 'IB MRO'!$G:$G,2, 'IB MRO'!$I:$I,"Closed", 'IB MRO'!$U:$U,"NO", 'IB MRO'!$N:$N,">="&$B$1, 'IB MRO'!$N:$N,"<"&$C$1+1 ), COUNTIFS( 'IB MRO'!$D:$D,"Incident", 'IB MRO'!$G:$G,2, 'IB MRO'!$I:$I,"Triaged", 'IB MRO'!$U:$U,"NO", 'IB MRO'!$N:$N,">="&$B$1, 'IB MRO'!$N:$N,"<"&$C$1+1 ) ) -> 0 | I16: =COUNTIFS( 'IB MRO'!$D:$D,"Incident", 'IB MRO'!$G:$G,2, 'IB MRO'!$U:$U,"<>YES", 'IB MRO'!$K:$K,"<"&$B$1, 'IB MRO'!$N:$N,"" ) + COUNTIFS( 'IB MRO'!$D:$D,"Incident", 'IB MRO'!$G:$G,2, 'IB MRO'!$U:$U,"<>YES", 'IB MRO'!$K:$K,"<"&$B$1, 'IB MRO'!$N:$N,">="&$B$1 ) + COUNTIFS( 'IB MRO'!$D:$D,"Incident", 'IB MRO'!$G:$G,2, 'IB MRO'!$U:$U,"<>YES", 'IB MRO'!$K:$K,">="&$B$1, 'IB MRO'!$K:$K,"<"&$C$1+1 ) - COUNTIFS( 'IB MRO'!$D:$D,"Incident", 'IB MRO'!$G:$G,2, 'IB MRO'!$U:$U,"<>YES", 'IB MRO'!$I:$I,"Closed", 'IB MRO'!$N:$N,">="&$B$1, 'IB MRO'!$N:$N,"<"&$C$1+1 ) - COUNTIFS( 'IB MRO'!$D:$D,"Incident", 'IB MRO'!$G:$G,2, 'IB MRO'!$U:$U,"<>YES", 'IB MRO'!$I:$I,"Triaged", 'IB MRO'!$N:$N,">="&$B$1, 'IB MRO'!$N:$N,"<"&$C$1+1 ) -> 0 | J16: =COUNTIFS( 'IB MRO'!$D:$D,"Incident", 'IB MRO'!$G:$G,3, 'IB MRO'!$U:$U,"NO", 'IB MRO'!$L:$L,">="&$B$1, 'IB MRO'!$L:$L,"<"&$C$1+1 ) -> 0 | K16: =SUM( COUNTIFS( 'IB MRO'!$D:$D,"Incident", 'IB MRO'!$G:$G,3, 'IB MRO'!$I:$I,"Closed", 'IB MRO'!$U:$U,"NO", 'IB MRO'!$N:$N,">="&$B$1, 'IB MRO'!$N:$N,"<"&$C$1+1 ), COUNTIFS( 'IB MRO'!$D:$D,"Incident", 'IB MRO'!$G:$G,3, 'IB MRO'!$I:$I,"Triaged", 'IB MRO'!$U:$U,"NO", 'IB MRO'!$N:$N,">="&$B$1, 'IB MRO'!$N:$N,"<"&$C$1+1 ) ) -> 0 | L16: =COUNTIFS( 'IB MRO'!$D:$D,"Incident", 'IB MRO'!$G:$G,3, 'IB MRO'!$U:$U,"<>YES", 'IB MRO'!$K:$K,"<"&$B$1, 'IB MRO'!$N:$N,"" ) + COUNTIFS( 'IB MRO'!$D:$D,"Incident", 'IB MRO'!$G:$G,3, 'IB MRO'!$U:$U,"<>YES", 'IB MRO'!$K:$K,"<"&$B$1, 'IB MRO'!$N:$N,">="&$B$1 ) + COUNTIFS( 'IB MRO'!$D:$D,"Incident", 'IB MRO'!$G:$G,3, 'IB MRO'!$U:$U,"<>YES", 'IB MRO'!$K:$K,">="&$B$1, 'IB MRO'!$K:$K,"<"&$C$1+1 ) - COUNTIFS( 'IB MRO'!$D:$D,"Incident", 'IB MRO'!$G:$G,3, 'IB MRO'!$U:$U,"<>YES", 'IB MRO'!$I:$I,"Closed", 'IB MRO'!$N:$N,">="&$B$1, 'IB MRO'!$N:$N,"<"&$C$1+1 ) - COUNTIFS( 'IB MRO'!$D:$D,"Incident", 'IB MRO'!$G:$G,3, 'IB MRO'!$U:$U,"<>YES", 'IB MRO'!$I:$I,"Triaged", 'IB MRO'!$N:$N,">="&$B$1, 'IB MRO'!$N:$N,"<"&$C$1+1 ) -> 0 | M16: =COUNTIFS( 'IB MRO'!$D:$D,"Incident", 'IB MRO'!$G:$G,4, 'IB MRO'!$U:$U,"NO", 'IB MRO'!$L:$L,">="&$B$1, 'IB MRO'!$L:$L,"<"&$C$1+1 ) -> 0 | N16: =SUM( COUNTIFS( 'IB MRO'!$D:$D,"Incident", 'IB MRO'!$G:$G,4, 'IB MRO'!$I:$I,"Closed", 'IB MRO'!$U:$U,"NO", 'IB MRO'!$N:$N,">="&$B$1, 'IB MRO'!$N:$N,"<"&$C$1+1 ), COUNTIFS( 'IB MRO'!$D:$D,"Incident", 'IB MRO'!$G:$G,4, 'IB MRO'!$I:$I,"Triaged", 'IB MRO'!$U:$U,"NO", 'IB MRO'!$N:$N,">="&$B$1, 'IB MRO'!$N:$N,"<"&$C$1+1 ) ) -> 0 | O16: =COUNTIFS( 'IB MRO'!$D:$D,"Incident", 'IB MRO'!$G:$G,4, 'IB MRO'!$U:$U,"<>YES", 'IB MRO'!$K:$K,"<"&$B$1, 'IB MRO'!$N:$N,"" ) + COUNTIFS( 'IB MRO'!$D:$D,"Incident", 'IB MRO'!$G:$G,4, 'IB MRO'!$U:$U,"<>YES", 'IB MRO'!$K:$K,"<"&$B$1, 'IB MRO'!$N:$N,">="&$B$1 ) + COUNTIFS( 'IB MRO'!$D:$D,"Incident", 'IB MRO'!$G:$G,4, 'IB MRO'!$U:$U,"<>YES", 'IB MRO'!$K:$K,">="&$B$1, 'IB MRO'!$K:$K,"<"&$C$1+1 ) - COUNTIFS( 'IB MRO'!$D:$D,"Incident", 'IB MRO'!$G:$G,4, 'IB MRO'!$U:$U,"<>YES", 'IB MRO'!$I:$I,"Closed", 'IB MRO'!$N:$N,">="&$B$1, 'IB MRO'!$N:$N,"<"&$C$1+1 ) - COUNTIFS( 'IB MRO'!$D:$D,"Incident", 'IB MRO'!$G:$G,4, 'IB MRO'!$U:$U,"<>YES", 'IB MRO'!$I:$I,"Triaged", 'IB MRO'!$N:$N,">="&$B$1, 'IB MRO'!$N:$N,"<"&$C$1+1 ) -> 0 | P16: =COUNTIFS( 'IB MRO'!$D:$D,"RFS", 'IB MRO'!$U:$U,"NO", 'IB MRO'!$L:$L,">="&$B$1, 'IB MRO'!$L:$L,"<"&$C$1+1 ) -> 0 | Q16: =SUM( COUNTIFS( 'IB MRO'!$D:$D,"RFS", 'IB MRO'!$I:$I,"Closed", 'IB MRO'!$U:$U,"NO", 'IB MRO'!$N:$N,">="&$B$1, 'IB MRO'!$N:$N,"<"&$C$1+1 ), COUNTIFS( 'IB MRO'!$D:$D,"RFS", 'IB MRO'!$I:$I,"Triaged", 'IB MRO'!$U:$U,"NO", 'IB MRO'!$N:$N,">="&$B$1, 'IB MRO'!$N:$N,"<"&$C$1+1 ) ) -> 0 | R16: =COUNTIFS( 'IB MRO'!$D:$D,"RFS", 'IB MRO'!$U:$U,"<>YES", 'IB MRO'!$K:$K,"<"&$B$1, 'IB MRO'!$N:$N,"" ) + COUNTIFS( 'IB MRO'!$D:$D,"RFS", 'IB MRO'!$U:$U,"<>YES", 'IB MRO'!$K:$K,"<"&$B$1, 'IB MRO'!$N:$N,">="&$B$1 ) + COUNTIFS( 'IB MRO'!$D:$D,"RFS", 'IB MRO'!$U:$U,"<>YES", 'IB MRO'!$K:$K,">="&$B$1, 'IB MRO'!$K:$K,"<"&$C$1+1 ) - COUNTIFS( 'IB MRO'!$D:$D,"RFS", 'IB MRO'!$I:$I,"Closed", 'IB MRO'!$U:$U,"<>YES", 'IB MRO'!$N:$N,">="&$B$1, 'IB MRO'!$N:$N,"<"&$C$1+1 ) - COUNTIFS( 'IB MRO'!$D:$D,"RFS", 'IB MRO'!$I:$I,"Triaged", 'IB MRO'!$U:$U,"<>YES", 'IB MRO'!$N:$N,">="&$B$1, 'IB MRO'!$N:$N,"<"&$C$1+1 ) -> 1 | S16: =SUM( COUNTIFS( 'IB MRO'!$D:$D,"P_Ticket", 'IB MRO'!$G:$G,"Low", 'IB MRO'!$U:$U,"NO", 'IB MRO'!$L:$L,">="&$B$1, 'IB MRO'!$L:$L,"<"&$C$1+1 ), COUNTIFS( 'IB MRO'!$D:$D,"P_Ticket", 'IB MRO'!$G:$G,"Medium", 'IB MRO'!$U:$U,"NO", 'IB MRO'!$L:$L,">="&$B$1, 'IB MRO'!$L:$L,"<"&$C$1+1 ), COUNTIFS( 'IB MRO'!$D:$D,"P_Ticket", 'IB MRO'!$G:$G,"High", 'IB MRO'!$U:$U,"NO", 'IB MRO'!$L:$L,">="&$B$1, 'IB MRO'!$L:$L,"<"&$C$1+1 ) ) -> 0 | T16: =SUM( COUNTIFS( 'IB MRO'!$D:$D,"P_Ticket", 'IB MRO'!$G:$G,"Low", 'IB MRO'!$I:$I,"Closed", 'IB MRO'!$U:$U,"NO", 'IB MRO'!$N:$N,"<"&$C$1+1, 'IB MRO'!$N:$N,">="&$B$1 ), COUNTIFS( 'IB MRO'!$D:$D,"P_Ticket", 'IB MRO'!$G:$G,"Medium", 'IB MRO'!$I:$I,"Closed", 'IB MRO'!$U:$U,"NO", 'IB MRO'!$N:$N,"<"&$C$1+1, 'IB MRO'!$N:$N,">="&$B$1 ), COUNTIFS( 'IB MRO'!$D:$D,"P_Ticket", 'IB MRO'!$G:$G,"High", 'IB MRO'!$I:$I,"Closed", 'IB MRO'!$U:$U,"NO", 'IB MRO'!$N:$N,"<"&$C$1+1, 'IB MRO'!$N:$N,">="&$B$1 ), COUNTIFS( 'IB MRO'!$D:$D,"P_Ticket", 'IB MRO'!$G:$G,"Low", 'IB MRO'!$I:$I,"Triaged", 'IB MRO'!$U:$U,"NO", 'IB MRO'!$N:$N,"<"&$C$1+1, 'IB MRO'!$N:$N,">="&$B$1 ), COUNTIFS( 'IB MRO'!$D:$D,"P_Ticket", 'IB MRO'!$G:$G,"Medium", 'IB MRO'!$I:$I,"Triaged", 'IB MRO'!$U:$U,"NO", 'IB MRO'!$N:$N,"<"&$C$1+1, 'IB MRO'!$N:$N,">="&$B$1 ), COUNTIFS( 'IB MRO'!$D:$D,"P_Ticket", 'IB MRO'!$G:$G,"High", 'IB MRO'!$I:$I,"Triaged", 'IB MRO'!$U:$U,"NO", 'IB MRO'!$N:$N,"<"&$C$1+1, 'IB MRO'!$N:$N,">="&$B$1 ) ) -> 0 | W16: =COUNTIFS( 'IB MRO'!$D:$D,"P_Ticket", 'IB MRO'!$G:$G,"High", 'IB MRO'!$U:$U,"NO", 'IB MRO'!$L:$L,">="&$B$1, 'IB MRO'!$L:$L,"<"&$C$1+1 ) -> 0 | X16: =SUM( COUNTIFS( 'IB MRO'!$D:$D,"P_Ticket", 'IB MRO'!$G:$G,"High", 'IB MRO'!$I:$I,"Closed", 'IB MRO'!$U:$U,"NO", 'IB MRO'!$N:$N,"<"&$C$1+1, 'IB MRO'!$N:$N,">="&$B$1 ), COUNTIFS( 'IB MRO'!$D:$D,"P_Ticket", 'IB MRO'!$G:$G,"High", 'IB MRO'!$I:$I,"Triaged", 'IB MRO'!$U:$U,"NO", 'IB MRO'!$N:$N,"<"&$C$1+1, 'IB MRO'!$N:$N,">="&$B$1 ) ) -> 0
A17: APPSUP_GROUNDOPS | B17: EI | C17: AO | D17: =COUNTIFS( 'EI AO'!$D:$D,"Incident", 'EI AO'!$G:$G,1, 'EI AO'!$U:$U,"NO", 'EI AO'!$L:$L,">="&$B$1, 'EI AO'!$L:$L,"<"&$C$1+1 ) -> 0 | E17: =SUM( COUNTIFS( 'EI AO'!$D:$D,"Incident", 'EI AO'!$G:$G,1, 'EI AO'!$I:$I,"Closed", 'EI AO'!$U:$U,"NO", 'EI AO'!$N:$N,">="&$B$1, 'EI AO'!$N:$N,"<"&$C$1+1 ), COUNTIFS( 'EI AO'!$D:$D,"Incident", 'EI AO'!$G:$G,1, 'EI AO'!$I:$I,"Triaged", 'EI AO'!$U:$U,"NO", 'EI AO'!$N:$N,">="&$B$1, 'EI AO'!$N:$N,"<"&$C$1+1 ) ) -> 0 | F17: =COUNTIFS( 'EI AO'!$D:$D,"Incident", 'EI AO'!$G:$G,1, 'EI AO'!$U:$U,"<>YES", 'EI AO'!$K:$K,"<"&$B$1, 'EI AO'!$N:$N,"" ) + COUNTIFS( 'EI AO'!$D:$D,"Incident", 'EI AO'!$G:$G,1, 'EI AO'!$U:$U,"<>YES", 'EI AO'!$K:$K,"<"&$B$1, 'EI AO'!$N:$N,">="&$B$1 ) + COUNTIFS( 'EI AO'!$D:$D,"Incident", 'EI AO'!$G:$G,1, 'EI AO'!$U:$U,"<>YES", 'EI AO'!$K:$K,">="&$B$1, 'EI AO'!$K:$K,"<"&$C$1+1 ) - COUNTIFS( 'EI AO'!$D:$D,"Incident", 'EI AO'!$G:$G,1, 'EI AO'!$U:$U,"<>YES", 'EI AO'!$I:$I,"Closed", 'EI AO'!$N:$N,">="&$B$1, 'EI AO'!$N:$N,"<"&$C$1+1 ) - COUNTIFS( 'EI AO'!$D:$D,"Incident", 'EI AO'!$G:$G,1, 'EI AO'!$U:$U,"<>YES", 'EI AO'!$I:$I,"Triaged", 'EI AO'!$N:$N,">="&$B$1, 'EI AO'!$N:$N,"<"&$C$1+1 ) -> 0 | G17: =COUNTIFS( 'EI AO'!$D:$D,"Incident", 'EI AO'!$G:$G,2, 'EI AO'!$U:$U,"NO", 'EI AO'!$L:$L,">="&$B$1, 'EI AO'!$L:$L,"<"&$C$1+1 ) -> 0 | H17: =SUM( COUNTIFS( 'EI AO'!$D:$D,"Incident", 'EI AO'!$G:$G,2, 'EI AO'!$I:$I,"Closed", 'EI AO'!$U:$U,"NO", 'EI AO'!$N:$N,">="&$B$1, 'EI AO'!$N:$N,"<"&$C$1+1 ), COUNTIFS( 'EI AO'!$D:$D,"Incident", 'EI AO'!$G:$G,2, 'EI AO'!$I:$I,"Triaged", 'EI AO'!$U:$U,"NO", 'EI AO'!$N:$N,">="&$B$1, 'EI AO'!$N:$N,"<"&$C$1+1 ) ) -> 0 | I17: =COUNTIFS( 'EI AO'!$D:$D,"Incident", 'EI AO'!$G:$G,2, 'EI AO'!$U:$U,"<>YES", 'EI AO'!$K:$K,"<"&$B$1, 'EI AO'!$N:$N,"" ) + COUNTIFS( 'EI AO'!$D:$D,"Incident", 'EI AO'!$G:$G,2, 'EI AO'!$U:$U,"<>YES", 'EI AO'!$K:$K,"<"&$B$1, 'EI AO'!$N:$N,">="&$B$1 ) + COUNTIFS( 'EI AO'!$D:$D,"Incident", 'EI AO'!$G:$G,2, 'EI AO'!$U:$U,"<>YES", 'EI AO'!$K:$K,">="&$B$1, 'EI AO'!$K:$K,"<"&$C$1+1 ) - COUNTIFS( 'EI AO'!$D:$D,"Incident", 'EI AO'!$G:$G,2, 'EI AO'!$U:$U,"<>YES", 'EI AO'!$I:$I,"Closed", 'EI AO'!$N:$N,">="&$B$1, 'EI AO'!$N:$N,"<"&$C$1+1 ) - COUNTIFS( 'EI AO'!$D:$D,"Incident", 'EI AO'!$G:$G,2, 'EI AO'!$U:$U,"<>YES", 'EI AO'!$I:$I,"Triaged", 'EI AO'!$N:$N,">="&$B$1, 'EI AO'!$N:$N,"<"&$C$1+1 ) -> 0 | J17: =COUNTIFS( 'EI AO'!$D:$D,"Incident", 'EI AO'!$G:$G,3, 'EI AO'!$U:$U,"NO", 'EI AO'!$L:$L,">="&$B$1, 'EI AO'!$L:$L,"<"&$C$1+1 ) -> 0 | K17: =SUM( COUNTIFS( 'EI AO'!$D:$D,"Incident", 'EI AO'!$G:$G,3, 'EI AO'!$I:$I,"Closed", 'EI AO'!$U:$U,"NO", 'EI AO'!$N:$N,">="&$B$1, 'EI AO'!$N:$N,"<"&$C$1+1 ), COUNTIFS( 'EI AO'!$D:$D,"Incident", 'EI AO'!$G:$G,3, 'EI AO'!$I:$I,"Triaged", 'EI AO'!$U:$U,"NO", 'EI AO'!$N:$N,">="&$B$1, 'EI AO'!$N:$N,"<"&$C$1+1 ) ) -> 0 | L17: =COUNTIFS( 'EI AO'!$D:$D,"Incident", 'EI AO'!$G:$G,3, 'EI AO'!$U:$U,"<>YES", 'EI AO'!$K:$K,"<"&$B$1, 'EI AO'!$N:$N,"" ) + COUNTIFS( 'EI AO'!$D:$D,"Incident", 'EI AO'!$G:$G,3, 'EI AO'!$U:$U,"<>YES", 'EI AO'!$K:$K,"<"&$B$1, 'EI AO'!$N:$N,">="&$B$1 ) + COUNTIFS( 'EI AO'!$D:$D,"Incident", 'EI AO'!$G:$G,3, 'EI AO'!$U:$U,"<>YES", 'EI AO'!$K:$K,">="&$B$1, 'EI AO'!$K:$K,"<"&$C$1+1 ) - COUNTIFS( 'EI AO'!$D:$D,"Incident", 'EI AO'!$G:$G,3, 'EI AO'!$U:$U,"<>YES", 'EI AO'!$I:$I,"Closed", 'EI AO'!$N:$N,">="&$B$1, 'EI AO'!$N:$N,"<"&$C$1+1 ) - COUNTIFS( 'EI AO'!$D:$D,"Incident", 'EI AO'!$G:$G,3, 'EI AO'!$U:$U,"<>YES", 'EI AO'!$I:$I,"Triaged", 'EI AO'!$N:$N,">="&$B$1, 'EI AO'!$N:$N,"<"&$C$1+1 ) -> 0 | M17: =COUNTIFS( 'EI AO'!$D:$D,"Incident", 'EI AO'!$G:$G,4, 'EI AO'!$U:$U,"NO", 'EI AO'!$L:$L,">="&$B$1, 'EI AO'!$L:$L,"<"&$C$1+1 ) -> 1 | N17: =SUM( COUNTIFS( 'EI AO'!$D:$D,"Incident", 'EI AO'!$G:$G,4, 'EI AO'!$I:$I,"Closed", 'EI AO'!$U:$U,"NO", 'EI AO'!$N:$N,">="&$B$1, 'EI AO'!$N:$N,"<"&$C$1+1 ), COUNTIFS( 'EI AO'!$D:$D,"Incident", 'EI AO'!$G:$G,4, 'EI AO'!$I:$I,"Triaged", 'EI AO'!$U:$U,"NO", 'EI AO'!$N:$N,">="&$B$1, 'EI AO'!$N:$N,"<"&$C$1+1 ) ) -> 1 | O17: =COUNTIFS( 'EI AO'!$D:$D,"Incident", 'EI AO'!$G:$G,4, 'EI AO'!$U:$U,"<>YES", 'EI AO'!$K:$K,"<"&$B$1, 'EI AO'!$N:$N,"" ) + COUNTIFS( 'EI AO'!$D:$D,"Incident", 'EI AO'!$G:$G,4, 'EI AO'!$U:$U,"<>YES", 'EI AO'!$K:$K,"<"&$B$1, 'EI AO'!$N:$N,">="&$B$1 ) + COUNTIFS( 'EI AO'!$D:$D,"Incident", 'EI AO'!$G:$G,4, 'EI AO'!$U:$U,"<>YES", 'EI AO'!$K:$K,">="&$B$1, 'EI AO'!$K:$K,"<"&$C$1+1 ) - COUNTIFS( 'EI AO'!$D:$D,"Incident", 'EI AO'!$G:$G,4, 'EI AO'!$U:$U,"<>YES", 'EI AO'!$I:$I,"Closed", 'EI AO'!$N:$N,">="&$B$1, 'EI AO'!$N:$N,"<"&$C$1+1 ) - COUNTIFS( 'EI AO'!$D:$D,"Incident", 'EI AO'!$G:$G,4, 'EI AO'!$U:$U,"<>YES", 'EI AO'!$I:$I,"Triaged", 'EI AO'!$N:$N,">="&$B$1, 'EI AO'!$N:$N,"<"&$C$1+1 ) -> 0 | P17: =COUNTIFS( 'EI AO'!$D:$D,"RFS", 'EI AO'!$U:$U,"NO", 'EI AO'!$L:$L,">="&$B$1, 'EI AO'!$L:$L,"<"&$C$1+1 ) -> 5 | Q17: =SUM( COUNTIFS( 'EI AO'!$D:$D,"RFS", 'EI AO'!$I:$I,"Closed", 'EI AO'!$U:$U,"NO", 'EI AO'!$N:$N,">="&$B$1, 'EI AO'!$N:$N,"<"&$C$1+1 ), COUNTIFS( 'EI AO'!$D:$D,"RFS", 'EI AO'!$I:$I,"Triaged", 'EI AO'!$U:$U,"NO", 'EI AO'!$N:$N,">="&$B$1, 'EI AO'!$N:$N,"<"&$C$1+1 ) ) -> 5 | R17: =COUNTIFS( 'EI AO'!$D:$D,"RFS", 'EI AO'!$U:$U,"<>YES", 'EI AO'!$K:$K,"<"&$B$1, 'EI AO'!$N:$N,"" ) + COUNTIFS( 'EI AO'!$D:$D,"RFS", 'EI AO'!$U:$U,"<>YES", 'EI AO'!$K:$K,"<"&$B$1, 'EI AO'!$N:$N,">="&$B$1 ) + COUNTIFS( 'EI AO'!$D:$D,"RFS", 'EI AO'!$U:$U,"<>YES", 'EI AO'!$K:$K,">="&$B$1, 'EI AO'!$K:$K,"<"&$C$1+1 ) - COUNTIFS( 'EI AO'!$D:$D,"RFS", 'EI AO'!$I:$I,"Closed", 'EI AO'!$U:$U,"<>YES", 'EI AO'!$N:$N,">="&$B$1, 'EI AO'!$N:$N,"<"&$C$1+1 ) - COUNTIFS( 'EI AO'!$D:$D,"RFS", 'EI AO'!$I:$I,"Triaged", 'EI AO'!$U:$U,"<>YES", 'EI AO'!$N:$N,">="&$B$1, 'EI AO'!$N:$N,"<"&$C$1+1 ) -> 0 | S17: =SUM( COUNTIFS( 'EI AO'!$D:$D,"P_Ticket", 'EI AO'!$G:$G,"Low", 'EI AO'!$U:$U,"NO", 'EI AO'!$L:$L,">="&$B$1, 'EI AO'!$L:$L,"<"&$C$1+1 ), COUNTIFS( 'EI AO'!$D:$D,"P_Ticket", 'EI AO'!$G:$G,"Medium", 'EI AO'!$U:$U,"NO", 'EI AO'!$L:$L,">="&$B$1, 'EI AO'!$L:$L,"<"&$C$1+1 ), COUNTIFS( 'EI AO'!$D:$D,"P_Ticket", 'EI AO'!$G:$G,"High", 'EI AO'!$U:$U,"NO", 'EI AO'!$L:$L,">="&$B$1, 'EI AO'!$L:$L,"<"&$C$1+1 ) ) -> 0 | T17: =SUM( COUNTIFS( 'EI AO'!$D:$D,"P_Ticket", 'EI AO'!$G:$G,"Low", 'EI AO'!$I:$I,"Closed", 'EI AO'!$U:$U,"NO", 'EI AO'!$N:$N,"<"&$C$1+1, 'EI AO'!$N:$N,">="&$B$1 ), COUNTIFS( 'EI AO'!$D:$D,"P_Ticket", 'EI AO'!$G:$G,"Medium", 'EI AO'!$I:$I,"Closed", 'EI AO'!$U:$U,"NO", 'EI AO'!$N:$N,"<"&$C$1+1, 'EI AO'!$N:$N,">="&$B$1 ), COUNTIFS( 'EI AO'!$D:$D,"P_Ticket", 'EI AO'!$G:$G,"High", 'EI AO'!$I:$I,"Closed", 'EI AO'!$U:$U,"NO", 'EI AO'!$N:$N,"<"&$C$1+1, 'EI AO'!$N:$N,">="&$B$1 ), COUNTIFS( 'EI AO'!$D:$D,"P_Ticket", 'EI AO'!$G:$G,"Low", 'EI AO'!$I:$I,"Triaged", 'EI AO'!$U:$U,"NO", 'EI AO'!$N:$N,"<"&$C$1+1, 'EI AO'!$N:$N,">="&$B$1 ), COUNTIFS( 'EI AO'!$D:$D,"P_Ticket", 'EI AO'!$G:$G,"Medium", 'EI AO'!$I:$I,"Triaged", 'EI AO'!$U:$U,"NO", 'EI AO'!$N:$N,"<"&$C$1+1, 'EI AO'!$N:$N,">="&$B$1 ), COUNTIFS( 'EI AO'!$D:$D,"P_Ticket", 'EI AO'!$G:$G,"High", 'EI AO'!$I:$I,"Triaged", 'EI AO'!$U:$U,"NO", 'EI AO'!$N:$N,"<"&$C$1+1, 'EI AO'!$N:$N,">="&$B$1 ) ) -> 0 | W17: =COUNTIFS( 'EI AO'!$D:$D,"P_Ticket", 'EI AO'!$G:$G,"High", 'EI AO'!$U:$U,"NO", 'EI AO'!$L:$L,">="&$B$1, 'EI AO'!$L:$L,"<"&$C$1+1 ) -> 0 | X17: =SUM( COUNTIFS( 'EI AO'!$D:$D,"P_Ticket", 'EI AO'!$G:$G,"High", 'EI AO'!$I:$I,"Closed", 'EI AO'!$U:$U,"NO", 'EI AO'!$N:$N,"<"&$C$1+1, 'EI AO'!$N:$N,">="&$B$1 ), COUNTIFS( 'EI AO'!$D:$D,"P_Ticket", 'EI AO'!$G:$G,"High", 'EI AO'!$I:$I,"Triaged", 'EI AO'!$U:$U,"NO", 'EI AO'!$N:$N,"<"&$C$1+1, 'EI AO'!$N:$N,">="&$B$1 ) ) -> 0
A18: APPSUP_ITTOOLS | B18: EI | C18: SharePoint | D18: =COUNTIFS( 'EI BackOffice'!$D:$D,"Incident", 'EI BackOffice'!$G:$G,1, 'EI BackOffice'!$C:$C,"SharePoint", 'EI BackOffice'!$U:$U,"NO", 'EI BackOffice'!$L:$L,">="&$B$1, 'EI BackOffice'!$L:$L,"<"&$C$1+1 ) -> 0 | E18: =SUM( COUNTIFS( 'EI BackOffice'!$D:$D,"Incident", 'EI BackOffice'!$C:$C,"SharePoint", 'EI BackOffice'!$G:$G,1, 'EI BackOffice'!$I:$I,"Closed", 'EI BackOffice'!$U:$U,"NO", 'EI BackOffice'!$N:$N,">="&$B$1, 'EI BackOffice'!$N:$N,"<"&$C$1+1 ), COUNTIFS( 'EI BackOffice'!$D:$D,"Incident", 'EI BackOffice'!$C:$C,"SharePoint", 'EI BackOffice'!$G:$G,1, 'EI BackOffice'!$I:$I,"Triaged", 'EI BackOffice'!$U:$U,"NO", 'EI BackOffice'!$N:$N,">="&$B$1, 'EI BackOffice'!$N:$N,"<"&$C$1+1 ) ) -> 0 | F18: =COUNTIFS( 'EI BackOffice'!$C:$C,"SharePoint", 'EI BackOffice'!$D:$D,"Incident", 'EI BackOffice'!$G:$G,1, 'EI BackOffice'!$S:$S,"<>YES", 'EI BackOffice'!$K:$K,"<"&$B$1, 'EI BackOffice'!$N:$N,"" ) + COUNTIFS( 'EI BackOffice'!$C:$C,"SharePoint", 'EI BackOffice'!$D:$D,"Incident", 'EI BackOffice'!$G:$G,1, 'EI BackOffice'!$S:$S,"<>YES", 'EI BackOffice'!$K:$K,"<"&$B$1, 'EI BackOffice'!$N:$N,">="&$B$1 ) + COUNTIFS( 'EI BackOffice'!$C:$C,"SharePoint", 'EI BackOffice'!$D:$D,"Incident", 'EI BackOffice'!$G:$G,1, 'EI BackOffice'!$S:$S,"<>YES", 'EI BackOffice'!$K:$K,">="&$B$1, 'EI BackOffice'!$K:$K,"<"&$C$1+1 ) - COUNTIFS( 'EI BackOffice'!$C:$C,"SharePoint", 'EI BackOffice'!$D:$D,"Incident", 'EI BackOffice'!$G:$G,1, 'EI BackOffice'!$S:$S,"<>YES", 'EI BackOffice'!$I:$I,"Closed", 'EI BackOffice'!$N:$N,">="&$B$1, 'EI BackOffice'!$N:$N,"<"&$C$1+1 ) - COUNTIFS( 'EI BackOffice'!$C:$C,"SharePoint", 'EI BackOffice'!$D:$D,"Incident", 'EI BackOffice'!$G:$G,1, 'EI BackOffice'!$S:$S,"<>YES", 'EI BackOffice'!$I:$I,"Triaged", 'EI BackOffice'!$N:$N,">="&$B$1, 'EI BackOffice'!$N:$N,"<"&$C$1+1 ) -> 0 | G18: =COUNTIFS( 'EI BackOffice'!$D:$D,"Incident", 'EI BackOffice'!$G:$G,2, 'EI BackOffice'!$C:$C,"SharePoint", 'EI BackOffice'!$U:$U,"NO", 'EI BackOffice'!$L:$L,">="&$B$1, 'EI BackOffice'!$L:$L,"<"&$C$1+1 ) -> 0 | H18: =SUM( COUNTIFS( 'EI BackOffice'!$D:$D,"Incident", 'EI BackOffice'!$C:$C,"SharePoint", 'EI BackOffice'!$G:$G,2, 'EI BackOffice'!$I:$I,"Closed", 'EI BackOffice'!$U:$U,"NO", 'EI BackOffice'!$N:$N,">="&$B$1, 'EI BackOffice'!$N:$N,"<"&$C$1+1 ), COUNTIFS( 'EI BackOffice'!$D:$D,"Incident", 'EI BackOffice'!$C:$C,"SharePoint", 'EI BackOffice'!$G:$G,2, 'EI BackOffice'!$I:$I,"Triaged", 'EI BackOffice'!$U:$U,"NO", 'EI BackOffice'!$N:$N,">="&$B$1, 'EI BackOffice'!$N:$N,"<"&$C$1+1 ) ) -> 0 | I18: =COUNTIFS( 'EI BackOffice'!$C:$C,"SharePoint", 'EI BackOffice'!$D:$D,"Incident", 'EI BackOffice'!$G:$G,2, 'EI BackOffice'!$S:$S,"<>YES", 'EI BackOffice'!$K:$K,"<"&$B$1, 'EI BackOffice'!$N:$N,"" ) + COUNTIFS( 'EI BackOffice'!$C:$C,"SharePoint", 'EI BackOffice'!$D:$D,"Incident", 'EI BackOffice'!$G:$G,2, 'EI BackOffice'!$S:$S,"<>YES", 'EI BackOffice'!$K:$K,"<"&$B$1, 'EI BackOffice'!$N:$N,">="&$B$1 ) + COUNTIFS( 'EI BackOffice'!$C:$C,"SharePoint", 'EI BackOffice'!$D:$D,"Incident", 'EI BackOffice'!$G:$G,2, 'EI BackOffice'!$S:$S,"<>YES", 'EI BackOffice'!$K:$K,">="&$B$1, 'EI BackOffice'!$K:$K,"<"&$C$1+1 ) - COUNTIFS( 'EI BackOffice'!$C:$C,"SharePoint", 'EI BackOffice'!$D:$D,"Incident", 'EI BackOffice'!$G:$G,2, 'EI BackOffice'!$S:$S,"<>YES", 'EI BackOffice'!$I:$I,"Closed", 'EI BackOffice'!$N:$N,">="&$B$1, 'EI BackOffice'!$N:$N,"<"&$C$1+1 ) - COUNTIFS( 'EI BackOffice'!$C:$C,"SharePoint", 'EI BackOffice'!$D:$D,"Incident", 'EI BackOffice'!$G:$G,2, 'EI BackOffice'!$S:$S,"<>YES", 'EI BackOffice'!$I:$I,"Triaged", 'EI BackOffice'!$N:$N,">="&$B$1, 'EI BackOffice'!$N:$N,"<"&$C$1+1 ) -> 0 | J18: =COUNTIFS( 'EI BackOffice'!$D:$D,"Incident", 'EI BackOffice'!$G:$G,3, 'EI BackOffice'!$C:$C,"SharePoint", 'EI BackOffice'!$U:$U,"NO", 'EI BackOffice'!$L:$L,">="&$B$1, 'EI BackOffice'!$L:$L,"<"&$C$1+1 ) -> 0 | K18: =SUM( COUNTIFS( 'EI BackOffice'!$D:$D,"Incident", 'EI BackOffice'!$C:$C,"SharePoint", 'EI BackOffice'!$G:$G,3, 'EI BackOffice'!$I:$I,"Closed", 'EI BackOffice'!$U:$U,"NO", 'EI BackOffice'!$N:$N,">="&$B$1, 'EI BackOffice'!$N:$N,"<"&$C$1+1 ), COUNTIFS( 'EI BackOffice'!$D:$D,"Incident", 'EI BackOffice'!$C:$C,"SharePoint", 'EI BackOffice'!$G:$G,3, 'EI BackOffice'!$I:$I,"Triaged", 'EI BackOffice'!$U:$U,"NO", 'EI BackOffice'!$N:$N,">="&$B$1, 'EI BackOffice'!$N:$N,"<"&$C$1+1 ) ) -> 0 | L18: =COUNTIFS( 'EI BackOffice'!$C:$C,"SharePoint", 'EI BackOffice'!$D:$D,"Incident", 'EI BackOffice'!$G:$G,3, 'EI BackOffice'!$S:$S,"<>YES", 'EI BackOffice'!$K:$K,"<"&$B$1, 'EI BackOffice'!$N:$N,"" ) + COUNTIFS( 'EI BackOffice'!$C:$C,"SharePoint", 'EI BackOffice'!$D:$D,"Incident", 'EI BackOffice'!$G:$G,3, 'EI BackOffice'!$S:$S,"<>YES", 'EI BackOffice'!$K:$K,"<"&$B$1, 'EI BackOffice'!$N:$N,">="&$B$1 ) + COUNTIFS( 'EI BackOffice'!$C:$C,"SharePoint", 'EI BackOffice'!$D:$D,"Incident", 'EI BackOffice'!$G:$G,3, 'EI BackOffice'!$S:$S,"<>YES", 'EI BackOffice'!$K:$K,">="&$B$1, 'EI BackOffice'!$K:$K,"<"&$C$1+1 ) - COUNTIFS( 'EI BackOffice'!$C:$C,"SharePoint", 'EI BackOffice'!$D:$D,"Incident", 'EI BackOffice'!$G:$G,3, 'EI BackOffice'!$S:$S,"<>YES", 'EI BackOffice'!$I:$I,"Closed", 'EI BackOffice'!$N:$N,">="&$B$1, 'EI BackOffice'!$N:$N,"<"&$C$1+1 ) - COUNTIFS( 'EI BackOffice'!$C:$C,"SharePoint", 'EI BackOffice'!$D:$D,"Incident", 'EI BackOffice'!$G:$G,3, 'EI BackOffice'!$S:$S,"<>YES", 'EI BackOffice'!$I:$I,"Triaged", 'EI BackOffice'!$N:$N,">="&$B$1, 'EI BackOffice'!$N:$N,"<"&$C$1+1 ) -> 0 | M18: =COUNTIFS( 'EI BackOffice'!$D:$D,"Incident", 'EI BackOffice'!$G:$G,4, 'EI BackOffice'!$C:$C,"SharePoint", 'EI BackOffice'!$U:$U,"NO", 'EI BackOffice'!$L:$L,">="&$B$1, 'EI BackOffice'!$L:$L,"<"&$C$1+1 ) -> 0 | N18: =SUM( COUNTIFS( 'EI BackOffice'!$D:$D,"Incident", 'EI BackOffice'!$C:$C,"SharePoint", 'EI BackOffice'!$G:$G,4, 'EI BackOffice'!$I:$I,"Closed", 'EI BackOffice'!$U:$U,"NO", 'EI BackOffice'!$N:$N,">="&$B$1, 'EI BackOffice'!$N:$N,"<"&$C$1+1 ), COUNTIFS( 'EI BackOffice'!$D:$D,"Incident", 'EI BackOffice'!$C:$C,"SharePoint", 'EI BackOffice'!$G:$G,4, 'EI BackOffice'!$I:$I,"Triaged", 'EI BackOffice'!$U:$U,"NO", 'EI BackOffice'!$N:$N,">="&$B$1, 'EI BackOffice'!$N:$N,"<"&$C$1+1 ) ) -> 0 | O18: =COUNTIFS( 'EI BackOffice'!$C:$C,"SharePoint", 'EI BackOffice'!$D:$D,"Incident", 'EI BackOffice'!$G:$G,4, 'EI BackOffice'!$S:$S,"<>YES", 'EI BackOffice'!$K:$K,"<"&$B$1, 'EI BackOffice'!$N:$N,"" ) + COUNTIFS( 'EI BackOffice'!$C:$C,"SharePoint", 'EI BackOffice'!$D:$D,"Incident", 'EI BackOffice'!$G:$G,4, 'EI BackOffice'!$S:$S,"<>YES", 'EI BackOffice'!$K:$K,"<"&$B$1, 'EI BackOffice'!$N:$N,">="&$B$1 ) + COUNTIFS( 'EI BackOffice'!$C:$C,"SharePoint", 'EI BackOffice'!$D:$D,"Incident", 'EI BackOffice'!$G:$G,4, 'EI BackOffice'!$S:$S,"<>YES", 'EI BackOffice'!$K:$K,">="&$B$1, 'EI BackOffice'!$K:$K,"<"&$C$1+1 ) - COUNTIFS( 'EI BackOffice'!$C:$C,"SharePoint", 'EI BackOffice'!$D:$D,"Incident", 'EI BackOffice'!$G:$G,4, 'EI BackOffice'!$S:$S,"<>YES", 'EI BackOffice'!$I:$I,"Closed", 'EI BackOffice'!$N:$N,">="&$B$1, 'EI BackOffice'!$N:$N,"<"&$C$1+1 ) - COUNTIFS( 'EI BackOffice'!$C:$C,"SharePoint", 'EI BackOffice'!$D:$D,"Incident", 'EI BackOffice'!$G:$G,4, 'EI BackOffice'!$S:$S,"<>YES", 'EI BackOffice'!$I:$I,"Triaged", 'EI BackOffice'!$N:$N,">="&$B$1, 'EI BackOffice'!$N:$N,"<"&$C$1+1 ) -> 0 | P18: =COUNTIFS( 'EI BackOffice'!$D:$D,"RFS", 'EI BackOffice'!$C:$C,"SharePoint", 'EI BackOffice'!$U:$U,"No", 'EI BackOffice'!$L:$L,">="&$B$1, 'EI BackOffice'!$L:$L,"<"&$C$1+1 ) -> 0 | Q18: =SUM( COUNTIFS( 'EI BackOffice'!$D:$D,"RFS", 'EI BackOffice'!$C:$C,"SharePoint", 'EI BackOffice'!$I:$I,"Closed", 'EI BackOffice'!$U:$U,"NO", 'EI BackOffice'!$N:$N,">="&$B$1, 'EI BackOffice'!$N:$N,"<"&$C$1+1 ), COUNTIFS( 'EI BackOffice'!$D:$D,"RFS", 'EI BackOffice'!$C:$C,"SharePoint", 'EI BackOffice'!$I:$I,"Triaged", 'EI BackOffice'!$U:$U,"NO", 'EI BackOffice'!$N:$N,">="&$B$1, 'EI BackOffice'!$N:$N,"<"&$C$1+1 ) ) -> 0 | R18: =COUNTIFS( 'EI BackOffice'!$D:$D,"RFS", 'EI BackOffice'!$C:$C,"SharePoint", 'EI BackOffice'!$U:$U,"<>YES", 'EI BackOffice'!$K:$K,"<"&$B$1, 'EI BackOffice'!$N:$N,"" ) + COUNTIFS( 'EI BackOffice'!$D:$D,"RFS", 'EI BackOffice'!$C:$C,"SharePoint", 'EI BackOffice'!$U:$U,"<>YES", 'EI BackOffice'!$K:$K,"<"&$B$1, 'EI BackOffice'!$N:$N,">="&$B$1 ) + COUNTIFS( 'EI BackOffice'!$D:$D,"RFS", 'EI BackOffice'!$C:$C,"SharePoint", 'EI BackOffice'!$U:$U,"<>YES", 'EI BackOffice'!$K:$K,">="&$B$1, 'EI BackOffice'!$K:$K,"<"&$C$1+1 ) - COUNTIFS( 'EI BackOffice'!$D:$D,"RFS", 'EI BackOffice'!$C:$C,"SharePoint", 'EI BackOffice'!$I:$I,"Closed", 'EI BackOffice'!$U:$U,"<>YES", 'EI BackOffice'!$N:$N,">="&$B$1, 'EI BackOffice'!$N:$N,"<"&$C$1+1 ) - COUNTIFS( 'EI BackOffice'!$D:$D,"RFS", 'EI BackOffice'!$C:$C,"SharePoint", 'EI BackOffice'!$I:$I,"Triaged", 'EI BackOffice'!$U:$U,"<>YES", 'EI BackOffice'!$N:$N,">="&$B$1, 'EI BackOffice'!$N:$N,"<"&$C$1+1 ) -> 0 | S18: =SUM( COUNTIFS( 'EI BackOffice'!$D:$D,"P_Ticket", 'EI BackOffice'!$G:$G,"Low", 'EI BackOffice'!$C:$C,"SharePoint", 'EI BackOffice'!$U:$U,"NO", 'EI BackOffice'!$L:$L,">="&$B$1, 'EI BackOffice'!$L:$L,"<"&$C$1+1 ), COUNTIFS( 'EI BackOffice'!$D:$D,"P_Ticket", 'EI BackOffice'!$G:$G,"Medium", 'EI BackOffice'!$C:$C,"SharePoint", 'EI BackOffice'!$U:$U,"NO", 'EI BackOffice'!$L:$L,">="&$B$1, 'EI BackOffice'!$L:$L,"<"&$C$1+1 ), COUNTIFS( 'EI BackOffice'!$D:$D,"P_Ticket", 'EI BackOffice'!$G:$G,"High", 'EI BackOffice'!$C:$C,"SharePoint", 'EI BackOffice'!$U:$U,"NO", 'EI BackOffice'!$L:$L,">="&$B$1, 'EI BackOffice'!$L:$L,"<"&$C$1+1 ) ) -> 0 | T18: =SUM( COUNTIFS( 'EI BackOffice'!$D:$D,"P_Ticket", 'EI BackOffice'!$C:$C,"SharePoint", 'EI BackOffice'!$G:$G,"Low", 'EI BackOffice'!$I:$I,"Closed", 'EI BackOffice'!$U:$U,"NO", 'EI BackOffice'!$N:$N,"<"&$C$1+1, 'EI BackOffice'!$N:$N,">="&$B$1 ), COUNTIFS( 'EI BackOffice'!$D:$D,"P_Ticket", 'EI BackOffice'!$C:$C,"SharePoint", 'EI BackOffice'!$G:$G,"Medium", 'EI BackOffice'!$I:$I,"Closed", 'EI BackOffice'!$U:$U,"NO", 'EI BackOffice'!$N:$N,"<"&$C$1+1, 'EI BackOffice'!$N:$N,">="&$B$1 ), COUNTIFS( 'EI BackOffice'!$D:$D,"P_Ticket", 'EI BackOffice'!$C:$C,"SharePoint", 'EI BackOffice'!$G:$G,"High", 'EI BackOffice'!$I:$I,"Closed", 'EI BackOffice'!$U:$U,"NO", 'EI BackOffice'!$N:$N,"<"&$C$1+1, 'EI BackOffice'!$N:$N,">="&$B$1 ), COUNTIFS( 'EI BackOffice'!$D:$D,"P_Ticket", 'EI BackOffice'!$C:$C,"SharePoint", 'EI BackOffice'!$G:$G,"Low", 'EI BackOffice'!$I:$I,"Triaged", 'EI BackOffice'!$U:$U,"NO", 'EI BackOffice'!$N:$N,"<"&$C$1+1, 'EI BackOffice'!$N:$N,">="&$B$1 ), COUNTIFS( 'EI BackOffice'!$D:$D,"P_Ticket", 'EI BackOffice'!$C:$C,"SharePoint", 'EI BackOffice'!$G:$G,"Medium", 'EI BackOffice'!$I:$I,"Triaged", 'EI BackOffice'!$U:$U,"NO", 'EI BackOffice'!$N:$N,"<"&$C$1+1, 'EI BackOffice'!$N:$N,">="&$B$1 ), COUNTIFS( 'EI BackOffice'!$D:$D,"P_Ticket", 'EI BackOffice'!$C:$C,"SharePoint", 'EI BackOffice'!$G:$G,"High", 'EI BackOffice'!$I:$I,"Triaged", 'EI BackOffice'!$U:$U,"NO", 'EI BackOffice'!$N:$N,"<"&$C$1+1, 'EI BackOffice'!$N:$N,">="&$B$1 ) ) -> 0 | W18: =COUNTIFS( 'EI BackOffice'!$D:$D,"P_Ticket", 'EI BackOffice'!$G:$G,"High", 'EI BackOffice'!$C:$C,"SharePoint", 'EI BackOffice'!$U:$U,"NO", 'EI BackOffice'!$L:$L,">="&$B$1, 'EI BackOffice'!$L:$L,"<"&$C$1+1 ) -> 0 | X18: =SUM( COUNTIFS( 'EI BackOffice'!$D:$D,"P_Ticket", 'EI BackOffice'!$C:$C,"SharePoint", 'EI BackOffice'!$G:$G,"High", 'EI BackOffice'!$I:$I,"Closed", 'EI BackOffice'!$U:$U,"NO", 'EI BackOffice'!$N:$N,"<"&$C$1+1, 'EI BackOffice'!$N:$N,">="&$B$1 ), COUNTIFS( 'EI BackOffice'!$D:$D,"P_Ticket", 'EI BackOffice'!$C:$C,"SharePoint", 'EI BackOffice'!$G:$G,"High", 'EI BackOffice'!$I:$I,"Triaged", 'EI BackOffice'!$U:$U,"NO", 'EI BackOffice'!$N:$N,"<"&$C$1+1, 'EI BackOffice'!$N:$N,">="&$B$1 ) ) -> 0
A19: APPSUP_CMJFE | B19: BA | C19: JFE
B20: Total | D20: =SUM(D4:D18) -> 0 | E20: =SUM(E4:E18) -> 0 | F20: =SUM(F4:F18) -> 0 | G20: =SUM(G4:G18) -> 0 | H20: =SUM(H4:H18) -> 0 | I20: =SUM(I4:I18) -> 0 | J20: =SUM(J4:J18) -> 16 | K20: =SUM(K4:K18) -> 27 | ... X20: =SUM(X4:X18) -> 0
B23: SLA Met
B25: Op Co | C25: Domain | D25: P1 Actioned | E25: Min Resolution | F25: Max Resolution | G25: Breach | H25: P2 Actioned | I25: Min Resolution | J25: Max Resolution | K25: Breach | L25: P3 Actioned | M25: Min Resolution | N25: Max Resolution | O25: Breach | P25: P4 Actioned | Q25: Min Resolution | R25: Max Resolution | S25: Breach
B26: BA | C26: SIP | D26: =SUM( COUNTIFS( SIP!$D:$D,"Incident", SIP!$G:$G,1, SIP!$C:$C,"SIP", SIP!$I:$I,"Closed", SIP!$U:$U,"NO", SIP!$N:$N,">="&$B$1, SIP!$N:$N,"<"&$C$1+1 ), COUNTIFS( SIP!$D:$D,"Incident", SIP!$G:$G,1, SIP!$C:$C,"SIP", SIP!$I:$I,"Triaged", SIP!$U:$U,"NO", SIP!$N:$N,">="&$B$1, SIP!$N:$N,"<"&$C$1+1 ) ) -> 0 | E26: =SUM( COUNTIFS( SIP!$D:$D,"Incident", SIP!$C:$C,"SIP", SIP!$G:$G,1, SIP!$I:$I,"Closed", SIP!$AI:$AI,"YES", SIP!$U:$U,"No", SIP!$N:$N,">="&$B$1, SIP!$N:$N,"<"&$C$1+1 ), COUNTIFS( SIP!$D:$D,"Incident", SIP!$C:$C,"SIP", SIP!$G:$G,1, SIP!$I:$I,"Triaged", SIP!$AI:$AI,"YES", SIP!$U:$U,"No", SIP!$N:$N,">="&$B$1, SIP!$N:$N,"<"&$C$1+1 ) ) -> 0 | F26: =SUM( COUNTIFS( SIP!$D:$D,"Incident", SIP!$C:$C,"SIP", SIP!$G:$G,1, SIP!$I:$I,"Closed", SIP!$AJ:$AJ,"YES", SIP!$U:$U,"No", SIP!$N:$N,">="&$B$1, SIP!$N:$N,"<"&$C$1+1 ), COUNTIFS( SIP!$D:$D,"Incident", SIP!$C:$C,"SIP", SIP!$G:$G,1, SIP!$I:$I,"Triaged", SIP!$AJ:$AJ,"YES", SIP!$U:$U,"No", SIP!$N:$N,">="&$B$1, SIP!$N:$N,"<"&$C$1+1 ) ) -> 0 | G26: =SUM( COUNTIFS( SIP!$D:$D,"Incident", SIP!$C:$C,"SIP", SIP!$G:$G,1, SIP!$I:$I,"Closed", SIP!$AI:$AI,"NO", SIP!$AJ:$AJ,"NO", SIP!$U:$U,"No", SIP!$N:$N,">="&$B$1, SIP!$N:$N,"<"&$C$1+1 ), COUNTIFS( SIP!$D:$D,"Incident", SIP!$C:$C,"SIP", SIP!$G:$G,1, SIP!$I:$I,"Triaged", SIP!$AI:$AI,"NO", SIP!$AJ:$AJ,"NO", SIP!$U:$U,"No", SIP!$N:$N,">="&$B$1, SIP!$N:$N,"<"&$C$1+1 ) ) -> 0 | H26: =SUM( COUNTIFS( SIP!$D:$D,"Incident", SIP!$G:$G,2, SIP!$C:$C,"SIP", SIP!$I:$I,"Closed", SIP!$U:$U,"NO", SIP!$N:$N,">="&$B$1, SIP!$N:$N,"<"&$C$1+1 ), COUNTIFS( SIP!$D:$D,"Incident", SIP!$G:$G,2, SIP!$C:$C,"SIP", SIP!$I:$I,"Triaged", SIP!$U:$U,"NO", SIP!$N:$N,">="&$B$1, SIP!$N:$N,"<"&$C$1+1 ) ) -> 0 | I26: =SUM( COUNTIFS( SIP!$D:$D,"Incident", SIP!$C:$C,"SIP", SIP!$G:$G,2, SIP!$I:$I,"Closed", SIP!$AI:$AI,"YES", SIP!$U:$U,"No", SIP!$N:$N,">="&$B$1, SIP!$N:$N,"<"&$C$1+1 ), COUNTIFS( SIP!$D:$D,"Incident", SIP!$C:$C,"SIP", SIP!$G:$G,2, SIP!$I:$I,"Triaged", SIP!$AI:$AI,"YES", SIP!$U:$U,"No", SIP!$N:$N,">="&$B$1, SIP!$N:$N,"<"&$C$1+1 ) ) -> 0 | J26: =SUM( COUNTIFS( SIP!$D:$D,"Incident", SIP!$C:$C,"SIP", SIP!$G:$G,2, SIP!$I:$I,"Closed", SIP!$AJ:$AJ,"YES", SIP!$U:$U,"No", SIP!$N:$N,">="&$B$1, SIP!$N:$N,"<"&$C$1+1 ), COUNTIFS( SIP!$D:$D,"Incident", SIP!$C:$C,"SIP", SIP!$G:$G,2, SIP!$I:$I,"Triaged", SIP!$AJ:$AJ,"YES", SIP!$U:$U,"No", SIP!$N:$N,">="&$B$1, SIP!$N:$N,"<"&$C$1+1 ) ) -> 0 | K26: =SUM( COUNTIFS( SIP!$D:$D,"Incident", SIP!$C:$C,"SIP", SIP!$G:$G,2, SIP!$I:$I,"Closed", SIP!$AI:$AI,"NO", SIP!$AJ:$AJ,"NO", SIP!$U:$U,"No", SIP!$N:$N,">="&$B$1, SIP!$N:$N,"<"&$C$1+1 ), COUNTIFS( SIP!$D:$D,"Incident", SIP!$C:$C,"SIP", SIP!$G:$G,2, SIP!$I:$I,"Triaged", SIP!$AI:$AI,"NO", SIP!$AJ:$AJ,"NO", SIP!$U:$U,"No", SIP!$N:$N,">="&$B$1, SIP!$N:$N,"<"&$C$1+1 ) ) -> 0 | L26: =SUM( COUNTIFS( SIP!$D:$D,"Incident", SIP!$G:$G,3, SIP!$C:$C,"SIP", SIP!$I:$I,"Closed", SIP!$U:$U,"NO", SIP!$N:$N,">="&$B$1, SIP!$N:$N,"<"&$C$1+1 ), COUNTIFS( SIP!$D:$D,"Incident", SIP!$G:$G,3, SIP!$C:$C,"SIP", SIP!$I:$I,"Triaged", SIP!$U:$U,"NO", SIP!$N:$N,">="&$B$1, SIP!$N:$N,"<"&$C$1+1 ) ) -> 0 | M26: =SUM( COUNTIFS( SIP!$D:$D,"Incident", SIP!$C:$C,"SIP", SIP!$G:$G,3, SIP!$I:$I,"Closed", SIP!$AI:$AI,"YES", SIP!$U:$U,"No", SIP!$N:$N,">="&$B$1, SIP!$N:$N,"<"&$C$1+1 ), COUNTIFS( SIP!$D:$D,"Incident", SIP!$C:$C,"SIP", SIP!$G:$G,3, SIP!$I:$I,"Triaged", SIP!$AI:$AI,"YES", SIP!$U:$U,"No", SIP!$N:$N,">="&$B$1, SIP!$N:$N,"<"&$C$1+1 ) ) -> 0 | N26: =SUM( COUNTIFS( SIP!$D:$D,"Incident", SIP!$C:$C,"SIP", SIP!$G:$G,3, SIP!$I:$I,"Closed", SIP!$AJ:$AJ,"YES", SIP!$U:$U,"No", SIP!$N:$N,">="&$B$1, SIP!$N:$N,"<"&$C$1+1 ), COUNTIFS( SIP!$D:$D,"Incident", SIP!$C:$C,"SIP", SIP!$G:$G,3, SIP!$I:$I,"Triaged", SIP!$AJ:$AJ,"YES", SIP!$U:$U,"No", SIP!$N:$N,">="&$B$1, SIP!$N:$N,"<"&$C$1+1 ) ) -> 0 | O26: =SUM( COUNTIFS( SIP!$D:$D,"Incident", SIP!$C:$C,"SIP", SIP!$G:$G,3, SIP!$I:$I,"Closed", SIP!$AI:$AI,"NO", SIP!$AJ:$AJ,"NO", SIP!$U:$U,"No", SIP!$N:$N,">="&$B$1, SIP!$N:$N,"<"&$C$1+1 ), COUNTIFS( SIP!$D:$D,"Incident", SIP!$C:$C,"SIP", SIP!$G:$G,3, SIP!$I:$I,"Triaged", SIP!$AI:$AI,"NO", SIP!$AJ:$AJ,"NO", SIP!$U:$U,"No", SIP!$N:$N,">="&$B$1, SIP!$N:$N,"<"&$C$1+1 ) ) -> 0 | P26: =SUM( COUNTIFS( SIP!$D:$D,"Incident", SIP!$G:$G,4, SIP!$C:$C,"SIP", SIP!$I:$I,"Closed", SIP!$U:$U,"NO", SIP!$N:$N,">="&$B$1, SIP!$N:$N,"<"&$C$1+1 ), COUNTIFS( SIP!$D:$D,"Incident", SIP!$G:$G,4, SIP!$C:$C,"SIP", SIP!$I:$I,"Triaged", SIP!$U:$U,"NO", SIP!$N:$N,">="&$B$1, SIP!$N:$N,"<"&$C$1+1 ) ) -> 0 | Q26: =SUM( COUNTIFS( SIP!$D:$D,"Incident", SIP!$C:$C,"SIP", SIP!$G:$G,4, SIP!$I:$I,"Closed", SIP!$AI:$AI,"YES", SIP!$U:$U,"No", SIP!$N:$N,">="&$B$1, SIP!$N:$N,"<"&$C$1+1 ), COUNTIFS( SIP!$D:$D,"Incident", SIP!$C:$C,"SIP", SIP!$G:$G,4, SIP!$I:$I,"Triaged", SIP!$AI:$AI,"YES", SIP!$U:$U,"No", SIP!$N:$N,">="&$B$1, SIP!$N:$N,"<"&$C$1+1 ) ) -> 0 | R26: =SUM( COUNTIFS( SIP!$D:$D,"Incident", SIP!$C:$C,"SIP", SIP!$G:$G,4, SIP!$I:$I,"Closed", SIP!$AJ:$AJ,"YES", SIP!$U:$U,"No", SIP!$N:$N,">="&$B$1, SIP!$N:$N,"<"&$C$1+1 ), COUNTIFS( SIP!$D:$D,"Incident", SIP!$C:$C,"SIP", SIP!$G:$G,4, SIP!$I:$I,"Triaged", SIP!$AJ:$AJ,"YES", SIP!$U:$U,"No", SIP!$N:$N,">="&$B$1, SIP!$N:$N,"<"&$C$1+1 ) ) -> 0 | S26: =SUM( COUNTIFS( SIP!$D:$D,"Incident", SIP!$C:$C,"SIP", SIP!$G:$G,4, SIP!$I:$I,"Closed", SIP!$AI:$AI,"NO", SIP!$AJ:$AJ,"NO", SIP!$U:$U,"No", SIP!$N:$N,">="&$B$1, SIP!$N:$N,"<"&$C$1+1 ), COUNTIFS( SIP!$D:$D,"Incident", SIP!$C:$C,"SIP", SIP!$G:$G,4, SIP!$I:$I,"Triaged", SIP!$AI:$AI,"NO", SIP!$AJ:$AJ,"NO", SIP!$U:$U,"No", SIP!$N:$N,">="&$B$1, SIP!$N:$N,"<"&$C$1+1 ) ) -> 0
B27: BA | C27: SharePoint | D27: =SUM( COUNTIFS( 'BA BackOffice'!$D:$D,"Incident", 'BA BackOffice'!$C:$C,"SharePoint", 'BA BackOffice'!$G:$G,1, 'BA BackOffice'!$I:$I,"Closed", 'BA BackOffice'!$U:$U,"NO", 'BA BackOffice'!$N:$N,">="&$B$1, 'BA BackOffice'!$N:$N,"<"&$C$1+1 ), COUNTIFS( 'BA BackOffice'!$D:$D,"Incident", 'BA BackOffice'!$C:$C,"SharePoint", 'BA BackOffice'!$G:$G,1, 'BA BackOffice'!$I:$I,"Triaged", 'BA BackOffice'!$U:$U,"NO", 'BA BackOffice'!$N:$N,">="&$B$1, 'BA BackOffice'!$N:$N,"<"&$C$1+1 ) ) -> 0 | E27: =SUM( COUNTIFS( 'BA BackOffice'!$D:$D,"Incident", 'BA BackOffice'!$C:$C,"SharePoint", 'BA BackOffice'!$G:$G,1, 'BA BackOffice'!$I:$I,"Closed", 'BA BackOffice'!$AI:$AI,"YES", 'BA BackOffice'!$U:$U,"No", 'BA BackOffice'!$N:$N,">="&$B$1, 'BA BackOffice'!$N:$N,"<"&$C$1+1 ), COUNTIFS( 'BA BackOffice'!$D:$D,"Incident", 'BA BackOffice'!$C:$C,"SharePoint", 'BA BackOffice'!$G:$G,1, 'BA BackOffice'!$I:$I,"Triaged", 'BA BackOffice'!$AI:$AI,"YES", 'BA BackOffice'!$U:$U,"No", 'BA BackOffice'!$N:$N,">="&$B$1, 'BA BackOffice'!$N:$N,"<"&$C$1+1 ) ) -> 0 | F27: =SUM( COUNTIFS( 'BA BackOffice'!$D:$D,"Incident", 'BA BackOffice'!$C:$C,"SharePoint", 'BA BackOffice'!$G:$G,1, 'BA BackOffice'!$I:$I,"Closed", 'BA BackOffice'!$AJ:$AJ,"YES", 'BA BackOffice'!$U:$U,"No", 'BA BackOffice'!$N:$N,">="&$B$1, 'BA BackOffice'!$N:$N,"<"&$C$1+1 ), COUNTIFS( 'BA BackOffice'!$D:$D,"Incident", 'BA BackOffice'!$C:$C,"SharePoint", 'BA BackOffice'!$G:$G,1, 'BA BackOffice'!$I:$I,"Triaged", 'BA BackOffice'!$AJ:$AJ,"YES", 'BA BackOffice'!$U:$U,"No", 'BA BackOffice'!$N:$N,">="&$B$1, 'BA BackOffice'!$N:$N,"<"&$C$1+1 ) ) -> 0 | G27: =SUM( COUNTIFS( 'BA BackOffice'!$D:$D,"Incident", 'BA BackOffice'!$C:$C,"SharePoint", 'BA BackOffice'!$G:$G,1, 'BA BackOffice'!$I:$I,"Closed", 'BA BackOffice'!$AI:$AI,"NO", 'BA BackOffice'!$AJ:$AJ,"NO", 'BA BackOffice'!$U:$U,"No", 'BA BackOffice'!$N:$N,">="&$B$1, 'BA BackOffice'!$N:$N,"<"&$C$1+1 ), COUNTIFS( 'BA BackOffice'!$D:$D,"Incident", 'BA BackOffice'!$C:$C,"SharePoint", 'BA BackOffice'!$G:$G,1, 'BA BackOffice'!$I:$I,"Triaged", 'BA BackOffice'!$AI:$AI,"NO", 'BA BackOffice'!$AJ:$AJ,"NO", 'BA BackOffice'!$U:$U,"No", 'BA BackOffice'!$N:$N,">="&$B$1, 'BA BackOffice'!$N:$N,"<"&$C$1+1 ) ) -> 0 | H27: =SUM( COUNTIFS( 'BA BackOffice'!$D:$D,"Incident", 'BA BackOffice'!$C:$C,"SharePoint", 'BA BackOffice'!$G:$G,2, 'BA BackOffice'!$I:$I,"Closed", 'BA BackOffice'!$U:$U,"NO", 'BA BackOffice'!$N:$N,">="&$B$1, 'BA BackOffice'!$N:$N,"<"&$C$1+1 ), COUNTIFS( 'BA BackOffice'!$D:$D,"Incident", 'BA BackOffice'!$C:$C,"SharePoint", 'BA BackOffice'!$G:$G,2, 'BA BackOffice'!$I:$I,"Triaged", 'BA BackOffice'!$U:$U,"NO", 'BA BackOffice'!$N:$N,">="&$B$1, 'BA BackOffice'!$N:$N,"<"&$C$1+1 ) ) -> 0 | I27: =SUM( COUNTIFS( 'BA BackOffice'!$D:$D,"Incident", 'BA BackOffice'!$C:$C,"SharePoint", 'BA BackOffice'!$G:$G,2, 'BA BackOffice'!$I:$I,"Closed", 'BA BackOffice'!$AI:$AI,"YES", 'BA BackOffice'!$U:$U,"No", 'BA BackOffice'!$N:$N,">="&$B$1, 'BA BackOffice'!$N:$N,"<"&$C$1+1 ), COUNTIFS( 'BA BackOffice'!$D:$D,"Incident", 'BA BackOffice'!$C:$C,"SharePoint", 'BA BackOffice'!$G:$G,2, 'BA BackOffice'!$I:$I,"Triaged", 'BA BackOffice'!$AI:$AI,"YES", 'BA BackOffice'!$U:$U,"No", 'BA BackOffice'!$N:$N,">="&$B$1, 'BA BackOffice'!$N:$N,"<"&$C$1+1 ) ) -> 0 | J27: =SUM( COUNTIFS( 'BA BackOffice'!$D:$D,"Incident", 'BA BackOffice'!$C:$C,"SharePoint", 'BA BackOffice'!$G:$G,2, 'BA BackOffice'!$I:$I,"Closed", 'BA BackOffice'!$AJ:$AJ,"YES", 'BA BackOffice'!$U:$U,"No", 'BA BackOffice'!$N:$N,">="&$B$1, 'BA BackOffice'!$N:$N,"<"&$C$1+1 ), COUNTIFS( 'BA BackOffice'!$D:$D,"Incident", 'BA BackOffice'!$C:$C,"SharePoint", 'BA BackOffice'!$G:$G,2, 'BA BackOffice'!$I:$I,"Triaged", 'BA BackOffice'!$AJ:$AJ,"YES", 'BA BackOffice'!$U:$U,"No", 'BA BackOffice'!$N:$N,">="&$B$1, 'BA BackOffice'!$N:$N,"<"&$C$1+1 ) ) -> 0 | K27: =SUM( COUNTIFS( 'BA BackOffice'!$D:$D,"Incident", 'BA BackOffice'!$C:$C,"SharePoint", 'BA BackOffice'!$G:$G,2, 'BA BackOffice'!$I:$I,"Closed", 'BA BackOffice'!$AI:$AI,"NO", 'BA BackOffice'!$AJ:$AJ,"NO", 'BA BackOffice'!$U:$U,"No", 'BA BackOffice'!$N:$N,">="&$B$1, 'BA BackOffice'!$N:$N,"<"&$C$1+1 ), COUNTIFS( 'BA BackOffice'!$D:$D,"Incident", 'BA BackOffice'!$C:$C,"SharePoint", 'BA BackOffice'!$G:$G,2, 'BA BackOffice'!$I:$I,"Triaged", 'BA BackOffice'!$AI:$AI,"NO", 'BA BackOffice'!$AJ:$AJ,"NO", 'BA BackOffice'!$U:$U,"No", 'BA BackOffice'!$N:$N,">="&$B$1, 'BA BackOffice'!$N:$N,"<"&$C$1+1 ) ) -> 0 | L27: =SUM( COUNTIFS( 'BA BackOffice'!$D:$D,"Incident", 'BA BackOffice'!$C:$C,"SharePoint", 'BA BackOffice'!$G:$G,3, 'BA BackOffice'!$I:$I,"Closed", 'BA BackOffice'!$U:$U,"NO", 'BA BackOffice'!$N:$N,">="&$B$1, 'BA BackOffice'!$N:$N,"<"&$C$1+1 ), COUNTIFS( 'BA BackOffice'!$D:$D,"Incident", 'BA BackOffice'!$C:$C,"SharePoint", 'BA BackOffice'!$G:$G,3, 'BA BackOffice'!$I:$I,"Triaged", 'BA BackOffice'!$U:$U,"NO", 'BA BackOffice'!$N:$N,">="&$B$1, 'BA BackOffice'!$N:$N,"<"&$C$1+1 ) ) -> 1 | M27: =SUM( COUNTIFS( 'BA BackOffice'!$D:$D,"Incident", 'BA BackOffice'!$C:$C,"SharePoint", 'BA BackOffice'!$G:$G,3, 'BA BackOffice'!$I:$I,"Closed", 'BA BackOffice'!$AI:$AI,"YES", 'BA BackOffice'!$U:$U,"No", 'BA BackOffice'!$N:$N,">="&$B$1, 'BA BackOffice'!$N:$N,"<"&$C$1+1 ), COUNTIFS( 'BA BackOffice'!$D:$D,"Incident", 'BA BackOffice'!$C:$C,"SharePoint", 'BA BackOffice'!$G:$G,3, 'BA BackOffice'!$I:$I,"Triaged", 'BA BackOffice'!$AI:$AI,"YES", 'BA BackOffice'!$U:$U,"No", 'BA BackOffice'!$N:$N,">="&$B$1, 'BA BackOffice'!$N:$N,"<"&$C$1+1 ) ) -> 1 | N27: =SUM( COUNTIFS( 'BA BackOffice'!$D:$D,"Incident", 'BA BackOffice'!$C:$C,"SharePoint", 'BA BackOffice'!$G:$G,3, 'BA BackOffice'!$I:$I,"Closed", 'BA BackOffice'!$AJ:$AJ,"YES", 'BA BackOffice'!$U:$U,"No", 'BA BackOffice'!$N:$N,">="&$B$1, 'BA BackOffice'!$N:$N,"<"&$C$1+1 ), COUNTIFS( 'BA BackOffice'!$D:$D,"Incident", 'BA BackOffice'!$C:$C,"SharePoint", 'BA BackOffice'!$G:$G,3, 'BA BackOffice'!$I:$I,"Triaged", 'BA BackOffice'!$AJ:$AJ,"YES", 'BA BackOffice'!$U:$U,"No", 'BA BackOffice'!$N:$N,">="&$B$1, 'BA BackOffice'!$N:$N,"<"&$C$1+1 ) ) -> 1 | O27: =SUM( COUNTIFS( 'BA BackOffice'!$D:$D,"Incident", 'BA BackOffice'!$C:$C,"SharePoint", 'BA BackOffice'!$G:$G,3, 'BA BackOffice'!$I:$I,"Closed", 'BA BackOffice'!$AI:$AI,"NO", 'BA BackOffice'!$AJ:$AJ,"NO", 'BA BackOffice'!$U:$U,"No", 'BA BackOffice'!$N:$N,">="&$B$1, 'BA BackOffice'!$N:$N,"<"&$C$1+1 ), COUNTIFS( 'BA BackOffice'!$D:$D,"Incident", 'BA BackOffice'!$C:$C,"SharePoint", 'BA BackOffice'!$G:$G,3, 'BA BackOffice'!$I:$I,"Triaged", 'BA BackOffice'!$AI:$AI,"NO", 'BA BackOffice'!$AJ:$AJ,"NO", 'BA BackOffice'!$U:$U,"No", 'BA BackOffice'!$N:$N,">="&$B$1, 'BA BackOffice'!$N:$N,"<"&$C$1+1 ) ) -> 0 | P27: =SUM( COUNTIFS( 'BA BackOffice'!$D:$D,"Incident", 'BA BackOffice'!$C:$C,"SharePoint", 'BA BackOffice'!$G:$G,4, 'BA BackOffice'!$I:$I,"Closed", 'BA BackOffice'!$U:$U,"NO", 'BA BackOffice'!$N:$N,">="&$B$1, 'BA BackOffice'!$N:$N,"<"&$C$1+1 ), COUNTIFS( 'BA BackOffice'!$D:$D,"Incident", 'BA BackOffice'!$C:$C,"SharePoint", 'BA BackOffice'!$G:$G,4, 'BA BackOffice'!$I:$I,"Triaged", 'BA BackOffice'!$U:$U,"NO", 'BA BackOffice'!$N:$N,">="&$B$1, 'BA BackOffice'!$N:$N,"<"&$C$1+1 ) ) -> 6 | Q27: =SUM( COUNTIFS( 'BA BackOffice'!$D:$D,"Incident", 'BA BackOffice'!$C:$C,"SharePoint", 'BA BackOffice'!$G:$G,4, 'BA BackOffice'!$I:$I,"Closed", 'BA BackOffice'!$AI:$AI,"YES", 'BA BackOffice'!$U:$U,"No", 'BA BackOffice'!$N:$N,">="&$B$1, 'BA BackOffice'!$N:$N,"<"&$C$1+1 ), COUNTIFS( 'BA BackOffice'!$D:$D,"Incident", 'BA BackOffice'!$C:$C,"SharePoint", 'BA BackOffice'!$G:$G,4, 'BA BackOffice'!$I:$I,"Triaged", 'BA BackOffice'!$AI:$AI,"YES", 'BA BackOffice'!$U:$U,"No", 'BA BackOffice'!$N:$N,">="&$B$1, 'BA BackOffice'!$N:$N,"<"&$C$1+1 ) ) -> 6 | R27: =SUM( COUNTIFS( 'BA BackOffice'!$D:$D,"Incident", 'BA BackOffice'!$C:$C,"SharePoint", 'BA BackOffice'!$G:$G,4, 'BA BackOffice'!$I:$I,"Closed", 'BA BackOffice'!$AJ:$AJ,"YES", 'BA BackOffice'!$U:$U,"No", 'BA BackOffice'!$N:$N,">="&$B$1, 'BA BackOffice'!$N:$N,"<"&$C$1+1 ), COUNTIFS( 'BA BackOffice'!$D:$D,"Incident", 'BA BackOffice'!$C:$C,"SharePoint", 'BA BackOffice'!$G:$G,4, 'BA BackOffice'!$I:$I,"Triaged", 'BA BackOffice'!$AJ:$AJ,"YES", 'BA BackOffice'!$U:$U,"No", 'BA BackOffice'!$N:$N,">="&$B$1, 'BA BackOffice'!$N:$N,"<"&$C$1+1 ) ) -> 6 | S27: =SUM( COUNTIFS( 'BA BackOffice'!$D:$D,"Incident", 'BA BackOffice'!$C:$C,"SharePoint", 'BA BackOffice'!$G:$G,4, 'BA BackOffice'!$I:$I,"Closed", 'BA BackOffice'!$AI:$AI,"NO", 'BA BackOffice'!$AJ:$AJ,"NO", 'BA BackOffice'!$U:$U,"No", 'BA BackOffice'!$N:$N,">="&$B$1, 'BA BackOffice'!$N:$N,"<"&$C$1+1 ), COUNTIFS( 'BA BackOffice'!$D:$D,"Incident", 'BA BackOffice'!$C:$C,"SharePoint", 'BA BackOffice'!$G:$G,4, 'BA BackOffice'!$I:$I,"Triaged", 'BA BackOffice'!$AI:$AI,"NO", 'BA BackOffice'!$AJ:$AJ,"NO", 'BA BackOffice'!$U:$U,"No", 'BA BackOffice'!$N:$N,">="&$B$1, 'BA BackOffice'!$N:$N,"<"&$C$1+1 ) ) -> 0
B28: BA | C28: Apex | D28: =SUM( COUNTIFS( 'BA BackOffice'!$D:$D,"Incident", 'BA BackOffice'!$C:$C,"Apex", 'BA BackOffice'!$G:$G,1, 'BA BackOffice'!$I:$I,"Closed", 'BA BackOffice'!$U:$U,"NO", 'BA BackOffice'!$N:$N,">="&$B$1, 'BA BackOffice'!$N:$N,"<"&$C$1+1 ), COUNTIFS( 'BA BackOffice'!$D:$D,"Incident", 'BA BackOffice'!$C:$C,"Apex", 'BA BackOffice'!$G:$G,1, 'BA BackOffice'!$I:$I,"Triaged", 'BA BackOffice'!$U:$U,"NO", 'BA BackOffice'!$N:$N,">="&$B$1, 'BA BackOffice'!$N:$N,"<"&$C$1+1 ) ) -> 0 | E28: =SUM( COUNTIFS( 'BA BackOffice'!$D:$D,"Incident", 'BA BackOffice'!$C:$C,"Apex", 'BA BackOffice'!$G:$G,1, 'BA BackOffice'!$I:$I,"Closed", 'BA BackOffice'!$AI:$AI,"YES", 'BA BackOffice'!$U:$U,"No", 'BA BackOffice'!$N:$N,">="&$B$1, 'BA BackOffice'!$N:$N,"<"&$C$1+1 ), COUNTIFS( 'BA BackOffice'!$D:$D,"Incident", 'BA BackOffice'!$C:$C,"Apex", 'BA BackOffice'!$G:$G,1, 'BA BackOffice'!$I:$I,"Triaged", 'BA BackOffice'!$AI:$AI,"YES", 'BA BackOffice'!$U:$U,"No", 'BA BackOffice'!$N:$N,">="&$B$1, 'BA BackOffice'!$N:$N,"<"&$C$1+1 ) ) -> 0 | F28: =SUM( COUNTIFS( 'BA BackOffice'!$D:$D,"Incident", 'BA BackOffice'!$C:$C,"Apex", 'BA BackOffice'!$G:$G,1, 'BA BackOffice'!$I:$I,"Closed", 'BA BackOffice'!$AJ:$AJ,"YES", 'BA BackOffice'!$U:$U,"No", 'BA BackOffice'!$N:$N,">="&$B$1, 'BA BackOffice'!$N:$N,"<"&$C$1+1 ), COUNTIFS( 'BA BackOffice'!$D:$D,"Incident", 'BA BackOffice'!$C:$C,"Apex", 'BA BackOffice'!$G:$G,1, 'BA BackOffice'!$I:$I,"Triaged", 'BA BackOffice'!$AJ:$AJ,"YES", 'BA BackOffice'!$U:$U,"No", 'BA BackOffice'!$N:$N,">="&$B$1, 'BA BackOffice'!$N:$N,"<"&$C$1+1 ) ) -> 0 | G28: =SUM( COUNTIFS( 'BA BackOffice'!$D:$D,"Incident", 'BA BackOffice'!$C:$C,"Apex", 'BA BackOffice'!$G:$G,1, 'BA BackOffice'!$I:$I,"Closed", 'BA BackOffice'!$AI:$AI,"NO", 'BA BackOffice'!$AJ:$AJ,"NO", 'BA BackOffice'!$U:$U,"No", 'BA BackOffice'!$N:$N,">="&$B$1, 'BA BackOffice'!$N:$N,"<"&$C$1+1 ), COUNTIFS( 'BA BackOffice'!$D:$D,"Incident", 'BA BackOffice'!$C:$C,"Apex", 'BA BackOffice'!$G:$G,1, 'BA BackOffice'!$I:$I,"Triaged", 'BA BackOffice'!$AI:$AI,"NO", 'BA BackOffice'!$AJ:$AJ,"NO", 'BA BackOffice'!$U:$U,"No", 'BA BackOffice'!$N:$N,">="&$B$1, 'BA BackOffice'!$N:$N,"<"&$C$1+1 ) ) -> 0 | H28: =SUM( COUNTIFS( 'BA BackOffice'!$D:$D,"Incident", 'BA BackOffice'!$C:$C,"Apex", 'BA BackOffice'!$G:$G,2, 'BA BackOffice'!$I:$I,"Closed", 'BA BackOffice'!$U:$U,"NO", 'BA BackOffice'!$N:$N,">="&$B$1, 'BA BackOffice'!$N:$N,"<"&$C$1+1 ), COUNTIFS( 'BA BackOffice'!$D:$D,"Incident", 'BA BackOffice'!$C:$C,"Apex", 'BA BackOffice'!$G:$G,2, 'BA BackOffice'!$I:$I,"Triaged", 'BA BackOffice'!$U:$U,"NO", 'BA BackOffice'!$N:$N,">="&$B$1, 'BA BackOffice'!$N:$N,"<"&$C$1+1 ) ) -> 0 | I28: =SUM( COUNTIFS( 'BA BackOffice'!$D:$D,"Incident", 'BA BackOffice'!$C:$C,"Apex", 'BA BackOffice'!$G:$G,2, 'BA BackOffice'!$I:$I,"Closed", 'BA BackOffice'!$AI:$AI,"YES", 'BA BackOffice'!$U:$U,"No", 'BA BackOffice'!$N:$N,">="&$B$1, 'BA BackOffice'!$N:$N,"<"&$C$1+1 ), COUNTIFS( 'BA BackOffice'!$D:$D,"Incident", 'BA BackOffice'!$C:$C,"Apex", 'BA BackOffice'!$G:$G,2, 'BA BackOffice'!$I:$I,"Triaged", 'BA BackOffice'!$AI:$AI,"YES", 'BA BackOffice'!$U:$U,"No", 'BA BackOffice'!$N:$N,">="&$B$1, 'BA BackOffice'!$N:$N,"<"&$C$1+1 ) ) -> 0 | J28: =SUM( COUNTIFS( 'BA BackOffice'!$D:$D,"Incident", 'BA BackOffice'!$C:$C,"Apex", 'BA BackOffice'!$G:$G,2, 'BA BackOffice'!$I:$I,"Closed", 'BA BackOffice'!$AJ:$AJ,"YES", 'BA BackOffice'!$U:$U,"No", 'BA BackOffice'!$N:$N,">="&$B$1, 'BA BackOffice'!$N:$N,"<"&$C$1+1 ), COUNTIFS( 'BA BackOffice'!$D:$D,"Incident", 'BA BackOffice'!$C:$C,"Apex", 'BA BackOffice'!$G:$G,2, 'BA BackOffice'!$I:$I,"Triaged", 'BA BackOffice'!$AJ:$AJ,"YES", 'BA BackOffice'!$U:$U,"No", 'BA BackOffice'!$N:$N,">="&$B$1, 'BA BackOffice'!$N:$N,"<"&$C$1+1 ) ) -> 0 | K28: =SUM( COUNTIFS( 'BA BackOffice'!$D:$D,"Incident", 'BA BackOffice'!$C:$C,"Apex", 'BA BackOffice'!$G:$G,2, 'BA BackOffice'!$I:$I,"Closed", 'BA BackOffice'!$AI:$AI,"NO", 'BA BackOffice'!$AJ:$AJ,"NO", 'BA BackOffice'!$U:$U,"No", 'BA BackOffice'!$N:$N,">="&$B$1, 'BA BackOffice'!$N:$N,"<"&$C$1+1 ), COUNTIFS( 'BA BackOffice'!$D:$D,"Incident", 'BA BackOffice'!$C:$C,"Apex", 'BA BackOffice'!$G:$G,2, 'BA BackOffice'!$I:$I,"Triaged", 'BA BackOffice'!$AI:$AI,"NO", 'BA BackOffice'!$AJ:$AJ,"NO", 'BA BackOffice'!$U:$U,"No", 'BA BackOffice'!$N:$N,">="&$B$1, 'BA BackOffice'!$N:$N,"<"&$C$1+1 ) ) -> 0 | L28: =SUM( COUNTIFS( 'BA BackOffice'!$D:$D,"Incident", 'BA BackOffice'!$C:$C,"Apex", 'BA BackOffice'!$G:$G,3, 'BA BackOffice'!$I:$I,"Closed", 'BA BackOffice'!$U:$U,"NO", 'BA BackOffice'!$N:$N,">="&$B$1, 'BA BackOffice'!$N:$N,"<"&$C$1+1 ), COUNTIFS( 'BA BackOffice'!$D:$D,"Incident", 'BA BackOffice'!$C:$C,"Apex", 'BA BackOffice'!$G:$G,3, 'BA BackOffice'!$I:$I,"Triaged", 'BA BackOffice'!$U:$U,"NO", 'BA BackOffice'!$N:$N,">="&$B$1, 'BA BackOffice'!$N:$N,"<"&$C$1+1 ) ) -> 0 | M28: =SUM( COUNTIFS( 'BA BackOffice'!$D:$D,"Incident", 'BA BackOffice'!$C:$C,"Apex", 'BA BackOffice'!$G:$G,3, 'BA BackOffice'!$I:$I,"Closed", 'BA BackOffice'!$AI:$AI,"YES", 'BA BackOffice'!$U:$U,"No", 'BA BackOffice'!$N:$N,">="&$B$1, 'BA BackOffice'!$N:$N,"<"&$C$1+1 ), COUNTIFS( 'BA BackOffice'!$D:$D,"Incident", 'BA BackOffice'!$C:$C,"Apex", 'BA BackOffice'!$G:$G,3, 'BA BackOffice'!$I:$I,"Triaged", 'BA BackOffice'!$AI:$AI,"YES", 'BA BackOffice'!$U:$U,"No", 'BA BackOffice'!$N:$N,">="&$B$1, 'BA BackOffice'!$N:$N,"<"&$C$1+1 ) ) -> 0 | N28: =SUM( COUNTIFS( 'BA BackOffice'!$D:$D,"Incident", 'BA BackOffice'!$C:$C,"Apex", 'BA BackOffice'!$G:$G,3, 'BA BackOffice'!$I:$I,"Closed", 'BA BackOffice'!$AJ:$AJ,"YES", 'BA BackOffice'!$U:$U,"No", 'BA BackOffice'!$N:$N,">="&$B$1, 'BA BackOffice'!$N:$N,"<"&$C$1+1 ), COUNTIFS( 'BA BackOffice'!$D:$D,"Incident", 'BA BackOffice'!$C:$C,"Apex", 'BA BackOffice'!$G:$G,3, 'BA BackOffice'!$I:$I,"Triaged", 'BA BackOffice'!$AJ:$AJ,"YES", 'BA BackOffice'!$U:$U,"No", 'BA BackOffice'!$N:$N,">="&$B$1, 'BA BackOffice'!$N:$N,"<"&$C$1+1 ) ) -> 0 | O28: =SUM( COUNTIFS( 'BA BackOffice'!$D:$D,"Incident", 'BA BackOffice'!$C:$C,"Apex", 'BA BackOffice'!$G:$G,3, 'BA BackOffice'!$I:$I,"Closed", 'BA BackOffice'!$AI:$AI,"NO", 'BA BackOffice'!$AJ:$AJ,"NO", 'BA BackOffice'!$U:$U,"No", 'BA BackOffice'!$N:$N,">="&$B$1, 'BA BackOffice'!$N:$N,"<"&$C$1+1 ), COUNTIFS( 'BA BackOffice'!$D:$D,"Incident", 'BA BackOffice'!$C:$C,"Apex", 'BA BackOffice'!$G:$G,3, 'BA BackOffice'!$I:$I,"Triaged", 'BA BackOffice'!$AI:$AI,"NO", 'BA BackOffice'!$AJ:$AJ,"NO", 'BA BackOffice'!$U:$U,"No", 'BA BackOffice'!$N:$N,">="&$B$1, 'BA BackOffice'!$N:$N,"<"&$C$1+1 ) ) -> 0 | P28: =SUM( COUNTIFS( 'BA BackOffice'!$D:$D,"Incident", 'BA BackOffice'!$C:$C,"Apex", 'BA BackOffice'!$G:$G,4, 'BA BackOffice'!$I:$I,"Closed", 'BA BackOffice'!$U:$U,"NO", 'BA BackOffice'!$N:$N,">="&$B$1, 'BA BackOffice'!$N:$N,"<"&$C$1+1 ), COUNTIFS( 'BA BackOffice'!$D:$D,"Incident", 'BA BackOffice'!$C:$C,"Apex", 'BA BackOffice'!$G:$G,4, 'BA BackOffice'!$I:$I,"Triaged", 'BA BackOffice'!$U:$U,"NO", 'BA BackOffice'!$N:$N,">="&$B$1, 'BA BackOffice'!$N:$N,"<"&$C$1+1 ) ) -> 0 | Q28: =SUM( COUNTIFS( 'BA BackOffice'!$D:$D,"Incident", 'BA BackOffice'!$C:$C,"Apex", 'BA BackOffice'!$G:$G,4, 'BA BackOffice'!$I:$I,"Closed", 'BA BackOffice'!$AI:$AI,"YES", 'BA BackOffice'!$U:$U,"No", 'BA BackOffice'!$N:$N,">="&$B$1, 'BA BackOffice'!$N:$N,"<"&$C$1+1 ), COUNTIFS( 'BA BackOffice'!$D:$D,"Incident", 'BA BackOffice'!$C:$C,"Apex", 'BA BackOffice'!$G:$G,4, 'BA BackOffice'!$I:$I,"Triaged", 'BA BackOffice'!$AI:$AI,"YES", 'BA BackOffice'!$U:$U,"No", 'BA BackOffice'!$N:$N,">="&$B$1, 'BA BackOffice'!$N:$N,"<"&$C$1+1 ) ) -> 0 | R28: =SUM( COUNTIFS( 'BA BackOffice'!$D:$D,"Incident", 'BA BackOffice'!$C:$C,"Apex", 'BA BackOffice'!$G:$G,4, 'BA BackOffice'!$I:$I,"Closed", 'BA BackOffice'!$AJ:$AJ,"YES", 'BA BackOffice'!$U:$U,"No", 'BA BackOffice'!$N:$N,">="&$B$1, 'BA BackOffice'!$N:$N,"<"&$C$1+1 ), COUNTIFS( 'BA BackOffice'!$D:$D,"Incident", 'BA BackOffice'!$C:$C,"Apex", 'BA BackOffice'!$G:$G,4, 'BA BackOffice'!$I:$I,"Triaged", 'BA BackOffice'!$AJ:$AJ,"YES", 'BA BackOffice'!$U:$U,"No", 'BA BackOffice'!$N:$N,">="&$B$1, 'BA BackOffice'!$N:$N,"<"&$C$1+1 ) ) -> 0 | S28: =SUM( COUNTIFS( 'BA BackOffice'!$D:$D,"Incident", 'BA BackOffice'!$C:$C,"Apex", 'BA BackOffice'!$G:$G,4, 'BA BackOffice'!$I:$I,"Closed", 'BA BackOffice'!$AI:$AI,"NO", 'BA BackOffice'!$AJ:$AJ,"NO", 'BA BackOffice'!$U:$U,"No", 'BA BackOffice'!$N:$N,">="&$B$1, 'BA BackOffice'!$N:$N,"<"&$C$1+1 ), COUNTIFS( 'BA BackOffice'!$D:$D,"Incident", 'BA BackOffice'!$C:$C,"Apex", 'BA BackOffice'!$G:$G,4, 'BA BackOffice'!$I:$I,"Triaged", 'BA BackOffice'!$AI:$AI,"NO", 'BA BackOffice'!$AJ:$AJ,"NO", 'BA BackOffice'!$U:$U,"No", 'BA BackOffice'!$N:$N,">="&$B$1, 'BA BackOffice'!$N:$N,"<"&$C$1+1 ) ) -> 0
B29: BA | C29: TechTools | D29: =SUM( COUNTIFS( 'BA BackOffice'!$D:$D,"Incident", 'BA BackOffice'!$C:$C,"TechTools", 'BA BackOffice'!$G:$G,1, 'BA BackOffice'!$I:$I,"Closed", 'BA BackOffice'!$U:$U,"NO", 'BA BackOffice'!$N:$N,">="&$B$1, 'BA BackOffice'!$N:$N,"<"&$C$1+1 ), COUNTIFS( 'BA BackOffice'!$D:$D,"Incident", 'BA BackOffice'!$C:$C,"TechTools", 'BA BackOffice'!$G:$G,1, 'BA BackOffice'!$I:$I,"Triaged", 'BA BackOffice'!$U:$U,"NO", 'BA BackOffice'!$N:$N,">="&$B$1, 'BA BackOffice'!$N:$N,"<"&$C$1+1 ) ) -> 0 | E29: =SUM( COUNTIFS( 'BA BackOffice'!$D:$D,"Incident", 'BA BackOffice'!$C:$C,"TechTools", 'BA BackOffice'!$G:$G,1, 'BA BackOffice'!$I:$I,"Closed", 'BA BackOffice'!$AI:$AI,"YES", 'BA BackOffice'!$U:$U,"No", 'BA BackOffice'!$N:$N,">="&$B$1, 'BA BackOffice'!$N:$N,"<"&$C$1+1 ), COUNTIFS( 'BA BackOffice'!$D:$D,"Incident", 'BA BackOffice'!$C:$C,"TechTools", 'BA BackOffice'!$G:$G,1, 'BA BackOffice'!$I:$I,"Triaged", 'BA BackOffice'!$AI:$AI,"YES", 'BA BackOffice'!$U:$U,"No", 'BA BackOffice'!$N:$N,">="&$B$1, 'BA BackOffice'!$N:$N,"<"&$C$1+1 ) ) -> 0 | F29: =SUM( COUNTIFS( 'BA BackOffice'!$D:$D,"Incident", 'BA BackOffice'!$C:$C,"TechTools", 'BA BackOffice'!$G:$G,1, 'BA BackOffice'!$I:$I,"Closed", 'BA BackOffice'!$AJ:$AJ,"YES", 'BA BackOffice'!$U:$U,"No", 'BA BackOffice'!$N:$N,">="&$B$1, 'BA BackOffice'!$N:$N,"<"&$C$1+1 ), COUNTIFS( 'BA BackOffice'!$D:$D,"Incident", 'BA BackOffice'!$C:$C,"TechTools", 'BA BackOffice'!$G:$G,1, 'BA BackOffice'!$I:$I,"Triaged", 'BA BackOffice'!$AJ:$AJ,"YES", 'BA BackOffice'!$U:$U,"No", 'BA BackOffice'!$N:$N,">="&$B$1, 'BA BackOffice'!$N:$N,"<"&$C$1+1 ) ) -> 0 | G29: =SUM( COUNTIFS( 'BA BackOffice'!$D:$D,"Incident", 'BA BackOffice'!$C:$C,"TechTools", 'BA BackOffice'!$G:$G,1, 'BA BackOffice'!$I:$I,"Closed", 'BA BackOffice'!$AI:$AI,"NO", 'BA BackOffice'!$AJ:$AJ,"NO", 'BA BackOffice'!$U:$U,"No", 'BA BackOffice'!$N:$N,">="&$B$1, 'BA BackOffice'!$N:$N,"<"&$C$1+1 ), COUNTIFS( 'BA BackOffice'!$D:$D,"Incident", 'BA BackOffice'!$C:$C,"TechTools", 'BA BackOffice'!$G:$G,1, 'BA BackOffice'!$I:$I,"Triaged", 'BA BackOffice'!$AI:$AI,"NO", 'BA BackOffice'!$AJ:$AJ,"NO", 'BA BackOffice'!$U:$U,"No", 'BA BackOffice'!$N:$N,">="&$B$1, 'BA BackOffice'!$N:$N,"<"&$C$1+1 ) ) -> 0 | H29: =SUM( COUNTIFS( 'BA BackOffice'!$D:$D,"Incident", 'BA BackOffice'!$C:$C,"TechTools", 'BA BackOffice'!$G:$G,2, 'BA BackOffice'!$I:$I,"Closed", 'BA BackOffice'!$U:$U,"NO", 'BA BackOffice'!$N:$N,">="&$B$1, 'BA BackOffice'!$N:$N,"<"&$C$1+1 ), COUNTIFS( 'BA BackOffice'!$D:$D,"Incident", 'BA BackOffice'!$C:$C,"TechTools", 'BA BackOffice'!$G:$G,2, 'BA BackOffice'!$I:$I,"Triaged", 'BA BackOffice'!$U:$U,"NO", 'BA BackOffice'!$N:$N,">="&$B$1, 'BA BackOffice'!$N:$N,"<"&$C$1+1 ) ) -> 0 | I29: =SUM( COUNTIFS( 'BA BackOffice'!$D:$D,"Incident", 'BA BackOffice'!$C:$C,"TechTools", 'BA BackOffice'!$G:$G,2, 'BA BackOffice'!$I:$I,"Closed", 'BA BackOffice'!$AI:$AI,"YES", 'BA BackOffice'!$U:$U,"No", 'BA BackOffice'!$N:$N,">="&$B$1, 'BA BackOffice'!$N:$N,"<"&$C$1+1 ), COUNTIFS( 'BA BackOffice'!$D:$D,"Incident", 'BA BackOffice'!$C:$C,"TechTools", 'BA BackOffice'!$G:$G,2, 'BA BackOffice'!$I:$I,"Triaged", 'BA BackOffice'!$AI:$AI,"YES", 'BA BackOffice'!$U:$U,"No", 'BA BackOffice'!$N:$N,">="&$B$1, 'BA BackOffice'!$N:$N,"<"&$C$1+1 ) ) -> 0 | J29: =SUM( COUNTIFS( 'BA BackOffice'!$D:$D,"Incident", 'BA BackOffice'!$C:$C,"TechTools", 'BA BackOffice'!$G:$G,2, 'BA BackOffice'!$I:$I,"Closed", 'BA BackOffice'!$AJ:$AJ,"YES", 'BA BackOffice'!$U:$U,"No", 'BA BackOffice'!$N:$N,">="&$B$1, 'BA BackOffice'!$N:$N,"<"&$C$1+1 ), COUNTIFS( 'BA BackOffice'!$D:$D,"Incident", 'BA BackOffice'!$C:$C,"TechTools", 'BA BackOffice'!$G:$G,2, 'BA BackOffice'!$I:$I,"Triaged", 'BA BackOffice'!$AJ:$AJ,"YES", 'BA BackOffice'!$U:$U,"No", 'BA BackOffice'!$N:$N,">="&$B$1, 'BA BackOffice'!$N:$N,"<"&$C$1+1 ) ) -> 0 | K29: =SUM( COUNTIFS( 'BA BackOffice'!$D:$D,"Incident", 'BA BackOffice'!$C:$C,"TechTools", 'BA BackOffice'!$G:$G,2, 'BA BackOffice'!$I:$I,"Closed", 'BA BackOffice'!$AI:$AI,"NO", 'BA BackOffice'!$AJ:$AJ,"NO", 'BA BackOffice'!$U:$U,"No", 'BA BackOffice'!$N:$N,">="&$B$1, 'BA BackOffice'!$N:$N,"<"&$C$1+1 ), COUNTIFS( 'BA BackOffice'!$D:$D,"Incident", 'BA BackOffice'!$C:$C,"TechTools", 'BA BackOffice'!$G:$G,2, 'BA BackOffice'!$I:$I,"Triaged", 'BA BackOffice'!$AI:$AI,"NO", 'BA BackOffice'!$AJ:$AJ,"NO", 'BA BackOffice'!$U:$U,"No", 'BA BackOffice'!$N:$N,">="&$B$1, 'BA BackOffice'!$N:$N,"<"&$C$1+1 ) ) -> 0 | L29: =SUM( COUNTIFS( 'BA BackOffice'!$D:$D,"Incident", 'BA BackOffice'!$C:$C,"TechTools", 'BA BackOffice'!$G:$G,3, 'BA BackOffice'!$I:$I,"Closed", 'BA BackOffice'!$U:$U,"NO", 'BA BackOffice'!$N:$N,">="&$B$1, 'BA BackOffice'!$N:$N,"<"&$C$1+1 ), COUNTIFS( 'BA BackOffice'!$D:$D,"Incident", 'BA BackOffice'!$C:$C,"TechTools", 'BA BackOffice'!$G:$G,3, 'BA BackOffice'!$I:$I,"Triaged", 'BA BackOffice'!$U:$U,"NO", 'BA BackOffice'!$N:$N,">="&$B$1, 'BA BackOffice'!$N:$N,"<"&$C$1+1 ) ) -> 8 | M29: =SUM( COUNTIFS( 'BA BackOffice'!$D:$D,"Incident", 'BA BackOffice'!$C:$C,"TechTools", 'BA BackOffice'!$G:$G,3, 'BA BackOffice'!$I:$I,"Closed", 'BA BackOffice'!$AI:$AI,"YES", 'BA BackOffice'!$U:$U,"No", 'BA BackOffice'!$N:$N,">="&$B$1, 'BA BackOffice'!$N:$N,"<"&$C$1+1 ), COUNTIFS( 'BA BackOffice'!$D:$D,"Incident", 'BA BackOffice'!$C:$C,"TechTools", 'BA BackOffice'!$G:$G,3, 'BA BackOffice'!$I:$I,"Triaged", 'BA BackOffice'!$AI:$AI,"YES", 'BA BackOffice'!$U:$U,"No", 'BA BackOffice'!$N:$N,">="&$B$1, 'BA BackOffice'!$N:$N,"<"&$C$1+1 ) ) -> 5 | N29: =SUM( COUNTIFS( 'BA BackOffice'!$D:$D,"Incident", 'BA BackOffice'!$C:$C,"TechTools", 'BA BackOffice'!$G:$G,3, 'BA BackOffice'!$I:$I,"Closed", 'BA BackOffice'!$AJ:$AJ,"YES", 'BA BackOffice'!$U:$U,"No", 'BA BackOffice'!$N:$N,">="&$B$1, 'BA BackOffice'!$N:$N,"<"&$C$1+1 ), COUNTIFS( 'BA BackOffice'!$D:$D,"Incident", 'BA BackOffice'!$C:$C,"TechTools", 'BA BackOffice'!$G:$G,3, 'BA BackOffice'!$I:$I,"Triaged", 'BA BackOffice'!$AJ:$AJ,"YES", 'BA BackOffice'!$U:$U,"No", 'BA BackOffice'!$N:$N,">="&$B$1, 'BA BackOffice'!$N:$N,"<"&$C$1+1 ) ) -> 6 | O29: =SUM( COUNTIFS( 'BA BackOffice'!$D:$D,"Incident", 'BA BackOffice'!$C:$C,"TechTools", 'BA BackOffice'!$G:$G,3, 'BA BackOffice'!$I:$I,"Closed", 'BA BackOffice'!$AI:$AI,"NO", 'BA BackOffice'!$AJ:$AJ,"NO", 'BA BackOffice'!$U:$U,"No", 'BA BackOffice'!$N:$N,">="&$B$1, 'BA BackOffice'!$N:$N,"<"&$C$1+1 ), COUNTIFS( 'BA BackOffice'!$D:$D,"Incident", 'BA BackOffice'!$C:$C,"TechTools", 'BA BackOffice'!$G:$G,3, 'BA BackOffice'!$I:$I,"Triaged", 'BA BackOffice'!$AI:$AI,"NO", 'BA BackOffice'!$AJ:$AJ,"NO", 'BA BackOffice'!$U:$U,"No", 'BA BackOffice'!$N:$N,">="&$B$1, 'BA BackOffice'!$N:$N,"<"&$C$1+1 ) ) -> 2 | P29: =SUM( COUNTIFS( 'BA BackOffice'!$D:$D,"Incident", 'BA BackOffice'!$C:$C,"TechTools", 'BA BackOffice'!$G:$G,4, 'BA BackOffice'!$I:$I,"Closed", 'BA BackOffice'!$U:$U,"NO", 'BA BackOffice'!$N:$N,">="&$B$1, 'BA BackOffice'!$N:$N,"<"&$C$1+1 ), COUNTIFS( 'BA BackOffice'!$D:$D,"Incident", 'BA BackOffice'!$C:$C,"TechTools", 'BA BackOffice'!$G:$G,4, 'BA BackOffice'!$I:$I,"Triaged", 'BA BackOffice'!$U:$U,"NO", 'BA BackOffice'!$N:$N,">="&$B$1, 'BA BackOffice'!$N:$N,"<"&$C$1+1 ) ) -> 7 | Q29: =SUM( COUNTIFS( 'BA BackOffice'!$D:$D,"Incident", 'BA BackOffice'!$C:$C,"TechTools", 'BA BackOffice'!$G:$G,4, 'BA BackOffice'!$I:$I,"Closed", 'BA BackOffice'!$AI:$AI,"YES", 'BA BackOffice'!$U:$U,"No", 'BA BackOffice'!$N:$N,">="&$B$1, 'BA BackOffice'!$N:$N,"<"&$C$1+1 ), COUNTIFS( 'BA BackOffice'!$D:$D,"Incident", 'BA BackOffice'!$C:$C,"TechTools", 'BA BackOffice'!$G:$G,4, 'BA BackOffice'!$I:$I,"Triaged", 'BA BackOffice'!$AI:$AI,"YES", 'BA BackOffice'!$U:$U,"No", 'BA BackOffice'!$N:$N,">="&$B$1, 'BA BackOffice'!$N:$N,"<"&$C$1+1 ) ) -> 7 | R29: =SUM( COUNTIFS( 'BA BackOffice'!$D:$D,"Incident", 'BA BackOffice'!$C:$C,"TechTools", 'BA BackOffice'!$G:$G,4, 'BA BackOffice'!$I:$I,"Closed", 'BA BackOffice'!$AJ:$AJ,"YES", 'BA BackOffice'!$U:$U,"No", 'BA BackOffice'!$N:$N,">="&$B$1, 'BA BackOffice'!$N:$N,"<"&$C$1+1 ), COUNTIFS( 'BA BackOffice'!$D:$D,"Incident", 'BA BackOffice'!$C:$C,"TechTools", 'BA BackOffice'!$G:$G,4, 'BA BackOffice'!$I:$I,"Triaged", 'BA BackOffice'!$AJ:$AJ,"YES", 'BA BackOffice'!$U:$U,"No", 'BA BackOffice'!$N:$N,">="&$B$1, 'BA BackOffice'!$N:$N,"<"&$C$1+1 ) ) -> 7 | S29: =SUM( COUNTIFS( 'BA BackOffice'!$D:$D,"Incident", 'BA BackOffice'!$C:$C,"TechTools", 'BA BackOffice'!$G:$G,4, 'BA BackOffice'!$I:$I,"Closed", 'BA BackOffice'!$AI:$AI,"NO", 'BA BackOffice'!$AJ:$AJ,"NO", 'BA BackOffice'!$U:$U,"No", 'BA BackOffice'!$N:$N,">="&$B$1, 'BA BackOffice'!$N:$N,"<"&$C$1+1 ), COUNTIFS( 'BA BackOffice'!$D:$D,"Incident", 'BA BackOffice'!$C:$C,"TechTools", 'BA BackOffice'!$G:$G,4, 'BA BackOffice'!$I:$I,"Triaged", 'BA BackOffice'!$AI:$AI,"NO", 'BA BackOffice'!$AJ:$AJ,"NO", 'BA BackOffice'!$U:$U,"No", 'BA BackOffice'!$N:$N,">="&$B$1, 'BA BackOffice'!$N:$N,"<"&$C$1+1 ) ) -> 0
B30: BA | C30: AO | D30: =SUM( COUNTIFS( 'BA AO'!$D:$D,"Incident", 'BA AO'!$G:$G,1, 'BA AO'!$I:$I,"Closed", 'BA AO'!$U:$U,"NO", 'BA AO'!$N:$N,">="&$B$1, 'BA AO'!$N:$N,"<"&$C$1+1 ), COUNTIFS( 'BA AO'!$D:$D,"Incident", 'BA AO'!$G:$G,1, 'BA AO'!$I:$I,"Triaged", 'BA AO'!$U:$U,"NO", 'BA AO'!$N:$N,">="&$B$1, 'BA AO'!$N:$N,"<"&$C$1+1 ) ) -> 0 | E30: =SUM( COUNTIFS( 'BA AO'!$D:$D,"Incident", 'BA AO'!$G:$G,1, 'BA AO'!$I:$I,"Closed", 'BA AO'!$AI:$AI,"YES", 'BA AO'!$U:$U,"No", 'BA AO'!$N:$N,">="&$B$1, 'BA AO'!$N:$N,"<"&$C$1+1 ), COUNTIFS( 'BA AO'!$D:$D,"Incident", 'BA AO'!$G:$G,1, 'BA AO'!$I:$I,"Triaged", 'BA AO'!$AI:$AI,"YES", 'BA AO'!$U:$U,"No", 'BA AO'!$N:$N,">="&$B$1, 'BA AO'!$N:$N,"<"&$C$1+1 ) ) -> 0 | F30: =SUM( COUNTIFS( 'BA AO'!$D:$D,"Incident", 'BA AO'!$G:$G,1, 'BA AO'!$I:$I,"Closed", 'BA AO'!$AJ:$AJ,"YES", 'BA AO'!$U:$U,"No", 'BA AO'!$N:$N,">="&$B$1, 'BA AO'!$N:$N,"<"&$C$1+1 ), COUNTIFS( 'BA AO'!$D:$D,"Incident", 'BA AO'!$G:$G,1, 'BA AO'!$I:$I,"Triaged", 'BA AO'!$AJ:$AJ,"YES", 'BA AO'!$U:$U,"No", 'BA AO'!$N:$N,">="&$B$1, 'BA AO'!$N:$N,"<"&$C$1+1 ) ) -> 0 | G30: =SUM( COUNTIFS( 'BA AO'!$D:$D,"Incident", 'BA AO'!$G:$G,1, 'BA AO'!$I:$I,"Closed", 'BA AO'!$AI:$AI,"NO", 'BA AO'!$AJ:$AJ,"NO", 'BA AO'!$U:$U,"No", 'BA AO'!$N:$N,">="&$B$1, 'BA AO'!$N:$N,"<"&$C$1+1 ), COUNTIFS( 'BA AO'!$D:$D,"Incident", 'BA AO'!$G:$G,1, 'BA AO'!$I:$I,"Triaged", 'BA AO'!$AI:$AI,"NO", 'BA AO'!$AJ:$AJ,"NO", 'BA AO'!$U:$U,"No", 'BA AO'!$N:$N,">="&$B$1, 'BA AO'!$N:$N,"<"&$C$1+1 ) ) -> 0 | H30: =SUM( COUNTIFS( 'BA AO'!$D:$D,"Incident", 'BA AO'!$G:$G,2, 'BA AO'!$I:$I,"Closed", 'BA AO'!$U:$U,"NO", 'BA AO'!$N:$N,">="&$B$1, 'BA AO'!$N:$N,"<"&$C$1+1 ), COUNTIFS( 'BA AO'!$D:$D,"Incident", 'BA AO'!$G:$G,2, 'BA AO'!$I:$I,"Triaged", 'BA AO'!$U:$U,"NO", 'BA AO'!$N:$N,">="&$B$1, 'BA AO'!$N:$N,"<"&$C$1+1 ) ) -> 0 | I30: =SUM( COUNTIFS( 'BA AO'!$D:$D,"Incident", 'BA AO'!$G:$G,2, 'BA AO'!$I:$I,"Closed", 'BA AO'!$AI:$AI,"YES", 'BA AO'!$U:$U,"No", 'BA AO'!$N:$N,">="&$B$1, 'BA AO'!$N:$N,"<"&$C$1+1 ), COUNTIFS( 'BA AO'!$D:$D,"Incident", 'BA AO'!$G:$G,2, 'BA AO'!$I:$I,"Triaged", 'BA AO'!$AI:$AI,"YES", 'BA AO'!$U:$U,"No", 'BA AO'!$N:$N,">="&$B$1, 'BA AO'!$N:$N,"<"&$C$1+1 ) ) -> 0 | J30: =SUM( COUNTIFS( 'BA AO'!$D:$D,"Incident", 'BA AO'!$G:$G,2, 'BA AO'!$I:$I,"Closed", 'BA AO'!$AJ:$AJ,"YES", 'BA AO'!$U:$U,"No", 'BA AO'!$N:$N,">="&$B$1, 'BA AO'!$N:$N,"<"&$C$1+1 ), COUNTIFS( 'BA AO'!$D:$D,"Incident", 'BA AO'!$G:$G,2, 'BA AO'!$I:$I,"Triaged", 'BA AO'!$AJ:$AJ,"YES", 'BA AO'!$U:$U,"No", 'BA AO'!$N:$N,">="&$B$1, 'BA AO'!$N:$N,"<"&$C$1+1 ) ) -> 0 | K30: =SUM( COUNTIFS( 'BA AO'!$D:$D,"Incident", 'BA AO'!$G:$G,2, 'BA AO'!$I:$I,"Closed", 'BA AO'!$AI:$AI,"NO", 'BA AO'!$AJ:$AJ,"NO", 'BA AO'!$U:$U,"No", 'BA AO'!$N:$N,">="&$B$1, 'BA AO'!$N:$N,"<"&$C$1+1 ), COUNTIFS( 'BA AO'!$D:$D,"Incident", 'BA AO'!$G:$G,2, 'BA AO'!$I:$I,"Triaged", 'BA AO'!$AI:$AI,"NO", 'BA AO'!$AJ:$AJ,"NO", 'BA AO'!$U:$U,"No", 'BA AO'!$N:$N,">="&$B$1, 'BA AO'!$N:$N,"<"&$C$1+1 ) ) -> 0 | L30: =SUM( COUNTIFS( 'BA AO'!$D:$D,"Incident", 'BA AO'!$G:$G,3, 'BA AO'!$I:$I,"Closed", 'BA AO'!$U:$U,"NO", 'BA AO'!$N:$N,">="&$B$1, 'BA AO'!$N:$N,"<"&$C$1+1 ), COUNTIFS( 'BA AO'!$D:$D,"Incident", 'BA AO'!$G:$G,3, 'BA AO'!$I:$I,"Triaged", 'BA AO'!$U:$U,"NO", 'BA AO'!$N:$N,">="&$B$1, 'BA AO'!$N:$N,"<"&$C$1+1 ) ) -> 2 | M30: =SUM( COUNTIFS( 'BA AO'!$D:$D,"Incident", 'BA AO'!$G:$G,3, 'BA AO'!$I:$I,"Closed", 'BA AO'!$AI:$AI,"YES", 'BA AO'!$U:$U,"No", 'BA AO'!$N:$N,">="&$B$1, 'BA AO'!$N:$N,"<"&$C$1+1 ), COUNTIFS( 'BA AO'!$D:$D,"Incident", 'BA AO'!$G:$G,3, 'BA AO'!$I:$I,"Triaged", 'BA AO'!$AI:$AI,"YES", 'BA AO'!$U:$U,"No", 'BA AO'!$N:$N,">="&$B$1, 'BA AO'!$N:$N,"<"&$C$1+1 ) ) -> 0 | N30: =SUM( COUNTIFS( 'BA AO'!$D:$D,"Incident", 'BA AO'!$G:$G,3, 'BA AO'!$I:$I,"Closed", 'BA AO'!$AJ:$AJ,"YES", 'BA AO'!$U:$U,"No", 'BA AO'!$N:$N,">="&$B$1, 'BA AO'!$N:$N,"<"&$C$1+1 ), COUNTIFS( 'BA AO'!$D:$D,"Incident", 'BA AO'!$G:$G,3, 'BA AO'!$I:$I,"Triaged", 'BA AO'!$AJ:$AJ,"YES", 'BA AO'!$U:$U,"No", 'BA AO'!$N:$N,">="&$B$1, 'BA AO'!$N:$N,"<"&$C$1+1 ) ) -> 0 | O30: =SUM( COUNTIFS( 'BA AO'!$D:$D,"Incident", 'BA AO'!$G:$G,3, 'BA AO'!$I:$I,"Closed", 'BA AO'!$AI:$AI,"NO", 'BA AO'!$AJ:$AJ,"NO", 'BA AO'!$U:$U,"No", 'BA AO'!$N:$N,">="&$B$1, 'BA AO'!$N:$N,"<"&$C$1+1 ), COUNTIFS( 'BA AO'!$D:$D,"Incident", 'BA AO'!$G:$G,3, 'BA AO'!$I:$I,"Triaged", 'BA AO'!$AI:$AI,"NO", 'BA AO'!$AJ:$AJ,"NO", 'BA AO'!$U:$U,"No", 'BA AO'!$N:$N,">="&$B$1, 'BA AO'!$N:$N,"<"&$C$1+1 ) ) -> 2 | P30: =SUM( COUNTIFS( 'BA AO'!$D:$D,"Incident", 'BA AO'!$G:$G,4, 'BA AO'!$I:$I,"Closed", 'BA AO'!$U:$U,"NO", 'BA AO'!$N:$N,">="&$B$1, 'BA AO'!$N:$N,"<"&$C$1+1 ), COUNTIFS( 'BA AO'!$D:$D,"Incident", 'BA AO'!$G:$G,4, 'BA AO'!$I:$I,"Triaged", 'BA AO'!$U:$U,"NO", 'BA AO'!$N:$N,">="&$B$1, 'BA AO'!$N:$N,"<"&$C$1+1 ) ) -> 3 | Q30: =SUM( COUNTIFS( 'BA AO'!$D:$D,"Incident", 'BA AO'!$G:$G,4, 'BA AO'!$I:$I,"Closed", 'BA AO'!$AI:$AI,"YES", 'BA AO'!$U:$U,"No", 'BA AO'!$N:$N,">="&$B$1, 'BA AO'!$N:$N,"<"&$C$1+1 ), COUNTIFS( 'BA AO'!$D:$D,"Incident", 'BA AO'!$G:$G,4, 'BA AO'!$I:$I,"Triaged", 'BA AO'!$AI:$AI,"YES", 'BA AO'!$U:$U,"No", 'BA AO'!$N:$N,">="&$B$1, 'BA AO'!$N:$N,"<"&$C$1+1 ) ) -> 2 | R30: =SUM( COUNTIFS( 'BA AO'!$D:$D,"Incident", 'BA AO'!$G:$G,4, 'BA AO'!$I:$I,"Closed", 'BA AO'!$AJ:$AJ,"YES", 'BA AO'!$U:$U,"No", 'BA AO'!$N:$N,">="&$B$1, 'BA AO'!$N:$N,"<"&$C$1+1 ), COUNTIFS( 'BA AO'!$D:$D,"Incident", 'BA AO'!$G:$G,4, 'BA AO'!$I:$I,"Triaged", 'BA AO'!$AJ:$AJ,"YES", 'BA AO'!$U:$U,"No", 'BA AO'!$N:$N,">="&$B$1, 'BA AO'!$N:$N,"<"&$C$1+1 ) ) -> 2 | S30: =SUM( COUNTIFS( 'BA AO'!$D:$D,"Incident", 'BA AO'!$G:$G,4, 'BA AO'!$I:$I,"Closed", 'BA AO'!$AI:$AI,"NO", 'BA AO'!$AJ:$AJ,"NO", 'BA AO'!$U:$U,"No", 'BA AO'!$N:$N,">="&$B$1, 'BA AO'!$N:$N,"<"&$C$1+1 ), COUNTIFS( 'BA AO'!$D:$D,"Incident", 'BA AO'!$G:$G,4, 'BA AO'!$I:$I,"Triaged", 'BA AO'!$AI:$AI,"NO", 'BA AO'!$AJ:$AJ,"NO", 'BA AO'!$U:$U,"No", 'BA AO'!$N:$N,">="&$B$1, 'BA AO'!$N:$N,"<"&$C$1+1 ) ) -> 1
B31: BA | C31: Mobile | D31: =SUM( COUNTIFS( 'BA Mobile'!$D:$D,"Incident", 'BA Mobile'!$G:$G,1, 'BA Mobile'!$I:$I,"Closed", 'BA Mobile'!$U:$U,"NO", 'BA Mobile'!$N:$N,">="&$B$1, 'BA Mobile'!$N:$N,"<"&$C$1+1 ), COUNTIFS( 'BA Mobile'!$D:$D,"Incident", 'BA Mobile'!$G:$G,1, 'BA Mobile'!$I:$I,"Triaged", 'BA Mobile'!$U:$U,"NO", 'BA Mobile'!$N:$N,">="&$B$1, 'BA Mobile'!$N:$N,"<"&$C$1+1 ) ) -> 0 | E31: =SUM( COUNTIFS( 'BA Mobile'!$D:$D,"Incident", 'BA Mobile'!$G:$G,1, 'BA Mobile'!$I:$I,"Closed", 'BA Mobile'!$AI:$AI,"YES", 'BA Mobile'!$U:$U,"No", 'BA Mobile'!$N:$N,">="&$B$1, 'BA Mobile'!$N:$N,"<"&$C$1+1 ), COUNTIFS( 'BA Mobile'!$D:$D,"Incident", 'BA Mobile'!$G:$G,1, 'BA Mobile'!$I:$I,"Triaged", 'BA Mobile'!$AI:$AI,"YES", 'BA Mobile'!$U:$U,"No", 'BA Mobile'!$N:$N,">="&$B$1, 'BA Mobile'!$N:$N,"<"&$C$1+1 ) ) -> 0 | F31: =SUM( COUNTIFS( 'BA Mobile'!$D:$D,"Incident", 'BA Mobile'!$G:$G,1, 'BA Mobile'!$I:$I,"Closed", 'BA Mobile'!$AJ:$AJ,"YES", 'BA Mobile'!$U:$U,"No", 'BA Mobile'!$N:$N,">="&$B$1, 'BA Mobile'!$N:$N,"<"&$C$1+1 ), COUNTIFS( 'BA Mobile'!$D:$D,"Incident", 'BA Mobile'!$G:$G,1, 'BA Mobile'!$I:$I,"Triaged", 'BA Mobile'!$AJ:$AJ,"YES", 'BA Mobile'!$U:$U,"No", 'BA Mobile'!$N:$N,">="&$B$1, 'BA Mobile'!$N:$N,"<"&$C$1+1 ) ) -> 0 | G31: =SUM( COUNTIFS( 'BA Mobile'!$D:$D,"Incident", 'BA Mobile'!$G:$G,1, 'BA Mobile'!$I:$I,"Closed", 'BA Mobile'!$AI:$AI,"NO", 'BA Mobile'!$AJ:$AJ,"NO", 'BA Mobile'!$U:$U,"No", 'BA Mobile'!$N:$N,">="&$B$1, 'BA Mobile'!$N:$N,"<"&$C$1+1 ), COUNTIFS( 'BA Mobile'!$D:$D,"Incident", 'BA Mobile'!$G:$G,1, 'BA Mobile'!$I:$I,"Triaged", 'BA Mobile'!$AI:$AI,"NO", 'BA Mobile'!$AJ:$AJ,"NO", 'BA Mobile'!$U:$U,"No", 'BA Mobile'!$N:$N,">="&$B$1, 'BA Mobile'!$N:$N,"<"&$C$1+1 ) ) -> 0 | H31: =SUM( COUNTIFS( 'BA Mobile'!$D:$D,"Incident", 'BA Mobile'!$G:$G,2, 'BA Mobile'!$I:$I,"Closed", 'BA Mobile'!$U:$U,"NO", 'BA Mobile'!$N:$N,">="&$B$1, 'BA Mobile'!$N:$N,"<"&$C$1+1 ), COUNTIFS( 'BA Mobile'!$D:$D,"Incident", 'BA Mobile'!$G:$G,2, 'BA Mobile'!$I:$I,"Triaged", 'BA Mobile'!$U:$U,"NO", 'BA Mobile'!$N:$N,">="&$B$1, 'BA Mobile'!$N:$N,"<"&$C$1+1 ) ) -> 0 | I31: =SUM( COUNTIFS( 'BA Mobile'!$D:$D,"Incident", 'BA Mobile'!$G:$G,2, 'BA Mobile'!$I:$I,"Closed", 'BA Mobile'!$AI:$AI,"YES", 'BA Mobile'!$U:$U,"No", 'BA Mobile'!$N:$N,">="&$B$1, 'BA Mobile'!$N:$N,"<"&$C$1+1 ), COUNTIFS( 'BA Mobile'!$D:$D,"Incident", 'BA Mobile'!$G:$G,2, 'BA Mobile'!$I:$I,"Triaged", 'BA Mobile'!$AI:$AI,"YES", 'BA Mobile'!$U:$U,"No", 'BA Mobile'!$N:$N,">="&$B$1, 'BA Mobile'!$N:$N,"<"&$C$1+1 ) ) -> 0 | J31: =SUM( COUNTIFS( 'BA Mobile'!$D:$D,"Incident", 'BA Mobile'!$G:$G,2, 'BA Mobile'!$I:$I,"Closed", 'BA Mobile'!$AJ:$AJ,"YES", 'BA Mobile'!$U:$U,"No", 'BA Mobile'!$N:$N,">="&$B$1, 'BA Mobile'!$N:$N,"<"&$C$1+1 ), COUNTIFS( 'BA Mobile'!$D:$D,"Incident", 'BA Mobile'!$G:$G,2, 'BA Mobile'!$I:$I,"Triaged", 'BA Mobile'!$AJ:$AJ,"YES", 'BA Mobile'!$U:$U,"No", 'BA Mobile'!$N:$N,">="&$B$1, 'BA Mobile'!$N:$N,"<"&$C$1+1 ) ) -> 0 | K31: =SUM( COUNTIFS( 'BA Mobile'!$D:$D,"Incident", 'BA Mobile'!$G:$G,2, 'BA Mobile'!$I:$I,"Closed", 'BA Mobile'!$AI:$AI,"NO", 'BA Mobile'!$AJ:$AJ,"NO", 'BA Mobile'!$U:$U,"No", 'BA Mobile'!$N:$N,">="&$B$1, 'BA Mobile'!$N:$N,"<"&$C$1+1 ), COUNTIFS( 'BA Mobile'!$D:$D,"Incident", 'BA Mobile'!$G:$G,2, 'BA Mobile'!$I:$I,"Triaged", 'BA Mobile'!$AI:$AI,"NO", 'BA Mobile'!$AJ:$AJ,"NO", 'BA Mobile'!$U:$U,"No", 'BA Mobile'!$N:$N,">="&$B$1, 'BA Mobile'!$N:$N,"<"&$C$1+1 ) ) -> 0 | L31: =SUM( COUNTIFS( 'BA Mobile'!$D:$D,"Incident", 'BA Mobile'!$G:$G,3, 'BA Mobile'!$I:$I,"Closed", 'BA Mobile'!$U:$U,"NO", 'BA Mobile'!$N:$N,">="&$B$1, 'BA Mobile'!$N:$N,"<"&$C$1+1 ), COUNTIFS( 'BA Mobile'!$D:$D,"Incident", 'BA Mobile'!$G:$G,3, 'BA Mobile'!$I:$I,"Triaged", 'BA Mobile'!$U:$U,"NO", 'BA Mobile'!$N:$N,">="&$B$1, 'BA Mobile'!$N:$N,"<"&$C$1+1 ) ) -> 0 | M31: =SUM( COUNTIFS( 'BA Mobile'!$D:$D,"Incident", 'BA Mobile'!$G:$G,3, 'BA Mobile'!$I:$I,"Closed", 'BA Mobile'!$AI:$AI,"YES", 'BA Mobile'!$U:$U,"No", 'BA Mobile'!$N:$N,">="&$B$1, 'BA Mobile'!$N:$N,"<"&$C$1+1 ), COUNTIFS( 'BA Mobile'!$D:$D,"Incident", 'BA Mobile'!$G:$G,3, 'BA Mobile'!$I:$I,"Triaged", 'BA Mobile'!$AI:$AI,"YES", 'BA Mobile'!$U:$U,"No", 'BA Mobile'!$N:$N,">="&$B$1, 'BA Mobile'!$N:$N,"<"&$C$1+1 ) ) -> 0 | N31: =SUM( COUNTIFS( 'BA Mobile'!$D:$D,"Incident", 'BA Mobile'!$G:$G,3, 'BA Mobile'!$I:$I,"Closed", 'BA Mobile'!$AJ:$AJ,"YES", 'BA Mobile'!$U:$U,"No", 'BA Mobile'!$N:$N,">="&$B$1, 'BA Mobile'!$N:$N,"<"&$C$1+1 ), COUNTIFS( 'BA Mobile'!$D:$D,"Incident", 'BA Mobile'!$G:$G,3, 'BA Mobile'!$I:$I,"Triaged", 'BA Mobile'!$AJ:$AJ,"YES", 'BA Mobile'!$U:$U,"No", 'BA Mobile'!$N:$N,">="&$B$1, 'BA Mobile'!$N:$N,"<"&$C$1+1 ) ) -> 0 | O31: =SUM( COUNTIFS( 'BA Mobile'!$D:$D,"Incident", 'BA Mobile'!$G:$G,3, 'BA Mobile'!$I:$I,"Closed", 'BA Mobile'!$AI:$AI,"NO", 'BA Mobile'!$AJ:$AJ,"NO", 'BA Mobile'!$U:$U,"No", 'BA Mobile'!$N:$N,">="&$B$1, 'BA Mobile'!$N:$N,"<"&$C$1+1 ), COUNTIFS( 'BA Mobile'!$D:$D,"Incident", 'BA Mobile'!$G:$G,3, 'BA Mobile'!$I:$I,"Triaged", 'BA Mobile'!$AI:$AI,"NO", 'BA Mobile'!$AJ:$AJ,"NO", 'BA Mobile'!$U:$U,"No", 'BA Mobile'!$N:$N,">="&$B$1, 'BA Mobile'!$N:$N,"<"&$C$1+1 ) ) -> 0 | P31: =SUM( COUNTIFS( 'BA Mobile'!$D:$D,"Incident", 'BA Mobile'!$G:$G,4, 'BA Mobile'!$I:$I,"Closed", 'BA Mobile'!$U:$U,"NO", 'BA Mobile'!$N:$N,">="&$B$1, 'BA Mobile'!$N:$N,"<"&$C$1+1 ), COUNTIFS( 'BA Mobile'!$D:$D,"Incident", 'BA Mobile'!$G:$G,4, 'BA Mobile'!$I:$I,"Triaged", 'BA Mobile'!$U:$U,"NO", 'BA Mobile'!$N:$N,">="&$B$1, 'BA Mobile'!$N:$N,"<"&$C$1+1 ) ) -> 1 | Q31: =SUM( COUNTIFS( 'BA Mobile'!$D:$D,"Incident", 'BA Mobile'!$G:$G,4, 'BA Mobile'!$I:$I,"Closed", 'BA Mobile'!$AI:$AI,"YES", 'BA Mobile'!$U:$U,"No", 'BA Mobile'!$N:$N,">="&$B$1, 'BA Mobile'!$N:$N,"<"&$C$1+1 ), COUNTIFS( 'BA Mobile'!$D:$D,"Incident", 'BA Mobile'!$G:$G,4, 'BA Mobile'!$I:$I,"Triaged", 'BA Mobile'!$AI:$AI,"YES", 'BA Mobile'!$U:$U,"No", 'BA Mobile'!$N:$N,">="&$B$1, 'BA Mobile'!$N:$N,"<"&$C$1+1 ) ) -> 0 | R31: =SUM( COUNTIFS( 'BA Mobile'!$D:$D,"Incident", 'BA Mobile'!$G:$G,4, 'BA Mobile'!$I:$I,"Closed", 'BA Mobile'!$AJ:$AJ,"YES", 'BA Mobile'!$U:$U,"No", 'BA Mobile'!$N:$N,">="&$B$1, 'BA Mobile'!$N:$N,"<"&$C$1+1 ), COUNTIFS( 'BA Mobile'!$D:$D,"Incident", 'BA Mobile'!$G:$G,4, 'BA Mobile'!$I:$I,"Triaged", 'BA Mobile'!$AJ:$AJ,"YES", 'BA Mobile'!$U:$U,"No", 'BA Mobile'!$N:$N,">="&$B$1, 'BA Mobile'!$N:$N,"<"&$C$1+1 ) ) -> 0 | S31: =SUM( COUNTIFS( 'BA Mobile'!$D:$D,"Incident", 'BA Mobile'!$G:$G,4, 'BA Mobile'!$I:$I,"Closed", 'BA Mobile'!$AI:$AI,"NO", 'BA Mobile'!$AJ:$AJ,"NO", 'BA Mobile'!$U:$U,"No", 'BA Mobile'!$N:$N,">="&$B$1, 'BA Mobile'!$N:$N,"<"&$C$1+1 ), COUNTIFS( 'BA Mobile'!$D:$D,"Incident", 'BA Mobile'!$G:$G,4, 'BA Mobile'!$I:$I,"Triaged", 'BA Mobile'!$AI:$AI,"NO", 'BA Mobile'!$AJ:$AJ,"NO", 'BA Mobile'!$U:$U,"No", 'BA Mobile'!$N:$N,">="&$B$1, 'BA Mobile'!$N:$N,"<"&$C$1+1 ) ) -> 0
B32: BA | C32: LIP | D32: =SUM( COUNTIFS( LIP!$D:$D,"Incident", LIP!$G:$G,1, LIP!$I:$I,"Closed", LIP!$U:$U,"NO", LIP!$N:$N,">="&$B$1, LIP!$N:$N,"<"&$C$1+1 ), COUNTIFS( LIP!$D:$D,"Incident", LIP!$G:$G,1, LIP!$I:$I,"Triaged", LIP!$U:$U,"NO", LIP!$N:$N,">="&$B$1, LIP!$N:$N,"<"&$C$1+1 ) ) -> 0 | E32: =SUM( COUNTIFS( LIP!$D:$D,"Incident", LIP!$G:$G,1, LIP!$I:$I,"Closed", LIP!$AI:$AI,"YES", LIP!$U:$U,"No", LIP!$N:$N,">="&$B$1, LIP!$N:$N,"<"&$C$1+1 ), COUNTIFS( LIP!$D:$D,"Incident", LIP!$G:$G,1, LIP!$I:$I,"Triaged", LIP!$AI:$AI,"YES", LIP!$U:$U,"No", LIP!$N:$N,">="&$B$1, LIP!$N:$N,"<"&$C$1+1 ) ) -> 0 | F32: =SUM( COUNTIFS( LIP!$D:$D,"Incident", LIP!$G:$G,1, LIP!$I:$I,"Closed", LIP!$AJ:$AJ,"YES", LIP!$U:$U,"No", LIP!$N:$N,">="&$B$1, LIP!$N:$N,"<"&$C$1+1 ), COUNTIFS( LIP!$D:$D,"Incident", LIP!$G:$G,1, LIP!$I:$I,"Triaged", LIP!$AJ:$AJ,"YES", LIP!$U:$U,"No", LIP!$N:$N,">="&$B$1, LIP!$N:$N,"<"&$C$1+1 ) ) -> 0 | G32: =SUM( COUNTIFS( LIP!$D:$D,"Incident", LIP!$G:$G,1, LIP!$I:$I,"Closed", LIP!$AI:$AI,"NO", LIP!$AJ:$AJ,"NO", LIP!$U:$U,"No", LIP!$N:$N,">="&$B$1, LIP!$N:$N,"<"&$C$1+1 ), COUNTIFS( LIP!$D:$D,"Incident", LIP!$G:$G,1, LIP!$I:$I,"Triaged", LIP!$AI:$AI,"NO", LIP!$AJ:$AJ,"NO", LIP!$U:$U,"No", LIP!$N:$N,">="&$B$1, LIP!$N:$N,"<"&$C$1+1 ) ) -> 0 | H32: =SUM( COUNTIFS( LIP!$D:$D,"Incident", LIP!$G:$G,2, LIP!$I:$I,"Closed", LIP!$U:$U,"NO", LIP!$N:$N,">="&$B$1, LIP!$N:$N,"<"&$C$1+1 ), COUNTIFS( LIP!$D:$D,"Incident", LIP!$G:$G,2, LIP!$I:$I,"Triaged", LIP!$U:$U,"NO", LIP!$N:$N,">="&$B$1, LIP!$N:$N,"<"&$C$1+1 ) ) -> 0 | I32: =SUM( COUNTIFS( LIP!$D:$D,"Incident", LIP!$G:$G,2, LIP!$I:$I,"Closed", LIP!$AI:$AI,"YES", LIP!$U:$U,"No", LIP!$N:$N,">="&$B$1, LIP!$N:$N,"<"&$C$1+1 ), COUNTIFS( LIP!$D:$D,"Incident", LIP!$G:$G,2, LIP!$I:$I,"Triaged", LIP!$AI:$AI,"YES", LIP!$U:$U,"No", LIP!$N:$N,">="&$B$1, LIP!$N:$N,"<"&$C$1+1 ) ) -> 0 | J32: =SUM( COUNTIFS( LIP!$D:$D,"Incident", LIP!$G:$G,2, LIP!$I:$I,"Closed", LIP!$AJ:$AJ,"YES", LIP!$U:$U,"No", LIP!$N:$N,">="&$B$1, LIP!$N:$N,"<"&$C$1+1 ), COUNTIFS( LIP!$D:$D,"Incident", LIP!$G:$G,2, LIP!$I:$I,"Triaged", LIP!$AJ:$AJ,"YES", LIP!$U:$U,"No", LIP!$N:$N,">="&$B$1, LIP!$N:$N,"<"&$C$1+1 ) ) -> 0 | K32: =SUM( COUNTIFS( LIP!$D:$D,"Incident", LIP!$G:$G,2, LIP!$I:$I,"Closed", LIP!$AI:$AI,"NO", LIP!$AJ:$AJ,"NO", LIP!$U:$U,"No", LIP!$N:$N,">="&$B$1, LIP!$N:$N,"<"&$C$1+1 ), COUNTIFS( LIP!$D:$D,"Incident", LIP!$G:$G,2, LIP!$I:$I,"Triaged", LIP!$AI:$AI,"NO", LIP!$AJ:$AJ,"NO", LIP!$U:$U,"No", LIP!$N:$N,">="&$B$1, LIP!$N:$N,"<"&$C$1+1 ) ) -> 0 | L32: =SUM( COUNTIFS( LIP!$D:$D,"Incident", LIP!$G:$G,3, LIP!$I:$I,"Closed", LIP!$U:$U,"NO", LIP!$N:$N,">="&$B$1, LIP!$N:$N,"<"&$C$1+1 ), COUNTIFS( LIP!$D:$D,"Incident", LIP!$G:$G,3, LIP!$I:$I,"Triaged", LIP!$U:$U,"NO", LIP!$N:$N,">="&$B$1, LIP!$N:$N,"<"&$C$1+1 ) ) -> 1 | M32: =SUM( COUNTIFS( LIP!$D:$D,"Incident", LIP!$G:$G,3, LIP!$I:$I,"Closed", LIP!$AI:$AI,"YES", LIP!$U:$U,"No", LIP!$N:$N,">="&$B$1, LIP!$N:$N,"<"&$C$1+1 ), COUNTIFS( LIP!$D:$D,"Incident", LIP!$G:$G,3, LIP!$I:$I,"Triaged", LIP!$AI:$AI,"YES", LIP!$U:$U,"No", LIP!$N:$N,">="&$B$1, LIP!$N:$N,"<"&$C$1+1 ) ) -> 1 | N32: =SUM( COUNTIFS( LIP!$D:$D,"Incident", LIP!$G:$G,3, LIP!$I:$I,"Closed", LIP!$AJ:$AJ,"YES", LIP!$U:$U,"No", LIP!$N:$N,">="&$B$1, LIP!$N:$N,"<"&$C$1+1 ), COUNTIFS( LIP!$D:$D,"Incident", LIP!$G:$G,3, LIP!$I:$I,"Triaged", LIP!$AJ:$AJ,"YES", LIP!$U:$U,"No", LIP!$N:$N,">="&$B$1, LIP!$N:$N,"<"&$C$1+1 ) ) -> 1 | O32: =SUM( COUNTIFS( LIP!$D:$D,"Incident", LIP!$G:$G,3, LIP!$I:$I,"Closed", LIP!$AI:$AI,"NO", LIP!$AJ:$AJ,"NO", LIP!$U:$U,"No", LIP!$N:$N,">="&$B$1, LIP!$N:$N,"<"&$C$1+1 ), COUNTIFS( LIP!$D:$D,"Incident", LIP!$G:$G,3, LIP!$I:$I,"Triaged", LIP!$AI:$AI,"NO", LIP!$AJ:$AJ,"NO", LIP!$U:$U,"No", LIP!$N:$N,">="&$B$1, LIP!$N:$N,"<"&$C$1+1 ) ) -> 0 | P32: =SUM( COUNTIFS( LIP!$D:$D,"Incident", LIP!$G:$G,4, LIP!$I:$I,"Closed", LIP!$U:$U,"NO", LIP!$N:$N,">="&$B$1, LIP!$N:$N,"<"&$C$1+1 ), COUNTIFS( LIP!$D:$D,"Incident", LIP!$G:$G,4, LIP!$I:$I,"Triaged", LIP!$U:$U,"NO", LIP!$N:$N,">="&$B$1, LIP!$N:$N,"<"&$C$1+1 ) ) -> 27 | Q32: =SUM( COUNTIFS( LIP!$D:$D,"Incident", LIP!$G:$G,4, LIP!$I:$I,"Closed", LIP!$AI:$AI,"YES", LIP!$U:$U,"No", LIP!$N:$N,">="&$B$1, LIP!$N:$N,"<"&$C$1+1 ), COUNTIFS( LIP!$D:$D,"Incident", LIP!$G:$G,4, LIP!$I:$I,"Triaged", LIP!$AI:$AI,"YES", LIP!$U:$U,"No", LIP!$N:$N,">="&$B$1, LIP!$N:$N,"<"&$C$1+1 ) ) -> 27 | R32: =SUM( COUNTIFS( LIP!$D:$D,"Incident", LIP!$G:$G,4, LIP!$I:$I,"Closed", LIP!$AJ:$AJ,"YES", LIP!$U:$U,"No", LIP!$N:$N,">="&$B$1, LIP!$N:$N,"<"&$C$1+1 ), COUNTIFS( LIP!$D:$D,"Incident", LIP!$G:$G,4, LIP!$I:$I,"Triaged", LIP!$AJ:$AJ,"YES", LIP!$U:$U,"No", LIP!$N:$N,">="&$B$1, LIP!$N:$N,"<"&$C$1+1 ) ) -> 27 | S32: =SUM( COUNTIFS( LIP!$D:$D,"Incident", LIP!$G:$G,4, LIP!$I:$I,"Closed", LIP!$AI:$AI,"NO", LIP!$AJ:$AJ,"NO", LIP!$U:$U,"No", LIP!$N:$N,">="&$B$1, LIP!$N:$N,"<"&$C$1+1 ), COUNTIFS( LIP!$D:$D,"Incident", LIP!$G:$G,4, LIP!$I:$I,"Triaged", LIP!$AI:$AI,"NO", LIP!$AJ:$AJ,"NO", LIP!$U:$U,"No", LIP!$N:$N,">="&$B$1, LIP!$N:$N,"<"&$C$1+1 ) ) -> 0
B33: BA | C33: QIP | D33: =SUM( COUNTIFS( QIP!$D:$D,"Incident", QIP!$G:$G,1, QIP!$I:$I,"Closed", QIP!$U:$U,"NO", QIP!$N:$N,">="&$B$1, QIP!$N:$N,"<"&$C$1+1 ), COUNTIFS( QIP!$D:$D,"Incident", QIP!$G:$G,1, QIP!$I:$I,"Triaged", QIP!$U:$U,"NO", QIP!$N:$N,">="&$B$1, QIP!$N:$N,"<"&$C$1+1 ) ) -> 0 | E33: =SUM( COUNTIFS( QIP!$D:$D,"Incident", QIP!$G:$G,1, QIP!$I:$I,"Closed", QIP!$AI:$AI,"YES", QIP!$U:$U,"No", QIP!$N:$N,">="&$B$1, QIP!$N:$N,"<"&$C$1+1 ), COUNTIFS( QIP!$D:$D,"Incident", QIP!$G:$G,1, QIP!$I:$I,"Triaged", QIP!$AI:$AI,"YES", QIP!$U:$U,"No", QIP!$N:$N,">="&$B$1, QIP!$N:$N,"<"&$C$1+1 ) ) -> 0 | F33: =SUM( COUNTIFS( QIP!$D:$D,"Incident", QIP!$G:$G,1, QIP!$I:$I,"Closed", QIP!$AJ:$AJ,"YES", QIP!$U:$U,"No", QIP!$N:$N,">="&$B$1, QIP!$N:$N,"<"&$C$1+1 ), COUNTIFS( QIP!$D:$D,"Incident", QIP!$G:$G,1, QIP!$I:$I,"Triaged", QIP!$AJ:$AJ,"YES", QIP!$U:$U,"No", QIP!$N:$N,">="&$B$1, QIP!$N:$N,"<"&$C$1+1 ) ) -> 0 | G33: =SUM( COUNTIFS( QIP!$D:$D,"Incident", QIP!$G:$G,1, QIP!$I:$I,"Closed", QIP!$AI:$AI,"NO", QIP!$AJ:$AJ,"NO", QIP!$U:$U,"No", QIP!$N:$N,">="&$B$1, QIP!$N:$N,"<"&$C$1+1 ), COUNTIFS( QIP!$D:$D,"Incident", QIP!$G:$G,1, QIP!$I:$I,"Triaged", QIP!$AI:$AI,"NO", QIP!$AJ:$AJ,"NO", QIP!$U:$U,"No", QIP!$N:$N,">="&$B$1, QIP!$N:$N,"<"&$C$1+1 ) ) -> 0 | H33: =SUM( COUNTIFS( QIP!$D:$D,"Incident", QIP!$G:$G,2, QIP!$I:$I,"Closed", QIP!$U:$U,"NO", QIP!$N:$N,">="&$B$1, QIP!$N:$N,"<"&$C$1+1 ), COUNTIFS( QIP!$D:$D,"Incident", QIP!$G:$G,2, QIP!$I:$I,"Triaged", QIP!$U:$U,"NO", QIP!$N:$N,">="&$B$1, QIP!$N:$N,"<"&$C$1+1 ) ) -> 0 | I33: =SUM( COUNTIFS( QIP!$D:$D,"Incident", QIP!$G:$G,2, QIP!$I:$I,"Closed", QIP!$AI:$AI,"YES", QIP!$U:$U,"No", QIP!$N:$N,">="&$B$1, QIP!$N:$N,"<"&$C$1+1 ), COUNTIFS( QIP!$D:$D,"Incident", QIP!$G:$G,2, QIP!$I:$I,"Triaged", QIP!$AI:$AI,"YES", QIP!$U:$U,"No", QIP!$N:$N,">="&$B$1, QIP!$N:$N,"<"&$C$1+1 ) ) -> 0 | J33: =SUM( COUNTIFS( QIP!$D:$D,"Incident", QIP!$G:$G,2, QIP!$I:$I,"Closed", QIP!$AJ:$AJ,"YES", QIP!$U:$U,"No", QIP!$N:$N,">="&$B$1, QIP!$N:$N,"<"&$C$1+1 ), COUNTIFS( QIP!$D:$D,"Incident", QIP!$G:$G,2, QIP!$I:$I,"Triaged", QIP!$AJ:$AJ,"YES", QIP!$U:$U,"No", QIP!$N:$N,">="&$B$1, QIP!$N:$N,"<"&$C$1+1 ) ) -> 0 | K33: =SUM( COUNTIFS( QIP!$D:$D,"Incident", QIP!$G:$G,2, QIP!$I:$I,"Closed", QIP!$AI:$AI,"NO", QIP!$AJ:$AJ,"NO", QIP!$U:$U,"No", QIP!$N:$N,">="&$B$1, QIP!$N:$N,"<"&$C$1+1 ), COUNTIFS( QIP!$D:$D,"Incident", QIP!$G:$G,2, QIP!$I:$I,"Triaged", QIP!$AI:$AI,"NO", QIP!$AJ:$AJ,"NO", QIP!$U:$U,"No", QIP!$N:$N,">="&$B$1, QIP!$N:$N,"<"&$C$1+1 ) ) -> 0 | L33: =SUM( COUNTIFS( QIP!$D:$D,"Incident", QIP!$G:$G,3, QIP!$I:$I,"Closed", QIP!$U:$U,"NO", QIP!$N:$N,">="&$B$1, QIP!$N:$N,"<"&$C$1+1 ), COUNTIFS( QIP!$D:$D,"Incident", QIP!$G:$G,3, QIP!$I:$I,"Triaged", QIP!$U:$U,"NO", QIP!$N:$N,">="&$B$1, QIP!$N:$N,"<"&$C$1+1 ) ) -> 7 | M33: =SUM( COUNTIFS( QIP!$D:$D,"Incident", QIP!$G:$G,3, QIP!$I:$I,"Closed", QIP!$AI:$AI,"YES", QIP!$U:$U,"No", QIP!$N:$N,">="&$B$1, QIP!$N:$N,"<"&$C$1+1 ), COUNTIFS( QIP!$D:$D,"Incident", QIP!$G:$G,3, QIP!$I:$I,"Triaged", QIP!$AI:$AI,"YES", QIP!$U:$U,"No", QIP!$N:$N,">="&$B$1, QIP!$N:$N,"<"&$C$1+1 ) ) -> 4 | N33: =SUM( COUNTIFS( QIP!$D:$D,"Incident", QIP!$G:$G,3, QIP!$I:$I,"Closed", QIP!$AJ:$AJ,"YES", QIP!$U:$U,"No", QIP!$N:$N,">="&$B$1, QIP!$N:$N,"<"&$C$1+1 ), COUNTIFS( QIP!$D:$D,"Incident", QIP!$G:$G,3, QIP!$I:$I,"Triaged", QIP!$AJ:$AJ,"YES", QIP!$U:$U,"No", QIP!$N:$N,">="&$B$1, QIP!$N:$N,"<"&$C$1+1 ) ) -> 7 | O33: =SUM( COUNTIFS( QIP!$D:$D,"Incident", QIP!$G:$G,3, QIP!$I:$I,"Closed", QIP!$AI:$AI,"NO", QIP!$AJ:$AJ,"NO", QIP!$U:$U,"No", QIP!$N:$N,">="&$B$1, QIP!$N:$N,"<"&$C$1+1 ), COUNTIFS( QIP!$D:$D,"Incident", QIP!$G:$G,3, QIP!$I:$I,"Triaged", QIP!$AI:$AI,"NO", QIP!$AJ:$AJ,"NO", QIP!$U:$U,"No", QIP!$N:$N,">="&$B$1, QIP!$N:$N,"<"&$C$1+1 ) ) -> 0 | P33: =SUM( COUNTIFS( QIP!$D:$D,"Incident", QIP!$G:$G,4, QIP!$I:$I,"Closed", QIP!$U:$U,"NO", QIP!$N:$N,">="&$B$1, QIP!$N:$N,"<"&$C$1+1 ), COUNTIFS( QIP!$D:$D,"Incident", QIP!$G:$G,4, QIP!$I:$I,"Triaged", QIP!$U:$U,"NO", QIP!$N:$N,">="&$B$1, QIP!$N:$N,"<"&$C$1+1 ) ) -> 49 | Q33: =SUM( COUNTIFS( QIP!$D:$D,"Incident", QIP!$G:$G,4, QIP!$I:$I,"Closed", QIP!$AI:$AI,"YES", QIP!$U:$U,"No", QIP!$N:$N,">="&$B$1, QIP!$N:$N,"<"&$C$1+1 ), COUNTIFS( QIP!$D:$D,"Incident", QIP!$G:$G,4, QIP!$I:$I,"Triaged", QIP!$AI:$AI,"YES", QIP!$U:$U,"No", QIP!$N:$N,">="&$B$1, QIP!$N:$N,"<"&$C$1+1 ) ) -> 44 | R33: =SUM( COUNTIFS( QIP!$D:$D,"Incident", QIP!$G:$G,4, QIP!$I:$I,"Closed", QIP!$AJ:$AJ,"YES", QIP!$U:$U,"No", QIP!$N:$N,">="&$B$1, QIP!$N:$N,"<"&$C$1+1 ), COUNTIFS( QIP!$D:$D,"Incident", QIP!$G:$G,4, QIP!$I:$I,"Triaged", QIP!$AJ:$AJ,"YES", QIP!$U:$U,"No", QIP!$N:$N,">="&$B$1, QIP!$N:$N,"<"&$C$1+1 ) ) -> 44 | S33: =SUM( COUNTIFS( QIP!$D:$D,"Incident", QIP!$G:$G,4, QIP!$I:$I,"Closed", QIP!$AI:$AI,"NO", QIP!$AJ:$AJ,"NO", QIP!$U:$U,"No", QIP!$N:$N,">="&$B$1, QIP!$N:$N,"<"&$C$1+1 ), COUNTIFS( QIP!$D:$D,"Incident", QIP!$G:$G,4, QIP!$I:$I,"Triaged", QIP!$AI:$AI,"NO", QIP!$AJ:$AJ,"NO", QIP!$U:$U,"No", QIP!$N:$N,">="&$B$1, QIP!$N:$N,"<"&$C$1+1 ) ) -> 2
B34: BA | C34: MRO | D34: =SUM( COUNTIFS( 'BA MRO'!$D:$D,"Incident", 'BA MRO'!$G:$G,1, 'BA MRO'!$I:$I,"Closed", 'BA MRO'!$U:$U,"NO", 'BA MRO'!$N:$N,">="&$B$1, 'BA MRO'!$N:$N,"<"&$C$1+1 ), COUNTIFS( 'BA MRO'!$D:$D,"Incident", 'BA MRO'!$G:$G,1, 'BA MRO'!$I:$I,"Triaged", 'BA MRO'!$U:$U,"NO", 'BA MRO'!$N:$N,">="&$B$1, 'BA MRO'!$N:$N,"<"&$C$1+1 ) ) -> 0 | E34: =SUM( COUNTIFS( 'BA MRO'!$D:$D,"Incident", 'BA MRO'!$G:$G,1, 'BA MRO'!$I:$I,"Closed", 'BA MRO'!$AI:$AI,"YES", 'BA MRO'!$U:$U,"No", 'BA MRO'!$N:$N,">="&$B$1, 'BA MRO'!$N:$N,"<"&$C$1+1 ), COUNTIFS( 'BA MRO'!$D:$D,"Incident", 'BA MRO'!$G:$G,1, 'BA MRO'!$I:$I,"Triaged", 'BA MRO'!$AI:$AI,"YES", 'BA MRO'!$U:$U,"No", 'BA MRO'!$N:$N,">="&$B$1, 'BA MRO'!$N:$N,"<"&$C$1+1 ) ) -> 0 | F34: =SUM( COUNTIFS( 'BA MRO'!$D:$D,"Incident", 'BA MRO'!$G:$G,1, 'BA MRO'!$I:$I,"Closed", 'BA MRO'!$AJ:$AJ,"YES", 'BA MRO'!$U:$U,"No", 'BA MRO'!$N:$N,">="&$B$1, 'BA MRO'!$N:$N,"<"&$C$1+1 ), COUNTIFS( 'BA MRO'!$D:$D,"Incident", 'BA MRO'!$G:$G,1, 'BA MRO'!$I:$I,"Triaged", 'BA MRO'!$AJ:$AJ,"YES", 'BA MRO'!$U:$U,"No", 'BA MRO'!$N:$N,">="&$B$1, 'BA MRO'!$N:$N,"<"&$C$1+1 ) ) -> 0 | G34: =SUM( COUNTIFS( 'BA MRO'!$D:$D,"Incident", 'BA MRO'!$G:$G,1, 'BA MRO'!$I:$I,"Closed", 'BA MRO'!$AI:$AI,"NO", 'BA MRO'!$AJ:$AJ,"NO", 'BA MRO'!$U:$U,"No", 'BA MRO'!$N:$N,">="&$B$1, 'BA MRO'!$N:$N,"<"&$C$1+1 ), COUNTIFS( 'BA MRO'!$D:$D,"Incident", 'BA MRO'!$G:$G,1, 'BA MRO'!$I:$I,"Triaged", 'BA MRO'!$AI:$AI,"NO", 'BA MRO'!$AJ:$AJ,"NO", 'BA MRO'!$U:$U,"No", 'BA MRO'!$N:$N,">="&$B$1, 'BA MRO'!$N:$N,"<"&$C$1+1 ) ) -> 0 | H34: =SUM( COUNTIFS( 'BA MRO'!$D:$D,"Incident", 'BA MRO'!$G:$G,2, 'BA MRO'!$I:$I,"Closed", 'BA MRO'!$U:$U,"NO", 'BA MRO'!$N:$N,">="&$B$1, 'BA MRO'!$N:$N,"<"&$C$1+1 ), COUNTIFS( 'BA MRO'!$D:$D,"Incident", 'BA MRO'!$G:$G,2, 'BA MRO'!$I:$I,"Triaged", 'BA MRO'!$U:$U,"NO", 'BA MRO'!$N:$N,">="&$B$1, 'BA MRO'!$N:$N,"<"&$C$1+1 ) ) -> 0 | I34: =SUM( COUNTIFS( 'BA MRO'!$D:$D,"Incident", 'BA MRO'!$G:$G,2, 'BA MRO'!$I:$I,"Closed", 'BA MRO'!$AI:$AI,"YES", 'BA MRO'!$U:$U,"No", 'BA MRO'!$N:$N,">="&$B$1, 'BA MRO'!$N:$N,"<"&$C$1+1 ), COUNTIFS( 'BA MRO'!$D:$D,"Incident", 'BA MRO'!$G:$G,2, 'BA MRO'!$I:$I,"Triaged", 'BA MRO'!$AI:$AI,"YES", 'BA MRO'!$U:$U,"No", 'BA MRO'!$N:$N,">="&$B$1, 'BA MRO'!$N:$N,"<"&$C$1+1 ) ) -> 0 | J34: =SUM( COUNTIFS( 'BA MRO'!$D:$D,"Incident", 'BA MRO'!$G:$G,2, 'BA MRO'!$I:$I,"Closed", 'BA MRO'!$AJ:$AJ,"YES", 'BA MRO'!$U:$U,"No", 'BA MRO'!$N:$N,">="&$B$1, 'BA MRO'!$N:$N,"<"&$C$1+1 ), COUNTIFS( 'BA MRO'!$D:$D,"Incident", 'BA MRO'!$G:$G,2, 'BA MRO'!$I:$I,"Triaged", 'BA MRO'!$AJ:$AJ,"YES", 'BA MRO'!$U:$U,"No", 'BA MRO'!$N:$N,">="&$B$1, 'BA MRO'!$N:$N,"<"&$C$1+1 ) ) -> 0 | K34: =SUM( COUNTIFS( 'BA MRO'!$D:$D,"Incident", 'BA MRO'!$G:$G,2, 'BA MRO'!$I:$I,"Closed", 'BA MRO'!$AI:$AI,"NO", 'BA MRO'!$AJ:$AJ,"NO", 'BA MRO'!$U:$U,"No", 'BA MRO'!$N:$N,">="&$B$1, 'BA MRO'!$N:$N,"<"&$C$1+1 ), COUNTIFS( 'BA MRO'!$D:$D,"Incident", 'BA MRO'!$G:$G,2, 'BA MRO'!$I:$I,"Triaged", 'BA MRO'!$AI:$AI,"NO", 'BA MRO'!$AJ:$AJ,"NO", 'BA MRO'!$U:$U,"No", 'BA MRO'!$N:$N,">="&$B$1, 'BA MRO'!$N:$N,"<"&$C$1+1 ) ) -> 0 | L34: =SUM( COUNTIFS( 'BA MRO'!$D:$D,"Incident", 'BA MRO'!$G:$G,3, 'BA MRO'!$I:$I,"Closed", 'BA MRO'!$U:$U,"NO", 'BA MRO'!$N:$N,">="&$B$1, 'BA MRO'!$N:$N,"<"&$C$1+1 ), COUNTIFS( 'BA MRO'!$D:$D,"Incident", 'BA MRO'!$G:$G,3, 'BA MRO'!$I:$I,"Triaged", 'BA MRO'!$U:$U,"NO", 'BA MRO'!$N:$N,">="&$B$1, 'BA MRO'!$N:$N,"<"&$C$1+1 ) ) -> 0 | M34: =SUM( COUNTIFS( 'BA MRO'!$D:$D,"Incident", 'BA MRO'!$G:$G,3, 'BA MRO'!$I:$I,"Closed", 'BA MRO'!$AI:$AI,"YES", 'BA MRO'!$U:$U,"No", 'BA MRO'!$N:$N,">="&$B$1, 'BA MRO'!$N:$N,"<"&$C$1+1 ), COUNTIFS( 'BA MRO'!$D:$D,"Incident", 'BA MRO'!$G:$G,3, 'BA MRO'!$I:$I,"Triaged", 'BA MRO'!$AI:$AI,"YES", 'BA MRO'!$U:$U,"No", 'BA MRO'!$N:$N,">="&$B$1, 'BA MRO'!$N:$N,"<"&$C$1+1 ) ) -> 0 | N34: =SUM( COUNTIFS( 'BA MRO'!$D:$D,"Incident", 'BA MRO'!$G:$G,3, 'BA MRO'!$I:$I,"Closed", 'BA MRO'!$AJ:$AJ,"YES", 'BA MRO'!$U:$U,"No", 'BA MRO'!$N:$N,">="&$B$1, 'BA MRO'!$N:$N,"<"&$C$1+1 ), COUNTIFS( 'BA MRO'!$D:$D,"Incident", 'BA MRO'!$G:$G,3, 'BA MRO'!$I:$I,"Triaged", 'BA MRO'!$AJ:$AJ,"YES", 'BA MRO'!$U:$U,"No", 'BA MRO'!$N:$N,">="&$B$1, 'BA MRO'!$N:$N,"<"&$C$1+1 ) ) -> 0 | O34: =SUM( COUNTIFS( 'BA MRO'!$D:$D,"Incident", 'BA MRO'!$G:$G,3, 'BA MRO'!$I:$I,"Closed", 'BA MRO'!$AI:$AI,"NO", 'BA MRO'!$AJ:$AJ,"NO", 'BA MRO'!$U:$U,"No", 'BA MRO'!$N:$N,">="&$B$1, 'BA MRO'!$N:$N,"<"&$C$1+1 ), COUNTIFS( 'BA MRO'!$D:$D,"Incident", 'BA MRO'!$G:$G,3, 'BA MRO'!$I:$I,"Triaged", 'BA MRO'!$AI:$AI,"NO", 'BA MRO'!$AJ:$AJ,"NO", 'BA MRO'!$U:$U,"No", 'BA MRO'!$N:$N,">="&$B$1, 'BA MRO'!$N:$N,"<"&$C$1+1 ) ) -> 0 | P34: =SUM( COUNTIFS( 'BA MRO'!$D:$D,"Incident", 'BA MRO'!$G:$G,4, 'BA MRO'!$I:$I,"Closed", 'BA MRO'!$U:$U,"NO", 'BA MRO'!$N:$N,">="&$B$1, 'BA MRO'!$N:$N,"<"&$C$1+1 ), COUNTIFS( 'BA MRO'!$D:$D,"Incident", 'BA MRO'!$G:$G,4, 'BA MRO'!$I:$I,"Triaged", 'BA MRO'!$U:$U,"NO", 'BA MRO'!$N:$N,">="&$B$1, 'BA MRO'!$N:$N,"<"&$C$1+1 ) ) -> 0 | Q34: =SUM( COUNTIFS( 'BA MRO'!$D:$D,"Incident", 'BA MRO'!$G:$G,4, 'BA MRO'!$I:$I,"Closed", 'BA MRO'!$AI:$AI,"YES", 'BA MRO'!$U:$U,"No", 'BA MRO'!$N:$N,">="&$B$1, 'BA MRO'!$N:$N,"<"&$C$1+1 ), COUNTIFS( 'BA MRO'!$D:$D,"Incident", 'BA MRO'!$G:$G,4, 'BA MRO'!$I:$I,"Triaged", 'BA MRO'!$AI:$AI,"YES", 'BA MRO'!$U:$U,"No", 'BA MRO'!$N:$N,">="&$B$1, 'BA MRO'!$N:$N,"<"&$C$1+1 ) ) -> 0 | R34: =SUM( COUNTIFS( 'BA MRO'!$D:$D,"Incident", 'BA MRO'!$G:$G,4, 'BA MRO'!$I:$I,"Closed", 'BA MRO'!$AJ:$AJ,"YES", 'BA MRO'!$U:$U,"No", 'BA MRO'!$N:$N,">="&$B$1, 'BA MRO'!$N:$N,"<"&$C$1+1 ), COUNTIFS( 'BA MRO'!$D:$D,"Incident", 'BA MRO'!$G:$G,4, 'BA MRO'!$I:$I,"Triaged", 'BA MRO'!$AJ:$AJ,"YES", 'BA MRO'!$U:$U,"No", 'BA MRO'!$N:$N,">="&$B$1, 'BA MRO'!$N:$N,"<"&$C$1+1 ) ) -> 0 | S34: =SUM( COUNTIFS( 'BA MRO'!$D:$D,"Incident", 'BA MRO'!$G:$G,4, 'BA MRO'!$I:$I,"Closed", 'BA MRO'!$AI:$AI,"NO", 'BA MRO'!$AJ:$AJ,"NO", 'BA MRO'!$U:$U,"No", 'BA MRO'!$N:$N,">="&$B$1, 'BA MRO'!$N:$N,"<"&$C$1+1 ), COUNTIFS( 'BA MRO'!$D:$D,"Incident", 'BA MRO'!$G:$G,4, 'BA MRO'!$I:$I,"Triaged", 'BA MRO'!$AI:$AI,"NO", 'BA MRO'!$AJ:$AJ,"NO", 'BA MRO'!$U:$U,"No", 'BA MRO'!$N:$N,">="&$B$1, 'BA MRO'!$N:$N,"<"&$C$1+1 ) ) -> 0
B35: BA | C35: Pathway | D35: =SUM( COUNTIFS( Pathway!$D:$D,"Incident", Pathway!$G:$G,1, Pathway!$I:$I,"Closed", Pathway!$U:$U,"NO", Pathway!$N:$N,">="&$B$1, Pathway!$N:$N,"<"&$C$1+1 ), COUNTIFS( Pathway!$D:$D,"Incident", Pathway!$G:$G,1, Pathway!$I:$I,"Triaged", Pathway!$U:$U,"NO", Pathway!$N:$N,">="&$B$1, Pathway!$N:$N,"<"&$C$1+1 ) ) -> 0 | E35: =SUM( COUNTIFS( Pathway!$D:$D,"Incident", Pathway!$G:$G,1, Pathway!$I:$I,"Closed", Pathway!$AI:$AI,"YES", Pathway!$U:$U,"No", Pathway!$N:$N,">="&$B$1, Pathway!$N:$N,"<"&$C$1+1 ), COUNTIFS( Pathway!$D:$D,"Incident", Pathway!$G:$G,1, Pathway!$I:$I,"Triaged", Pathway!$AI:$AI,"YES", Pathway!$U:$U,"No", Pathway!$N:$N,">="&$B$1, Pathway!$N:$N,"<"&$C$1+1 ) ) -> 0 | F35: =SUM( COUNTIFS( Pathway!$D:$D,"Incident", Pathway!$G:$G,1, Pathway!$I:$I,"Closed", Pathway!$AJ:$AJ,"YES", Pathway!$U:$U,"No", Pathway!$N:$N,">="&$B$1, Pathway!$N:$N,"<"&$C$1+1 ), COUNTIFS( Pathway!$D:$D,"Incident", Pathway!$G:$G,1, Pathway!$I:$I,"Triaged", Pathway!$AJ:$AJ,"YES", Pathway!$U:$U,"No", Pathway!$N:$N,">="&$B$1, Pathway!$N:$N,"<"&$C$1+1 ) ) -> 0 | G35: =SUM( COUNTIFS( Pathway!$D:$D,"Incident", Pathway!$G:$G,1, Pathway!$I:$I,"Closed", Pathway!$AI:$AI,"NO", Pathway!$AJ:$AJ,"NO", Pathway!$U:$U,"No", Pathway!$N:$N,">="&$B$1, Pathway!$N:$N,"<"&$C$1+1 ), COUNTIFS( Pathway!$D:$D,"Incident", Pathway!$G:$G,1, Pathway!$I:$I,"Triaged", Pathway!$AI:$AI,"NO", Pathway!$AJ:$AJ,"NO", Pathway!$U:$U,"No", Pathway!$N:$N,">="&$B$1, Pathway!$N:$N,"<"&$C$1+1 ) ) -> 0 | H35: =SUM( COUNTIFS( Pathway!$D:$D,"Incident", Pathway!$G:$G,2, Pathway!$I:$I,"Closed", Pathway!$U:$U,"NO", Pathway!$N:$N,">="&$B$1, Pathway!$N:$N,"<"&$C$1+1 ), COUNTIFS( Pathway!$D:$D,"Incident", Pathway!$G:$G,2, Pathway!$I:$I,"Triaged", Pathway!$U:$U,"NO", Pathway!$N:$N,">="&$B$1, Pathway!$N:$N,"<"&$C$1+1 ) ) -> 0 | I35: =SUM( COUNTIFS( Pathway!$D:$D,"Incident", Pathway!$G:$G,2, Pathway!$I:$I,"Closed", Pathway!$AI:$AI,"YES", Pathway!$U:$U,"No", Pathway!$N:$N,">="&$B$1, Pathway!$N:$N,"<"&$C$1+1 ), COUNTIFS( Pathway!$D:$D,"Incident", Pathway!$G:$G,2, Pathway!$I:$I,"Triaged", Pathway!$AI:$AI,"YES", Pathway!$U:$U,"No", Pathway!$N:$N,">="&$B$1, Pathway!$N:$N,"<"&$C$1+1 ) ) -> 0 | J35: =SUM( COUNTIFS( Pathway!$D:$D,"Incident", Pathway!$G:$G,2, Pathway!$I:$I,"Closed", Pathway!$AJ:$AJ,"YES", Pathway!$U:$U,"No", Pathway!$N:$N,">="&$B$1, Pathway!$N:$N,"<"&$C$1+1 ), COUNTIFS( Pathway!$D:$D,"Incident", Pathway!$G:$G,2, Pathway!$I:$I,"Triaged", Pathway!$AJ:$AJ,"YES", Pathway!$U:$U,"No", Pathway!$N:$N,">="&$B$1, Pathway!$N:$N,"<"&$C$1+1 ) ) -> 0 | K35: =SUM( COUNTIFS( Pathway!$D:$D,"Incident", Pathway!$G:$G,2, Pathway!$I:$I,"Closed", Pathway!$AI:$AI,"NO", Pathway!$AJ:$AJ,"NO", Pathway!$U:$U,"No", Pathway!$N:$N,">="&$B$1, Pathway!$N:$N,"<"&$C$1+1 ), COUNTIFS( Pathway!$D:$D,"Incident", Pathway!$G:$G,2, Pathway!$I:$I,"Triaged", Pathway!$AI:$AI,"NO", Pathway!$AJ:$AJ,"NO", Pathway!$U:$U,"No", Pathway!$N:$N,">="&$B$1, Pathway!$N:$N,"<"&$C$1+1 ) ) -> 0 | L35: =SUM( COUNTIFS( Pathway!$D:$D,"Incident", Pathway!$G:$G,3, Pathway!$I:$I,"Closed", Pathway!$U:$U,"NO", Pathway!$N:$N,">="&$B$1, Pathway!$N:$N,"<"&$C$1+1 ), COUNTIFS( Pathway!$D:$D,"Incident", Pathway!$G:$G,3, Pathway!$I:$I,"Triaged", Pathway!$U:$U,"NO", Pathway!$N:$N,">="&$B$1, Pathway!$N:$N,"<"&$C$1+1 ) ) -> 8 | M35: =SUM( COUNTIFS( Pathway!$D:$D,"Incident", Pathway!$G:$G,3, Pathway!$I:$I,"Closed", Pathway!$AI:$AI,"YES", Pathway!$U:$U,"No", Pathway!$N:$N,">="&$B$1, Pathway!$N:$N,"<"&$C$1+1 ), COUNTIFS( Pathway!$D:$D,"Incident", Pathway!$G:$G,3, Pathway!$I:$I,"Triaged", Pathway!$AI:$AI,"YES", Pathway!$U:$U,"No", Pathway!$N:$N,">="&$B$1, Pathway!$N:$N,"<"&$C$1+1 ) ) -> 0 | N35: =SUM( COUNTIFS( Pathway!$D:$D,"Incident", Pathway!$G:$G,3, Pathway!$I:$I,"Closed", Pathway!$AJ:$AJ,"YES", Pathway!$U:$U,"No", Pathway!$N:$N,">="&$B$1, Pathway!$N:$N,"<"&$C$1+1 ), COUNTIFS( Pathway!$D:$D,"Incident", Pathway!$G:$G,3, Pathway!$I:$I,"Triaged", Pathway!$AJ:$AJ,"YES", Pathway!$U:$U,"No", Pathway!$N:$N,">="&$B$1, Pathway!$N:$N,"<"&$C$1+1 ) ) -> 0 | O35: =SUM( COUNTIFS( Pathway!$D:$D,"Incident", Pathway!$G:$G,3, Pathway!$I:$I,"Closed", Pathway!$AI:$AI,"NO", Pathway!$AJ:$AJ,"NO", Pathway!$U:$U,"No", Pathway!$N:$N,">="&$B$1, Pathway!$N:$N,"<"&$C$1+1 ), COUNTIFS( Pathway!$D:$D,"Incident", Pathway!$G:$G,3, Pathway!$I:$I,"Triaged", Pathway!$AI:$AI,"NO", Pathway!$AJ:$AJ,"NO", Pathway!$U:$U,"No", Pathway!$N:$N,">="&$B$1, Pathway!$N:$N,"<"&$C$1+1 ) ) -> 0 | P35: =SUM( COUNTIFS( Pathway!$D:$D,"Incident", Pathway!$G:$G,4, Pathway!$I:$I,"Closed", Pathway!$U:$U,"NO", Pathway!$N:$N,">="&$B$1, Pathway!$N:$N,"<"&$C$1+1 ), COUNTIFS( Pathway!$D:$D,"Incident", Pathway!$G:$G,4, Pathway!$I:$I,"Triaged", Pathway!$U:$U,"NO", Pathway!$N:$N,">="&$B$1, Pathway!$N:$N,"<"&$C$1+1 ) ) -> 3 | Q35: =SUM( COUNTIFS( Pathway!$D:$D,"Incident", Pathway!$G:$G,4, Pathway!$I:$I,"Closed", Pathway!$AI:$AI,"YES", Pathway!$U:$U,"No", Pathway!$N:$N,">="&$B$1, Pathway!$N:$N,"<"&$C$1+1 ), COUNTIFS( Pathway!$D:$D,"Incident", Pathway!$G:$G,4, Pathway!$I:$I,"Triaged", Pathway!$AI:$AI,"YES", Pathway!$U:$U,"No", Pathway!$N:$N,">="&$B$1, Pathway!$N:$N,"<"&$C$1+1 ) ) -> 0 | R35: =SUM( COUNTIFS( Pathway!$D:$D,"Incident", Pathway!$G:$G,4, Pathway!$I:$I,"Closed", Pathway!$AJ:$AJ,"YES", Pathway!$U:$U,"No", Pathway!$N:$N,">="&$B$1, Pathway!$N:$N,"<"&$C$1+1 ), COUNTIFS( Pathway!$D:$D,"Incident", Pathway!$G:$G,4, Pathway!$I:$I,"Triaged", Pathway!$AJ:$AJ,"YES", Pathway!$U:$U,"No", Pathway!$N:$N,">="&$B$1, Pathway!$N:$N,"<"&$C$1+1 ) ) -> 0 | S35: =SUM( COUNTIFS( Pathway!$D:$D,"Incident", Pathway!$G:$G,4, Pathway!$I:$I,"Closed", Pathway!$AI:$AI,"NO", Pathway!$AJ:$AJ,"NO", Pathway!$U:$U,"No", Pathway!$N:$N,">="&$B$1, Pathway!$N:$N,"<"&$C$1+1 ), COUNTIFS( Pathway!$D:$D,"Incident", Pathway!$G:$G,4, Pathway!$I:$I,"Triaged", Pathway!$AI:$AI,"NO", Pathway!$AJ:$AJ,"NO", Pathway!$U:$U,"No", Pathway!$N:$N,">="&$B$1, Pathway!$N:$N,"<"&$C$1+1 ) ) -> 0
